[
  {
    "id": "ocean-intro-core-001",
    "title": "【第1章｜基础知识】海洋热量收支表达可写为：______。",
    "year": 2026,
    "school": "中国海洋大学",
    "score": 5,
    "type": "填空题",
    "category": "第1章｜基础知识",
    "tags": [
      "物理海洋学",
      "物理海洋学导论",
      "第1章｜基础知识",
      "公式",
      "海洋热量收支表达"
    ],
    "options": [],
    "answer": "Q_net = Q_sw - Q_lw - Q_s - Q_l",
    "explanation": "海洋热量收支表达｜Q_net = Q_sw - Q_lw - Q_s - Q_l",
    "question": "【第1章｜基础知识】海洋热量收支表达可写为：______。"
  },
  {
    "id": "ocean-intro-core-002",
    "title": "【第1章｜基础知识】声速经验关系可写为：______。",
    "year": 2026,
    "school": "中国海洋大学",
    "score": 5,
    "type": "填空题",
    "category": "第1章｜基础知识",
    "tags": [
      "物理海洋学",
      "物理海洋学导论",
      "第1章｜基础知识",
      "公式",
      "声速经验关系"
    ],
    "options": [],
    "answer": "C = C(T, S, Z)",
    "explanation": "声速经验关系｜C = C(T, S, Z)",
    "question": "【第1章｜基础知识】声速经验关系可写为：______。"
  },
  {
    "id": "ocean-intro-core-003",
    "title": "【第1章｜基础知识】______：回声测深给出高精度原位深度，卫星高度计通过海表形状反演海底重力异常与地形。",
    "year": 2026,
    "school": "中国海洋大学",
    "score": 5,
    "type": "填空题",
    "category": "第1章｜基础知识",
    "tags": [
      "物理海洋学",
      "物理海洋学导论",
      "第1章｜基础知识",
      "方法",
      "海洋深度测量"
    ],
    "options": [],
    "answer": "海洋深度测量",
    "explanation": "海洋深度测量：回声测深给出高精度原位深度，卫星高度计通过海表形状反演海底重力异常与地形。",
    "question": "【第1章｜基础知识】______：回声测深给出高精度原位深度，卫星高度计通过海表形状反演海底重力异常与地形。"
  },
  {
    "id": "ocean-intro-core-004",
    "title": "【第1章｜基础知识】______：声学是几十米以下内部海洋信息的重要遥感手段。",
    "year": 2026,
    "school": "中国海洋大学",
    "score": 5,
    "type": "填空题",
    "category": "第1章｜基础知识",
    "tags": [
      "物理海洋学",
      "物理海洋学导论",
      "第1章｜基础知识",
      "方法",
      "海洋内部探测"
    ],
    "options": [],
    "answer": "海洋内部探测",
    "explanation": "海洋内部探测：声学是几十米以下内部海洋信息的重要遥感手段。",
    "question": "【第1章｜基础知识】______：声学是几十米以下内部海洋信息的重要遥感手段。"
  },
  {
    "id": "ocean-intro-core-005",
    "title": "【第1章｜基础知识】______说明海盆几何背景并不统一。",
    "year": 2026,
    "school": "中国海洋大学",
    "score": 5,
    "type": "填空题",
    "category": "第1章｜基础知识",
    "tags": [
      "物理海洋学",
      "物理海洋学导论",
      "第1章｜基础知识",
      "现象"
    ],
    "options": [],
    "answer": "四大洋与边缘海的面积和深度差异",
    "explanation": "四大洋与边缘海的面积和深度差异说明海盆几何背景并不统一。",
    "question": "【第1章｜基础知识】______说明海盆几何背景并不统一。"
  },
  {
    "id": "ocean-intro-core-006",
    "title": "【第1章｜基础知识】海洋是______。",
    "year": 2026,
    "school": "中国海洋大学",
    "score": 5,
    "type": "填空题",
    "category": "第1章｜基础知识",
    "tags": [
      "物理海洋学",
      "物理海洋学导论",
      "第1章｜基础知识",
      "现象"
    ],
    "options": [],
    "answer": "薄层流体，水平尺度常比垂向尺度大三个量级",
    "explanation": "海洋是薄层流体，水平尺度常比垂向尺度大三个量级。",
    "question": "【第1章｜基础知识】海洋是______。"
  },
  {
    "id": "ocean-intro-core-007",
    "title": "【第1章｜基础知识】______，因此海洋常被视为薄层流体。",
    "year": 2026,
    "school": "中国海洋大学",
    "score": 5,
    "type": "填空题",
    "category": "第1章｜基础知识",
    "tags": [
      "物理海洋学",
      "物理海洋学导论",
      "第1章｜基础知识",
      "课堂追问"
    ],
    "options": [],
    "answer": "教材强调海洋水平尺度远大于垂向尺度",
    "explanation": "教材强调海洋水平尺度远大于垂向尺度，因此海洋常被视为薄层流体。",
    "question": "【第1章｜基础知识】______，因此海洋常被视为薄层流体。"
  },
  {
    "id": "ocean-intro-core-008",
    "title": "【第1章｜基础知识】决定海水动力状态的核心状态量常概括为______。",
    "year": 2026,
    "school": "中国海洋大学",
    "score": 5,
    "type": "填空题",
    "category": "第1章｜基础知识",
    "tags": [
      "物理海洋学",
      "物理海洋学导论",
      "第1章｜基础知识",
      "课堂追问"
    ],
    "options": [],
    "answer": "温度、盐度和密度",
    "explanation": "决定海水动力状态的核心状态量常概括为温度、盐度和密度。",
    "question": "【第1章｜基础知识】决定海水动力状态的核心状态量常概括为______。"
  },
  {
    "id": "ocean-intro-core-009",
    "title": "【第1章｜基础知识】海洋热量收支中，与蒸发密切相关的冷却项是______。",
    "year": 2026,
    "school": "中国海洋大学",
    "score": 5,
    "type": "填空题",
    "category": "第1章｜基础知识",
    "tags": [
      "物理海洋学",
      "物理海洋学导论",
      "第1章｜基础知识",
      "课堂追问"
    ],
    "options": [],
    "answer": "潜热通量",
    "explanation": "海洋热量收支中，与蒸发密切相关的冷却项是潜热通量。",
    "question": "【第1章｜基础知识】海洋热量收支中，与蒸发密切相关的冷却项是______。"
  },
  {
    "id": "ocean-intro-core-010",
    "title": "【第1章｜基础知识】教材用于高精度原位测深的主要方法是______。",
    "year": 2026,
    "school": "中国海洋大学",
    "score": 5,
    "type": "填空题",
    "category": "第1章｜基础知识",
    "tags": [
      "物理海洋学",
      "物理海洋学导论",
      "第1章｜基础知识",
      "课堂追问"
    ],
    "options": [],
    "answer": "船载声学回声 / 回声测深",
    "explanation": "教材用于高精度原位测深的主要方法是船载声学回声 / 回声测深。",
    "question": "【第1章｜基础知识】教材用于高精度原位测深的主要方法是______。"
  },
  {
    "id": "ocean-intro-core-011",
    "title": "【第1章｜基础知识】海洋内部远距离传递信息的便利手段是______。",
    "year": 2026,
    "school": "中国海洋大学",
    "score": 5,
    "type": "填空题",
    "category": "第1章｜基础知识",
    "tags": [
      "物理海洋学",
      "物理海洋学导论",
      "第1章｜基础知识",
      "课堂追问"
    ],
    "options": [],
    "answer": "声音 / 声学信号",
    "explanation": "海洋内部远距离传递信息的便利手段是声音 / 声学信号。",
    "question": "【第1章｜基础知识】海洋内部远距离传递信息的便利手段是______。"
  },
  {
    "id": "ocean-intro-core-012",
    "title": "【第1章｜基础知识】比原位温度更适合比较不同深度水体热状态的量是______。",
    "year": 2026,
    "school": "中国海洋大学",
    "score": 5,
    "type": "填空题",
    "category": "第1章｜基础知识",
    "tags": [
      "物理海洋学",
      "物理海洋学导论",
      "第1章｜基础知识",
      "课堂追问"
    ],
    "options": [],
    "answer": "位温",
    "explanation": "比原位温度更适合比较不同深度水体热状态的量是位温。",
    "question": "【第1章｜基础知识】比原位温度更适合比较不同深度水体热状态的量是______。"
  },
  {
    "id": "ocean-intro-core-013",
    "title": "【第2章｜物理海洋方程组】全导数 / 物质导数可写为：______。",
    "year": 2026,
    "school": "中国海洋大学",
    "score": 5,
    "type": "填空题",
    "category": "第2章｜物理海洋方程组",
    "tags": [
      "物理海洋学",
      "物理海洋学导论",
      "第2章｜物理海洋方程组",
      "公式",
      "全导数 / 物质导数"
    ],
    "options": [],
    "answer": "D/Dt = ∂/∂t + u∂/∂x + v∂/∂y + w∂/∂z",
    "explanation": "全导数 / 物质导数｜D/Dt = ∂/∂t + u∂/∂x + v∂/∂y + w∂/∂z",
    "question": "【第2章｜物理海洋方程组】全导数 / 物质导数可写为：______。"
  },
  {
    "id": "ocean-intro-core-014",
    "title": "【第2章｜物理海洋方程组】连续性方程可写为：______。",
    "year": 2026,
    "school": "中国海洋大学",
    "score": 5,
    "type": "填空题",
    "category": "第2章｜物理海洋方程组",
    "tags": [
      "物理海洋学",
      "物理海洋学导论",
      "第2章｜物理海洋方程组",
      "公式",
      "连续性方程"
    ],
    "options": [],
    "answer": "∇·V = 0（不可压近似）",
    "explanation": "连续性方程｜∇·V = 0（不可压近似）",
    "question": "【第2章｜物理海洋方程组】连续性方程可写为：______。"
  },
  {
    "id": "ocean-intro-core-015",
    "title": "【第2章｜物理海洋方程组】______：教材用陆架海区水量收支示例说明守恒律如何先从积分形式工作。",
    "year": 2026,
    "school": "中国海洋大学",
    "score": 5,
    "type": "填空题",
    "category": "第2章｜物理海洋方程组",
    "tags": [
      "物理海洋学",
      "物理海洋学导论",
      "第2章｜物理海洋方程组",
      "方法",
      "箱式模型"
    ],
    "options": [],
    "answer": "箱式模型",
    "explanation": "箱式模型：教材用陆架海区水量收支示例说明守恒律如何先从积分形式工作。",
    "question": "【第2章｜物理海洋方程组】______：教材用陆架海区水量收支示例说明守恒律如何先从积分形式工作。"
  },
  {
    "id": "ocean-intro-core-016",
    "title": "【第2章｜物理海洋方程组】______：把海洋分成固定控制体，研究流体穿越边界与场量变化。",
    "year": 2026,
    "school": "中国海洋大学",
    "score": 5,
    "type": "填空题",
    "category": "第2章｜物理海洋方程组",
    "tags": [
      "物理海洋学",
      "物理海洋学导论",
      "第2章｜物理海洋方程组",
      "方法",
      "欧拉观点"
    ],
    "options": [],
    "answer": "欧拉观点",
    "explanation": "欧拉观点：把海洋分成固定控制体，研究流体穿越边界与场量变化。",
    "question": "【第2章｜物理海洋方程组】______：把海洋分成固定控制体，研究流体穿越边界与场量变化。"
  },
  {
    "id": "ocean-intro-core-017",
    "title": "【第2章｜物理海洋方程组】______使解析求解在大多数情况下困难。",
    "year": 2026,
    "school": "中国海洋大学",
    "score": 5,
    "type": "填空题",
    "category": "第2章｜物理海洋方程组",
    "tags": [
      "物理海洋学",
      "物理海洋学导论",
      "第2章｜物理海洋方程组",
      "现象"
    ],
    "options": [],
    "answer": "海洋方程组中的非线性平流项",
    "explanation": "海洋方程组中的非线性平流项，使解析求解在大多数情况下困难。",
    "question": "【第2章｜物理海洋方程组】______使解析求解在大多数情况下困难。"
  },
  {
    "id": "ocean-intro-core-018",
    "title": "【第2章｜物理海洋方程组】湍流参数化反映了______。",
    "year": 2026,
    "school": "中国海洋大学",
    "score": 5,
    "type": "填空题",
    "category": "第2章｜物理海洋方程组",
    "tags": [
      "物理海洋学",
      "物理海洋学导论",
      "第2章｜物理海洋方程组",
      "现象"
    ],
    "options": [],
    "answer": "海洋中大量次网格混合过程",
    "explanation": "湍流参数化反映了海洋中大量次网格混合过程。",
    "question": "【第2章｜物理海洋方程组】湍流参数化反映了______。"
  },
  {
    "id": "ocean-intro-core-019",
    "title": "【第2章｜物理海洋方程组】把离散分子流体看作连续场的基本前提叫______。",
    "year": 2026,
    "school": "中国海洋大学",
    "score": 5,
    "type": "填空题",
    "category": "第2章｜物理海洋方程组",
    "tags": [
      "物理海洋学",
      "物理海洋学导论",
      "第2章｜物理海洋方程组",
      "课堂追问"
    ],
    "options": [],
    "answer": "连续介质假设",
    "explanation": "把离散分子流体看作连续场的基本前提叫连续介质假设。",
    "question": "【第2章｜物理海洋方程组】把离散分子流体看作连续场的基本前提叫______。"
  },
  {
    "id": "ocean-intro-core-020",
    "title": "【第2章｜物理海洋方程组】欧拉观点下，变量随流体质点变化的导数常写成______。",
    "year": 2026,
    "school": "中国海洋大学",
    "score": 5,
    "type": "填空题",
    "category": "第2章｜物理海洋方程组",
    "tags": [
      "物理海洋学",
      "物理海洋学导论",
      "第2章｜物理海洋方程组",
      "课堂追问"
    ],
    "options": [],
    "answer": "全 / 物质导数",
    "explanation": "欧拉观点下，变量随流体质点变化的导数常写成全 / 物质导数。",
    "question": "【第2章｜物理海洋方程组】欧拉观点下，变量随流体质点变化的导数常写成______。"
  },
  {
    "id": "ocean-intro-core-021",
    "title": "【第2章｜物理海洋方程组】不可压海水最常用的连续性方程写成______。",
    "year": 2026,
    "school": "中国海洋大学",
    "score": 5,
    "type": "填空题",
    "category": "第2章｜物理海洋方程组",
    "tags": [
      "物理海洋学",
      "物理海洋学导论",
      "第2章｜物理海洋方程组",
      "课堂追问"
    ],
    "options": [],
    "answer": "速度散度等于零",
    "explanation": "不可压海水最常用的连续性方程写成速度散度等于零。",
    "question": "【第2章｜物理海洋方程组】不可压海水最常用的连续性方程写成______。"
  },
  {
    "id": "ocean-intro-core-022",
    "title": "【第2章｜物理海洋方程组】将温盐结构与动力过程耦合起来的关系式是______。",
    "year": 2026,
    "school": "中国海洋大学",
    "score": 5,
    "type": "填空题",
    "category": "第2章｜物理海洋方程组",
    "tags": [
      "物理海洋学",
      "物理海洋学导论",
      "第2章｜物理海洋方程组",
      "课堂追问"
    ],
    "options": [],
    "answer": "海水状态方程",
    "explanation": "将温盐结构与动力过程耦合起来的关系式是海水状态方程。",
    "question": "【第2章｜物理海洋方程组】将温盐结构与动力过程耦合起来的关系式是______。"
  },
  {
    "id": "ocean-intro-core-023",
    "title": "【第2章｜物理海洋方程组】判断不同海洋过程该保留哪些方程项的方法叫______。",
    "year": 2026,
    "school": "中国海洋大学",
    "score": 5,
    "type": "填空题",
    "category": "第2章｜物理海洋方程组",
    "tags": [
      "物理海洋学",
      "物理海洋学导论",
      "第2章｜物理海洋方程组",
      "课堂追问"
    ],
    "options": [],
    "answer": "尺度分析",
    "explanation": "判断不同海洋过程该保留哪些方程项的方法叫尺度分析。",
    "question": "【第2章｜物理海洋方程组】判断不同海洋过程该保留哪些方程项的方法叫______。"
  },
  {
    "id": "ocean-intro-core-024",
    "title": "【第2章｜物理海洋方程组】把速度场重写为更易诊断形式时常用到______。",
    "year": 2026,
    "school": "中国海洋大学",
    "score": 5,
    "type": "填空题",
    "category": "第2章｜物理海洋方程组",
    "tags": [
      "物理海洋学",
      "物理海洋学导论",
      "第2章｜物理海洋方程组",
      "课堂追问"
    ],
    "options": [],
    "answer": "流函数和涡度",
    "explanation": "把速度场重写为更易诊断形式时，常用到流函数和涡度。",
    "question": "【第2章｜物理海洋方程组】把速度场重写为更易诊断形式时常用到______。"
  },
  {
    "id": "ocean-intro-core-025",
    "title": "【第3章｜潮汐】潮汐强迫可由______展开表示。",
    "year": 2026,
    "school": "中国海洋大学",
    "score": 5,
    "type": "填空题",
    "category": "第3章｜潮汐",
    "tags": [
      "物理海洋学",
      "物理海洋学导论",
      "第3章｜潮汐",
      "公式",
      "引潮势"
    ],
    "options": [],
    "answer": "月、日引潮势",
    "explanation": "引潮势｜潮汐强迫可由月、日引潮势展开表示",
    "question": "【第3章｜潮汐】潮汐强迫可由______展开表示。"
  },
  {
    "id": "ocean-intro-core-026",
    "title": "【第3章｜潮汐】调和表示可写为：______。",
    "year": 2026,
    "school": "中国海洋大学",
    "score": 5,
    "type": "填空题",
    "category": "第3章｜潮汐",
    "tags": [
      "物理海洋学",
      "物理海洋学导论",
      "第3章｜潮汐",
      "公式",
      "调和表示"
    ],
    "options": [],
    "answer": "η(t) = Σ H_i cos(ω_i t + φ_i)",
    "explanation": "调和表示｜η(t) = Σ H_i cos(ω_i t + φ_i)",
    "question": "【第3章｜潮汐】调和表示可写为：______。"
  },
  {
    "id": "ocean-intro-core-027",
    "title": "【第3章｜潮汐】______：验潮站获得长时间潮位序列，卫星高度计补充海盆尺度结构。",
    "year": 2026,
    "school": "中国海洋大学",
    "score": 5,
    "type": "填空题",
    "category": "第3章｜潮汐",
    "tags": [
      "物理海洋学",
      "物理海洋学导论",
      "第3章｜潮汐",
      "方法",
      "潮汐观测"
    ],
    "options": [],
    "answer": "潮汐观测",
    "explanation": "潮汐观测：验潮站获得长时间潮位序列，卫星高度计补充海盆尺度结构。",
    "question": "【第3章｜潮汐】______：验潮站获得长时间潮位序列，卫星高度计补充海盆尺度结构。"
  },
  {
    "id": "ocean-intro-core-028",
    "title": "【第3章｜潮汐】______：通过分潮常数做调和分析与报潮。",
    "year": 2026,
    "school": "中国海洋大学",
    "score": 5,
    "type": "填空题",
    "category": "第3章｜潮汐",
    "tags": [
      "物理海洋学",
      "物理海洋学导论",
      "第3章｜潮汐",
      "方法",
      "潮汐预报"
    ],
    "options": [],
    "answer": "潮汐预报",
    "explanation": "潮汐预报：通过分潮常数做调和分析与报潮。",
    "question": "【第3章｜潮汐】______：通过分潮常数做调和分析与报潮。"
  },
  {
    "id": "ocean-intro-core-029",
    "title": "【第3章｜潮汐】______体现海区响应差别。",
    "year": 2026,
    "school": "中国海洋大学",
    "score": 5,
    "type": "填空题",
    "category": "第3章｜潮汐",
    "tags": [
      "物理海洋学",
      "物理海洋学导论",
      "第3章｜潮汐",
      "现象"
    ],
    "options": [],
    "answer": "全日潮、半日潮和混合潮",
    "explanation": "全日潮、半日潮和混合潮体现海区响应差别。",
    "question": "【第3章｜潮汐】______体现海区响应差别。"
  },
  {
    "id": "ocean-intro-core-030",
    "title": "【第3章｜潮汐】______体现轨道几何和地球自转的调制。",
    "year": 2026,
    "school": "中国海洋大学",
    "score": 5,
    "type": "填空题",
    "category": "第3章｜潮汐",
    "tags": [
      "物理海洋学",
      "物理海洋学导论",
      "第3章｜潮汐",
      "现象"
    ],
    "options": [],
    "answer": "潮汐不等现象",
    "explanation": "潮汐不等现象体现轨道几何和地球自转的调制。",
    "question": "【第3章｜潮汐】______体现轨道几何和地球自转的调制。"
  },
  {
    "id": "ocean-intro-core-031",
    "title": "【第3章｜潮汐】由日、月对海水的周期性引力作用所引起的海面起伏称为______。",
    "year": 2026,
    "school": "中国海洋大学",
    "score": 5,
    "type": "填空题",
    "category": "第3章｜潮汐",
    "tags": [
      "物理海洋学",
      "物理海洋学导论",
      "第3章｜潮汐",
      "课堂追问"
    ],
    "options": [],
    "answer": "潮汐",
    "explanation": "由日、月对海水的周期性引力作用所引起的海面起伏称为潮汐。",
    "question": "【第3章｜潮汐】由日、月对海水的周期性引力作用所引起的海面起伏称为______。"
  },
  {
    "id": "ocean-intro-core-032",
    "title": "【第3章｜潮汐】与海面起伏相伴随的海水水平运动称为______。",
    "year": 2026,
    "school": "中国海洋大学",
    "score": 5,
    "type": "填空题",
    "category": "第3章｜潮汐",
    "tags": [
      "物理海洋学",
      "物理海洋学导论",
      "第3章｜潮汐",
      "课堂追问"
    ],
    "options": [],
    "answer": "潮流",
    "explanation": "与海面起伏相伴随的海水水平运动称为潮流。",
    "question": "【第3章｜潮汐】与海面起伏相伴随的海水水平运动称为______。"
  },
  {
    "id": "ocean-intro-core-033",
    "title": "【第3章｜潮汐】将复杂潮位分解成多个分潮叠加的方法叫______。",
    "year": 2026,
    "school": "中国海洋大学",
    "score": 5,
    "type": "填空题",
    "category": "第3章｜潮汐",
    "tags": [
      "物理海洋学",
      "物理海洋学导论",
      "第3章｜潮汐",
      "课堂追问"
    ],
    "options": [],
    "answer": "潮汐调和分析",
    "explanation": "将复杂潮位分解成多个分潮叠加的方法叫潮汐调和分析。",
    "question": "【第3章｜潮汐】将复杂潮位分解成多个分潮叠加的方法叫______。"
  },
  {
    "id": "ocean-intro-core-034",
    "title": "【第3章｜潮汐】理想条件下描述海洋对引潮势响应的理论称为______。",
    "year": 2026,
    "school": "中国海洋大学",
    "score": 5,
    "type": "填空题",
    "category": "第3章｜潮汐",
    "tags": [
      "物理海洋学",
      "物理海洋学导论",
      "第3章｜潮汐",
      "课堂追问"
    ],
    "options": [],
    "answer": "平衡潮理论",
    "explanation": "理想条件下描述海洋对引潮势响应的理论称为平衡潮理论。",
    "question": "【第3章｜潮汐】理想条件下描述海洋对引潮势响应的理论称为______。"
  },
  {
    "id": "ocean-intro-core-035",
    "title": "【第3章｜潮汐】潮汐在海盆中的传播形式可称为______。",
    "year": 2026,
    "school": "中国海洋大学",
    "score": 5,
    "type": "填空题",
    "category": "第3章｜潮汐",
    "tags": [
      "物理海洋学",
      "物理海洋学导论",
      "第3章｜潮汐",
      "课堂追问"
    ],
    "options": [],
    "answer": "潮波",
    "explanation": "潮汐在海盆中的传播形式可称为潮波。",
    "question": "【第3章｜潮汐】潮汐在海盆中的传播形式可称为______。"
  },
  {
    "id": "ocean-intro-core-036",
    "title": "【第3章｜潮汐】教材中对我国近海潮汐的应用讲解，最能体现______。",
    "year": 2026,
    "school": "中国海洋大学",
    "score": 5,
    "type": "填空题",
    "category": "第3章｜潮汐",
    "tags": [
      "物理海洋学",
      "物理海洋学导论",
      "第3章｜潮汐",
      "课堂追问"
    ],
    "options": [],
    "answer": "海盆和地形对天文强迫的改造",
    "explanation": "教材中对我国近海潮汐的应用讲解，最能体现海盆和地形对天文强迫的改造。",
    "question": "【第3章｜潮汐】教材中对我国近海潮汐的应用讲解，最能体现______。"
  },
  {
    "id": "ocean-intro-core-037",
    "title": "【第4章｜地转流】静力平衡可写为：______。",
    "year": 2026,
    "school": "中国海洋大学",
    "score": 5,
    "type": "填空题",
    "category": "第4章｜地转流",
    "tags": [
      "物理海洋学",
      "物理海洋学导论",
      "第4章｜地转流",
      "公式",
      "静力平衡"
    ],
    "options": [],
    "answer": "∂p/∂z = -ρg",
    "explanation": "静力平衡｜∂p/∂z = -ρg",
    "question": "【第4章｜地转流】静力平衡可写为：______。"
  },
  {
    "id": "ocean-intro-core-038",
    "title": "【第4章｜地转流】地转平衡可写为：______。",
    "year": 2026,
    "school": "中国海洋大学",
    "score": 5,
    "type": "填空题",
    "category": "第4章｜地转流",
    "tags": [
      "物理海洋学",
      "物理海洋学导论",
      "第4章｜地转流",
      "公式",
      "地转平衡"
    ],
    "options": [],
    "answer": "fv = (1/ρ)∂p/∂x，fu = -(1/ρ)∂p/∂y",
    "explanation": "地转平衡｜fv = (1/ρ)∂p/∂x，fu = -(1/ρ)∂p/∂y",
    "question": "【第4章｜地转流】地转平衡可写为：______。"
  },
  {
    "id": "ocean-intro-core-039",
    "title": "【第4章｜地转流】______：由海面高度异常或绝对动力地形反演表层地转流。",
    "year": 2026,
    "school": "中国海洋大学",
    "score": 5,
    "type": "填空题",
    "category": "第4章｜地转流",
    "tags": [
      "物理海洋学",
      "物理海洋学导论",
      "第4章｜地转流",
      "方法",
      "卫星高度计"
    ],
    "options": [],
    "answer": "卫星高度计",
    "explanation": "卫星高度计：由海面高度异常或绝对动力地形反演表层地转流。",
    "question": "【第4章｜地转流】______：由海面高度异常或绝对动力地形反演表层地转流。"
  },
  {
    "id": "ocean-intro-core-040",
    "title": "【第4章｜地转流】______：计算密度、比容异常和动力高度，进而估算相对地转流。",
    "year": 2026,
    "school": "中国海洋大学",
    "score": 5,
    "type": "填空题",
    "category": "第4章｜地转流",
    "tags": [
      "物理海洋学",
      "物理海洋学导论",
      "第4章｜地转流",
      "方法",
      "CTD / 温盐剖面"
    ],
    "options": [],
    "answer": "CTD / 温盐剖面",
    "explanation": "CTD / 温盐剖面：计算密度、比容异常和动力高度，进而估算相对地转流。",
    "question": "【第4章｜地转流】______：计算密度、比容异常和动力高度，进而估算相对地转流。"
  },
  {
    "id": "ocean-intro-core-041",
    "title": "【第4章｜地转流】______，卫星高度计因此能看见大尺度环流骨架。",
    "year": 2026,
    "school": "中国海洋大学",
    "score": 5,
    "type": "填空题",
    "category": "第4章｜地转流",
    "tags": [
      "物理海洋学",
      "物理海洋学导论",
      "第4章｜地转流",
      "现象"
    ],
    "options": [],
    "answer": "海表高度梯度对应表层地转流",
    "explanation": "海表高度梯度对应表层地转流，卫星高度计因此能看见大尺度环流骨架。",
    "question": "【第4章｜地转流】______，卫星高度计因此能看见大尺度环流骨架。"
  },
  {
    "id": "ocean-intro-core-042",
    "title": "【第4章｜地转流】水平密度梯度控制垂向剪切，是______。",
    "year": 2026,
    "school": "中国海洋大学",
    "score": 5,
    "type": "填空题",
    "category": "第4章｜地转流",
    "tags": [
      "物理海洋学",
      "物理海洋学导论",
      "第4章｜地转流",
      "现象"
    ],
    "options": [],
    "answer": "西边界流和中尺度涡旋的重要结构基础",
    "explanation": "水平密度梯度控制垂向剪切，是西边界流和中尺度涡旋的重要结构基础。",
    "question": "【第4章｜地转流】水平密度梯度控制垂向剪切，是______。"
  },
  {
    "id": "ocean-intro-core-043",
    "title": "【第4章｜地转流】在大尺度海洋中，垂向压强梯度与重力平衡称为______。",
    "year": 2026,
    "school": "中国海洋大学",
    "score": 5,
    "type": "填空题",
    "category": "第4章｜地转流",
    "tags": [
      "物理海洋学",
      "物理海洋学导论",
      "第4章｜地转流",
      "课堂追问"
    ],
    "options": [],
    "answer": "静力平衡",
    "explanation": "在大尺度海洋中，垂向压强梯度与重力平衡称为静力平衡。",
    "question": "【第4章｜地转流】在大尺度海洋中，垂向压强梯度与重力平衡称为______。"
  },
  {
    "id": "ocean-intro-core-044",
    "title": "【第4章｜地转流】______，压强梯度力与科氏力平衡形成地转流。",
    "year": 2026,
    "school": "中国海洋大学",
    "score": 5,
    "type": "填空题",
    "category": "第4章｜地转流",
    "tags": [
      "物理海洋学",
      "物理海洋学导论",
      "第4章｜地转流",
      "课堂追问"
    ],
    "options": [],
    "answer": "大尺度水平流中",
    "explanation": "大尺度水平流中，压强梯度力与科氏力平衡形成地转流。",
    "question": "【第4章｜地转流】______，压强梯度力与科氏力平衡形成地转流。"
  },
  {
    "id": "ocean-intro-core-045",
    "title": "【第4章｜地转流】把水平密度梯度与地转流垂向切变联系起来的关系叫______。",
    "year": 2026,
    "school": "中国海洋大学",
    "score": 5,
    "type": "填空题",
    "category": "第4章｜地转流",
    "tags": [
      "物理海洋学",
      "物理海洋学导论",
      "第4章｜地转流",
      "课堂追问"
    ],
    "options": [],
    "answer": "热成风关系",
    "explanation": "把水平密度梯度与地转流垂向切变联系起来的关系叫热成风关系。",
    "question": "【第4章｜地转流】把水平密度梯度与地转流垂向切变联系起来的关系叫______。"
  },
  {
    "id": "ocean-intro-core-046",
    "title": "【第4章｜地转流】利用海表面几何信息反推表层地转流的重要观测手段是______。",
    "year": 2026,
    "school": "中国海洋大学",
    "score": 5,
    "type": "填空题",
    "category": "第4章｜地转流",
    "tags": [
      "物理海洋学",
      "物理海洋学导论",
      "第4章｜地转流",
      "课堂追问"
    ],
    "options": [],
    "answer": "卫星高度计",
    "explanation": "利用海表面几何信息反推表层地转流的重要观测手段是卫星高度计。",
    "question": "【第4章｜地转流】利用海表面几何信息反推表层地转流的重要观测手段是______。"
  },
  {
    "id": "ocean-intro-core-047",
    "title": "【第4章｜地转流】______，首先要把温盐转成密度结构。",
    "year": 2026,
    "school": "中国海洋大学",
    "score": 5,
    "type": "填空题",
    "category": "第4章｜地转流",
    "tags": [
      "物理海洋学",
      "物理海洋学导论",
      "第4章｜地转流",
      "课堂追问"
    ],
    "options": [],
    "answer": "由温盐资料恢复内部地转流时",
    "explanation": "由温盐资料恢复内部地转流时，首先要把温盐转成密度结构。",
    "question": "【第4章｜地转流】______，首先要把温盐转成密度结构。"
  },
  {
    "id": "ocean-intro-core-048",
    "title": "【第4章｜地转流】不依赖静止参考面的绝对流估计教材中提到的方法是______。",
    "year": 2026,
    "school": "中国海洋大学",
    "score": 5,
    "type": "填空题",
    "category": "第4章｜地转流",
    "tags": [
      "物理海洋学",
      "物理海洋学导论",
      "第4章｜地转流",
      "课堂追问"
    ],
    "options": [],
    "answer": "P矢量 / P 矢量方法",
    "explanation": "不依赖静止参考面的绝对流估计教材中提到的方法是P矢量 / P 矢量方法。",
    "question": "【第4章｜地转流】不依赖静止参考面的绝对流估计教材中提到的方法是______。"
  },
  {
    "id": "ocean-intro-core-049",
    "title": "【第5章｜埃克曼流与惯性流】海表风应力可写为：______。",
    "year": 2026,
    "school": "中国海洋大学",
    "score": 5,
    "type": "填空题",
    "category": "第5章｜埃克曼流与惯性流",
    "tags": [
      "物理海洋学",
      "物理海洋学导论",
      "第5章｜埃克曼流与惯性流",
      "公式",
      "海表风应力"
    ],
    "options": [],
    "answer": "τ = ρ_a C_D |U| U",
    "explanation": "海表风应力｜τ = ρ_a C_D |U| U",
    "question": "【第5章｜埃克曼流与惯性流】海表风应力可写为：______。"
  },
  {
    "id": "ocean-intro-core-050",
    "title": "【第5章｜埃克曼流与惯性流】埃克曼输运可写为：______。",
    "year": 2026,
    "school": "中国海洋大学",
    "score": 5,
    "type": "填空题",
    "category": "第5章｜埃克曼流与惯性流",
    "tags": [
      "物理海洋学",
      "物理海洋学导论",
      "第5章｜埃克曼流与惯性流",
      "公式",
      "埃克曼输运"
    ],
    "options": [],
    "answer": "M_E = τ / (ρ f)",
    "explanation": "埃克曼输运｜M_E = τ / (ρ f)",
    "question": "【第5章｜埃克曼流与惯性流】埃克曼输运可写为：______。"
  },
  {
    "id": "ocean-intro-core-051",
    "title": "【第5章｜埃克曼流与惯性流】______：由海面 10 m 风速和阻力系数转换为动量通量。",
    "year": 2026,
    "school": "中国海洋大学",
    "score": 5,
    "type": "填空题",
    "category": "第5章｜埃克曼流与惯性流",
    "tags": [
      "物理海洋学",
      "物理海洋学导论",
      "第5章｜埃克曼流与惯性流",
      "方法",
      "风应力估算"
    ],
    "options": [],
    "answer": "风应力估算",
    "explanation": "风应力估算：由海面 10 m 风速和阻力系数转换为动量通量。",
    "question": "【第5章｜埃克曼流与惯性流】______：由海面 10 m 风速和阻力系数转换为动量通量。"
  },
  {
    "id": "ocean-intro-core-052",
    "title": "【第5章｜埃克曼流与惯性流】______：漂流浮标、流速剖面和海表响应可检验埃克曼理论。",
    "year": 2026,
    "school": "中国海洋大学",
    "score": 5,
    "type": "填空题",
    "category": "第5章｜埃克曼流与惯性流",
    "tags": [
      "物理海洋学",
      "物理海洋学导论",
      "第5章｜埃克曼流与惯性流",
      "方法",
      "海表观测"
    ],
    "options": [],
    "answer": "海表观测",
    "explanation": "海表观测：漂流浮标、流速剖面和海表响应可检验埃克曼理论。",
    "question": "【第5章｜埃克曼流与惯性流】______：漂流浮标、流速剖面和海表响应可检验埃克曼理论。"
  },
  {
    "id": "ocean-intro-core-053",
    "title": "【第5章｜埃克曼流与惯性流】______说明表层以下流向会逐渐旋转并衰减。",
    "year": 2026,
    "school": "中国海洋大学",
    "score": 5,
    "type": "填空题",
    "category": "第5章｜埃克曼流与惯性流",
    "tags": [
      "物理海洋学",
      "物理海洋学导论",
      "第5章｜埃克曼流与惯性流",
      "现象"
    ],
    "options": [],
    "answer": "埃克曼螺旋",
    "explanation": "埃克曼螺旋说明表层以下流向会逐渐旋转并衰减。",
    "question": "【第5章｜埃克曼流与惯性流】______说明表层以下流向会逐渐旋转并衰减。"
  },
  {
    "id": "ocean-intro-core-054",
    "title": "【第5章｜埃克曼流与惯性流】沿岸上升流可带来______。",
    "year": 2026,
    "school": "中国海洋大学",
    "score": 5,
    "type": "填空题",
    "category": "第5章｜埃克曼流与惯性流",
    "tags": [
      "物理海洋学",
      "物理海洋学导论",
      "第5章｜埃克曼流与惯性流",
      "现象"
    ],
    "options": [],
    "answer": "低温高营养海水",
    "explanation": "沿岸上升流可带来低温高营养海水。",
    "question": "【第5章｜埃克曼流与惯性流】沿岸上升流可带来______。"
  },
  {
    "id": "ocean-intro-core-055",
    "title": "【第5章｜埃克曼流与惯性流】风把动量传给海洋上层的直接边界量叫______。",
    "year": 2026,
    "school": "中国海洋大学",
    "score": 5,
    "type": "填空题",
    "category": "第5章｜埃克曼流与惯性流",
    "tags": [
      "物理海洋学",
      "物理海洋学导论",
      "第5章｜埃克曼流与惯性流",
      "课堂追问"
    ],
    "options": [],
    "answer": "海表风应力",
    "explanation": "风把动量传给海洋上层的直接边界量叫海表风应力。",
    "question": "【第5章｜埃克曼流与惯性流】风把动量传给海洋上层的直接边界量叫______。"
  },
  {
    "id": "ocean-intro-core-056",
    "title": "【第5章｜埃克曼流与惯性流】经典埃克曼层由______共同控制。",
    "year": 2026,
    "school": "中国海洋大学",
    "score": 5,
    "type": "填空题",
    "category": "第5章｜埃克曼流与惯性流",
    "tags": [
      "物理海洋学",
      "物理海洋学导论",
      "第5章｜埃克曼流与惯性流",
      "课堂追问"
    ],
    "options": [],
    "answer": "风应力、科氏力和垂向摩擦",
    "explanation": "经典埃克曼层由风应力、科氏力和垂向摩擦共同控制。",
    "question": "【第5章｜埃克曼流与惯性流】经典埃克曼层由______共同控制。"
  },
  {
    "id": "ocean-intro-core-057",
    "title": "【第5章｜埃克曼流与惯性流】比表层偏角更能代表______。",
    "year": 2026,
    "school": "中国海洋大学",
    "score": 5,
    "type": "填空题",
    "category": "第5章｜埃克曼流与惯性流",
    "tags": [
      "物理海洋学",
      "物理海洋学导论",
      "第5章｜埃克曼流与惯性流",
      "课堂追问"
    ],
    "options": [],
    "answer": "风生边界层整体效应的量是埃克曼质量输运",
    "explanation": "比表层偏角更能代表风生边界层整体效应的量是埃克曼质量输运。",
    "question": "【第5章｜埃克曼流与惯性流】比表层偏角更能代表______。"
  },
  {
    "id": "ocean-intro-core-058",
    "title": "【第5章｜埃克曼流与惯性流】______使表层水离岸输运并诱发冷水上涌的现象称为沿岸上升流。",
    "year": 2026,
    "school": "中国海洋大学",
    "score": 5,
    "type": "填空题",
    "category": "第5章｜埃克曼流与惯性流",
    "tags": [
      "物理海洋学",
      "物理海洋学导论",
      "第5章｜埃克曼流与惯性流",
      "课堂追问"
    ],
    "options": [],
    "answer": "沿岸风",
    "explanation": "沿岸风使表层水离岸输运并诱发冷水上涌的现象称为沿岸上升流。",
    "question": "【第5章｜埃克曼流与惯性流】______使表层水离岸输运并诱发冷水上涌的现象称为沿岸上升流。"
  },
  {
    "id": "ocean-intro-core-059",
    "title": "【第5章｜埃克曼流与惯性流】风应力旋度引起的垂向抽吸效应称为______。",
    "year": 2026,
    "school": "中国海洋大学",
    "score": 5,
    "type": "填空题",
    "category": "第5章｜埃克曼流与惯性流",
    "tags": [
      "物理海洋学",
      "物理海洋学导论",
      "第5章｜埃克曼流与惯性流",
      "课堂追问"
    ],
    "options": [],
    "answer": "埃克曼抽吸",
    "explanation": "风应力旋度引起的垂向抽吸效应称为埃克曼抽吸。",
    "question": "【第5章｜埃克曼流与惯性流】风应力旋度引起的垂向抽吸效应称为______。"
  },
  {
    "id": "ocean-intro-core-060",
    "title": "【第5章｜埃克曼流与惯性流】外力撤去后海水在科氏力控制下做的自由振荡称为______。",
    "year": 2026,
    "school": "中国海洋大学",
    "score": 5,
    "type": "填空题",
    "category": "第5章｜埃克曼流与惯性流",
    "tags": [
      "物理海洋学",
      "物理海洋学导论",
      "第5章｜埃克曼流与惯性流",
      "课堂追问"
    ],
    "options": [],
    "answer": "惯性流",
    "explanation": "外力撤去后海水在科氏力控制下做的自由振荡称为惯性流。",
    "question": "【第5章｜埃克曼流与惯性流】外力撤去后海水在科氏力控制下做的自由振荡称为______。"
  },
  {
    "id": "ocean-intro-core-061",
    "title": "【第6章｜风生大洋环流】斯韦德鲁普平衡可写为：______。",
    "year": 2026,
    "school": "中国海洋大学",
    "score": 5,
    "type": "填空题",
    "category": "第6章｜风生大洋环流",
    "tags": [
      "物理海洋学",
      "物理海洋学导论",
      "第6章｜风生大洋环流",
      "公式"
    ],
    "options": [],
    "answer": "β V ≈ curl(τ)/(ρ_0)",
    "explanation": "斯韦德鲁普平衡｜β V ≈ curl(τ)/(ρ_0)",
    "question": "【第6章｜风生大洋环流】斯韦德鲁普平衡可写为：______。"
  },
  {
    "id": "ocean-intro-core-062",
    "title": "【第6章｜风生大洋环流】位势涡度可写为：______。",
    "year": 2026,
    "school": "中国海洋大学",
    "score": 5,
    "type": "填空题",
    "category": "第6章｜风生大洋环流",
    "tags": [
      "物理海洋学",
      "物理海洋学导论",
      "第6章｜风生大洋环流",
      "公式",
      "位势涡度"
    ],
    "options": [],
    "answer": "q = (ζ + f)/H",
    "explanation": "位势涡度｜q = (ζ + f)/H",
    "question": "【第6章｜风生大洋环流】位势涡度可写为：______。"
  },
  {
    "id": "ocean-intro-core-063",
    "title": "【第6章｜风生大洋环流】______：从风应力旋度场出发判断海盆内部 Sverdrup 输运符号与大小。",
    "year": 2026,
    "school": "中国海洋大学",
    "score": 5,
    "type": "填空题",
    "category": "第6章｜风生大洋环流",
    "tags": [
      "物理海洋学",
      "物理海洋学导论",
      "第6章｜风生大洋环流",
      "方法",
      "风场诊断"
    ],
    "options": [],
    "answer": "风场诊断",
    "explanation": "风场诊断：从风应力旋度场出发判断海盆内部 Sverdrup 输运符号与大小。",
    "question": "【第6章｜风生大洋环流】______：从风应力旋度场出发判断海盆内部 Sverdrup 输运符号与大小。"
  },
  {
    "id": "ocean-intro-core-064",
    "title": "【第6章｜风生大洋环流】______：线性底摩擦、水平黏性和惯性非线性分别对应不同西边界流模型。",
    "year": 2026,
    "school": "中国海洋大学",
    "score": 5,
    "type": "填空题",
    "category": "第6章｜风生大洋环流",
    "tags": [
      "物理海洋学",
      "物理海洋学导论",
      "第6章｜风生大洋环流",
      "方法",
      "理论比较"
    ],
    "options": [],
    "answer": "理论比较",
    "explanation": "理论比较：线性底摩擦、水平黏性和惯性非线性分别对应不同西边界流模型。",
    "question": "【第6章｜风生大洋环流】______：线性底摩擦、水平黏性和惯性非线性分别对应不同西边界流模型。"
  },
  {
    "id": "ocean-intro-core-065",
    "title": "【第6章｜风生大洋环流】与副极地环流的方向与风带分布密切相关的是______。",
    "year": 2026,
    "school": "中国海洋大学",
    "score": 5,
    "type": "填空题",
    "category": "第6章｜风生大洋环流",
    "tags": [
      "物理海洋学",
      "物理海洋学导论",
      "第6章｜风生大洋环流",
      "现象"
    ],
    "options": [],
    "answer": "副热带环流",
    "explanation": "副热带环流与副极地环流的方向与风带分布密切相关。",
    "question": "【第6章｜风生大洋环流】与副极地环流的方向与风带分布密切相关的是______。"
  },
  {
    "id": "ocean-intro-core-066",
    "title": "【第6章｜风生大洋环流】______表现为窄、强、深、快。",
    "year": 2026,
    "school": "中国海洋大学",
    "score": 5,
    "type": "填空题",
    "category": "第6章｜风生大洋环流",
    "tags": [
      "物理海洋学",
      "物理海洋学导论",
      "第6章｜风生大洋环流",
      "现象"
    ],
    "options": [],
    "answer": "黑潮、湾流等西边界流",
    "explanation": "黑潮、湾流等西边界流表现为窄、强、深、快。",
    "question": "【第6章｜风生大洋环流】______表现为窄、强、深、快。"
  },
  {
    "id": "ocean-intro-core-067",
    "title": "【第6章｜风生大洋环流】决定海盆内部大尺度输运的风场量，不是风速本身而是______。",
    "year": 2026,
    "school": "中国海洋大学",
    "score": 5,
    "type": "填空题",
    "category": "第6章｜风生大洋环流",
    "tags": [
      "物理海洋学",
      "物理海洋学导论",
      "第6章｜风生大洋环流",
      "课堂追问"
    ],
    "options": [],
    "answer": "风应力旋度",
    "explanation": "决定海盆内部大尺度输运的风场量，不是风速本身而是风应力旋度。",
    "question": "【第6章｜风生大洋环流】决定海盆内部大尺度输运的风场量，不是风速本身而是______。"
  },
  {
    "id": "ocean-intro-core-068",
    "title": "【第6章｜风生大洋环流】解释海盆内部风生输运的经典理论是______。",
    "year": 2026,
    "school": "中国海洋大学",
    "score": 5,
    "type": "填空题",
    "category": "第6章｜风生大洋环流",
    "tags": [
      "物理海洋学",
      "物理海洋学导论",
      "第6章｜风生大洋环流",
      "课堂追问"
    ],
    "options": [],
    "answer": "斯韦德鲁普风生环流理论",
    "explanation": "解释海盆内部风生输运的经典理论是斯韦德鲁普风生环流理论。",
    "question": "【第6章｜风生大洋环流】解释海盆内部风生输运的经典理论是______。"
  },
  {
    "id": "ocean-intro-core-069",
    "title": "【第6章｜风生大洋环流】海盆环流闭合往往在西侧形成强而窄海流，这一现象称为______。",
    "year": 2026,
    "school": "中国海洋大学",
    "score": 5,
    "type": "填空题",
    "category": "第6章｜风生大洋环流",
    "tags": [
      "物理海洋学",
      "物理海洋学导论",
      "第6章｜风生大洋环流",
      "课堂追问"
    ],
    "options": [],
    "answer": "西边界强化",
    "explanation": "海盆环流闭合往往在西侧形成强而窄海流，这一现象称为西边界强化。",
    "question": "【第6章｜风生大洋环流】海盆环流闭合往往在西侧形成强而窄海流，这一现象称为______。"
  },
  {
    "id": "ocean-intro-core-070",
    "title": "【第6章｜风生大洋环流】黑潮和湾流是______。",
    "year": 2026,
    "school": "中国海洋大学",
    "score": 5,
    "type": "填空题",
    "category": "第6章｜风生大洋环流",
    "tags": [
      "物理海洋学",
      "物理海洋学导论",
      "第6章｜风生大洋环流",
      "课堂追问"
    ],
    "options": [],
    "answer": "现实海洋中典型的西边界流",
    "explanation": "黑潮和湾流是现实海洋中典型的西边界流。",
    "question": "【第6章｜风生大洋环流】黑潮和湾流是______。"
  },
  {
    "id": "ocean-intro-core-071",
    "title": "【第6章｜风生大洋环流】把相对涡度、行星涡度和流体柱厚度联系起来的守恒量是______。",
    "year": 2026,
    "school": "中国海洋大学",
    "score": 5,
    "type": "填空题",
    "category": "第6章｜风生大洋环流",
    "tags": [
      "物理海洋学",
      "物理海洋学导论",
      "第6章｜风生大洋环流",
      "课堂追问"
    ],
    "options": [],
    "answer": "位势涡度",
    "explanation": "把相对涡度、行星涡度和流体柱厚度联系起来的守恒量是位势涡度。",
    "question": "【第6章｜风生大洋环流】把相对涡度、行星涡度和流体柱厚度联系起来的守恒量是______。"
  },
  {
    "id": "ocean-intro-core-072",
    "title": "【第6章｜风生大洋环流】位势涡度守恒最直观的物理图像是______。",
    "year": 2026,
    "school": "中国海洋大学",
    "score": 5,
    "type": "填空题",
    "category": "第6章｜风生大洋环流",
    "tags": [
      "物理海洋学",
      "物理海洋学导论",
      "第6章｜风生大洋环流",
      "课堂追问"
    ],
    "options": [],
    "answer": "流体柱伸缩与自转变化相互补偿",
    "explanation": "位势涡度守恒最直观的物理图像是流体柱伸缩与自转变化相互补偿。",
    "question": "【第6章｜风生大洋环流】位势涡度守恒最直观的物理图像是______。"
  },
  {
    "id": "ocean-intro-core-073",
    "title": "【第7章｜深层环流理论】表层—深层之间存在的______，构成翻转环流的概念式表达。",
    "year": 2026,
    "school": "中国海洋大学",
    "score": 5,
    "type": "填空题",
    "category": "第7章｜深层环流理论",
    "tags": [
      "物理海洋学",
      "物理海洋学导论",
      "第7章｜深层环流理论",
      "公式"
    ],
    "options": [],
    "answer": "经向质量与热量再分配",
    "explanation": "翻转环流表达（概念式）｜表层—深层之间存在经向质量与热量再分配",
    "question": "【第7章｜深层环流理论】表层—深层之间存在的______，构成翻转环流的概念式表达。"
  },
  {
    "id": "ocean-intro-core-074",
    "title": "【第7章｜深层环流理论】______，系统可能存在多个稳定状态。",
    "year": 2026,
    "school": "中国海洋大学",
    "score": 5,
    "type": "填空题",
    "category": "第7章｜深层环流理论",
    "tags": [
      "物理海洋学",
      "物理海洋学导论",
      "第7章｜深层环流理论",
      "公式",
      "多平衡态的物理含义"
    ],
    "options": [],
    "answer": "同一外部背景下",
    "explanation": "多平衡态的物理含义｜同一外部背景下，系统可能存在多个稳定状态",
    "question": "【第7章｜深层环流理论】______，系统可能存在多个稳定状态。"
  },
  {
    "id": "ocean-intro-core-075",
    "title": "【第7章｜深层环流理论】______：利用长期系留和深海流速测量识别关键输送通道。",
    "year": 2026,
    "school": "中国海洋大学",
    "score": 5,
    "type": "填空题",
    "category": "第7章｜深层环流理论",
    "tags": [
      "物理海洋学",
      "物理海洋学导论",
      "第7章｜深层环流理论",
      "方法",
      "深层西边界流观测"
    ],
    "options": [],
    "answer": "深层西边界流观测",
    "explanation": "深层西边界流观测：利用长期系留和深海流速测量识别关键输送通道。",
    "question": "【第7章｜深层环流理论】______：利用长期系留和深海流速测量识别关键输送通道。"
  },
  {
    "id": "ocean-intro-core-076",
    "title": "【第7章｜深层环流理论】______：通过深层水团性质追踪来源、年龄和交换路径。",
    "year": 2026,
    "school": "中国海洋大学",
    "score": 5,
    "type": "填空题",
    "category": "第7章｜深层环流理论",
    "tags": [
      "物理海洋学",
      "物理海洋学导论",
      "第7章｜深层环流理论",
      "方法",
      "水文剖面与示踪物"
    ],
    "options": [],
    "answer": "水文剖面与示踪物",
    "explanation": "水文剖面与示踪物：通过深层水团性质追踪来源、年龄和交换路径。",
    "question": "【第7章｜深层环流理论】______：通过深层水团性质追踪来源、年龄和交换路径。"
  },
  {
    "id": "ocean-intro-core-077",
    "title": "【第7章｜深层环流理论】______控制全球热量长期再分配。",
    "year": 2026,
    "school": "中国海洋大学",
    "score": 5,
    "type": "填空题",
    "category": "第7章｜深层环流理论",
    "tags": [
      "物理海洋学",
      "物理海洋学导论",
      "第7章｜深层环流理论",
      "现象"
    ],
    "options": [],
    "answer": "深层环流",
    "explanation": "深层环流控制全球热量长期再分配。",
    "question": "【第7章｜深层环流理论】______控制全球热量长期再分配。"
  },
  {
    "id": "ocean-intro-core-078",
    "title": "【第7章｜深层环流理论】与深层水形成、下沉和再上翻密切相关的是______。",
    "year": 2026,
    "school": "中国海洋大学",
    "score": 5,
    "type": "填空题",
    "category": "第7章｜深层环流理论",
    "tags": [
      "物理海洋学",
      "物理海洋学导论",
      "第7章｜深层环流理论",
      "现象"
    ],
    "options": [],
    "answer": "海洋固碳",
    "explanation": "海洋固碳与深层水形成、下沉和再上翻密切相关。",
    "question": "【第7章｜深层环流理论】与深层水形成、下沉和再上翻密切相关的是______。"
  },
  {
    "id": "ocean-intro-core-079",
    "title": "【第7章｜深层环流理论】深层环流对气候最直接的重要性之一是______。",
    "year": 2026,
    "school": "中国海洋大学",
    "score": 5,
    "type": "填空题",
    "category": "第7章｜深层环流理论",
    "tags": [
      "物理海洋学",
      "物理海洋学导论",
      "第7章｜深层环流理论",
      "课堂追问"
    ],
    "options": [],
    "answer": "全球热量再分配",
    "explanation": "深层环流对气候最直接的重要性之一是全球热量再分配。",
    "question": "【第7章｜深层环流理论】深层环流对气候最直接的重要性之一是______。"
  },
  {
    "id": "ocean-intro-core-080",
    "title": "【第7章｜深层环流理论】教材强调深层环流除了热量作用外，还承担______。",
    "year": 2026,
    "school": "中国海洋大学",
    "score": 5,
    "type": "填空题",
    "category": "第7章｜深层环流理论",
    "tags": [
      "物理海洋学",
      "物理海洋学导论",
      "第7章｜深层环流理论",
      "课堂追问"
    ],
    "options": [],
    "answer": "海水固碳作用",
    "explanation": "教材强调深层环流除了热量作用外，还承担海水固碳作用。",
    "question": "【第7章｜深层环流理论】教材强调深层环流除了热量作用外，还承担______。"
  },
  {
    "id": "ocean-intro-core-081",
    "title": "【第7章｜深层环流理论】连接表层与深层的大尺度经向交换常概括为______。",
    "year": 2026,
    "school": "中国海洋大学",
    "score": 5,
    "type": "填空题",
    "category": "第7章｜深层环流理论",
    "tags": [
      "物理海洋学",
      "物理海洋学导论",
      "第7章｜深层环流理论",
      "课堂追问"
    ],
    "options": [],
    "answer": "翻转环流",
    "explanation": "连接表层与深层的大尺度经向交换常概括为翻转环流。",
    "question": "【第7章｜深层环流理论】连接表层与深层的大尺度经向交换常概括为______。"
  },
  {
    "id": "ocean-intro-core-082",
    "title": "【第7章｜深层环流理论】深层输送在盆地内部常通过狭窄的______完成。",
    "year": 2026,
    "school": "中国海洋大学",
    "score": 5,
    "type": "填空题",
    "category": "第7章｜深层环流理论",
    "tags": [
      "物理海洋学",
      "物理海洋学导论",
      "第7章｜深层环流理论",
      "课堂追问"
    ],
    "options": [],
    "answer": "深层西边界流",
    "explanation": "深层输送在盆地内部常通过狭窄的深层西边界流完成。",
    "question": "【第7章｜深层环流理论】深层输送在盆地内部常通过狭窄的______完成。"
  },
  {
    "id": "ocean-intro-core-083",
    "title": "【第7章｜深层环流理论】如果同样背景下系统可处于多个稳定状态，这一性质称为______。",
    "year": 2026,
    "school": "中国海洋大学",
    "score": 5,
    "type": "填空题",
    "category": "第7章｜深层环流理论",
    "tags": [
      "物理海洋学",
      "物理海洋学导论",
      "第7章｜深层环流理论",
      "课堂追问"
    ],
    "options": [],
    "answer": "多平衡态",
    "explanation": "如果同样背景下系统可处于多个稳定状态，这一性质称为多平衡态。",
    "question": "【第7章｜深层环流理论】如果同样背景下系统可处于多个稳定状态，这一性质称为______。"
  },
  {
    "id": "ocean-intro-core-084",
    "title": "【第7章｜深层环流理论】深层环流之所以被称为______。",
    "year": 2026,
    "school": "中国海洋大学",
    "score": 5,
    "type": "填空题",
    "category": "第7章｜深层环流理论",
    "tags": [
      "物理海洋学",
      "物理海洋学导论",
      "第7章｜深层环流理论",
      "课堂追问"
    ],
    "options": [],
    "answer": "气候系统的慢变量，是因为其调整时间尺度通常较长",
    "explanation": "深层环流之所以被称为气候系统的慢变量，是因为其调整时间尺度通常较长。",
    "question": "【第7章｜深层环流理论】深层环流之所以被称为______。"
  },
  {
    "id": "ocean-intro-core-085",
    "title": "【第8章｜波浪理论】线性表面重力波色散关系可写为：______。",
    "year": 2026,
    "school": "中国海洋大学",
    "score": 5,
    "type": "填空题",
    "category": "第8章｜波浪理论",
    "tags": [
      "物理海洋学",
      "物理海洋学导论",
      "第8章｜波浪理论",
      "公式",
      "线性表面重力波色散关系"
    ],
    "options": [],
    "answer": "ω² = gk tanh(kh)",
    "explanation": "线性表面重力波色散关系｜ω² = gk tanh(kh)",
    "question": "【第8章｜波浪理论】线性表面重力波色散关系可写为：______。"
  },
  {
    "id": "ocean-intro-core-086",
    "title": "【第8章｜波浪理论】波能可近似写为：______。",
    "year": 2026,
    "school": "中国海洋大学",
    "score": 5,
    "type": "填空题",
    "category": "第8章｜波浪理论",
    "tags": [
      "物理海洋学",
      "物理海洋学导论",
      "第8章｜波浪理论",
      "公式"
    ],
    "options": [],
    "answer": "E ≈ (1/8)ρgH²",
    "explanation": "波能｜E ≈ (1/8)ρgH²",
    "question": "【第8章｜波浪理论】波能可近似写为：______。"
  },
  {
    "id": "ocean-intro-core-087",
    "title": "【第8章｜波浪理论】______：从控制方程、边界条件和色散关系求解基础波场。",
    "year": 2026,
    "school": "中国海洋大学",
    "score": 5,
    "type": "填空题",
    "category": "第8章｜波浪理论",
    "tags": [
      "物理海洋学",
      "物理海洋学导论",
      "第8章｜波浪理论",
      "方法",
      "规则波分析"
    ],
    "options": [],
    "answer": "规则波分析",
    "explanation": "规则波分析：从控制方程、边界条件和色散关系求解基础波场。",
    "question": "【第8章｜波浪理论】______：从控制方程、边界条件和色散关系求解基础波场。"
  },
  {
    "id": "ocean-intro-core-088",
    "title": "【第8章｜波浪理论】______：用随机波浪理论描述真实海况中的频率能量分布。",
    "year": 2026,
    "school": "中国海洋大学",
    "score": 5,
    "type": "填空题",
    "category": "第8章｜波浪理论",
    "tags": [
      "物理海洋学",
      "物理海洋学导论",
      "第8章｜波浪理论",
      "方法",
      "波谱诊断"
    ],
    "options": [],
    "answer": "波谱诊断",
    "explanation": "波谱诊断：用随机波浪理论描述真实海况中的频率能量分布。",
    "question": "【第8章｜波浪理论】______：用随机波浪理论描述真实海况中的频率能量分布。"
  },
  {
    "id": "ocean-intro-core-089",
    "title": "【第8章｜波浪理论】______说明海浪传播的不只是波峰位置。",
    "year": 2026,
    "school": "中国海洋大学",
    "score": 5,
    "type": "填空题",
    "category": "第8章｜波浪理论",
    "tags": [
      "物理海洋学",
      "物理海洋学导论",
      "第8章｜波浪理论",
      "现象"
    ],
    "options": [],
    "answer": "相速和群速不一致",
    "explanation": "相速和群速不一致，说明海浪传播的不只是波峰位置。",
    "question": "【第8章｜波浪理论】______说明海浪传播的不只是波峰位置。"
  },
  {
    "id": "ocean-intro-core-090",
    "title": "【第8章｜波浪理论】______共同塑造近岸波场。",
    "year": 2026,
    "school": "中国海洋大学",
    "score": 5,
    "type": "填空题",
    "category": "第8章｜波浪理论",
    "tags": [
      "物理海洋学",
      "物理海洋学导论",
      "第8章｜波浪理论",
      "现象"
    ],
    "options": [],
    "answer": "浅水折射、绕射和破碎",
    "explanation": "浅水折射、绕射和破碎塑造近岸波场。",
    "question": "【第8章｜波浪理论】______共同塑造近岸波场。"
  },
  {
    "id": "ocean-intro-core-091",
    "title": "【第8章｜波浪理论】在线性波理论中，描述相位传播快慢的速度称为______。",
    "year": 2026,
    "school": "中国海洋大学",
    "score": 5,
    "type": "填空题",
    "category": "第8章｜波浪理论",
    "tags": [
      "物理海洋学",
      "物理海洋学导论",
      "第8章｜波浪理论",
      "课堂追问"
    ],
    "options": [],
    "answer": "相速",
    "explanation": "在线性波理论中，描述相位传播快慢的速度称为相速。",
    "question": "【第8章｜波浪理论】在线性波理论中，描述相位传播快慢的速度称为______。"
  },
  {
    "id": "ocean-intro-core-092",
    "title": "【第8章｜波浪理论】在线性波理论中，更能代表______。",
    "year": 2026,
    "school": "中国海洋大学",
    "score": 5,
    "type": "填空题",
    "category": "第8章｜波浪理论",
    "tags": [
      "物理海洋学",
      "物理海洋学导论",
      "第8章｜波浪理论",
      "课堂追问"
    ],
    "options": [],
    "answer": "能量传播的速度称为群速",
    "explanation": "在线性波理论中，更能代表能量传播的速度称为群速。",
    "question": "【第8章｜波浪理论】在线性波理论中，更能代表______。"
  },
  {
    "id": "ocean-intro-core-093",
    "title": "【第8章｜波浪理论】把实际海浪看作统计波场时，最常用的描述工具是______。",
    "year": 2026,
    "school": "中国海洋大学",
    "score": 5,
    "type": "填空题",
    "category": "第8章｜波浪理论",
    "tags": [
      "物理海洋学",
      "物理海洋学导论",
      "第8章｜波浪理论",
      "课堂追问"
    ],
    "options": [],
    "answer": "波浪谱",
    "explanation": "把实际海浪看作统计波场时，最常用的描述工具是波浪谱。",
    "question": "【第8章｜波浪理论】把实际海浪看作统计波场时，最常用的描述工具是______。"
  },
  {
    "id": "ocean-intro-core-094",
    "title": "【第8章｜波浪理论】波浪进入浅水区后因水深变化而改变传播方向的现象称为______。",
    "year": 2026,
    "school": "中国海洋大学",
    "score": 5,
    "type": "填空题",
    "category": "第8章｜波浪理论",
    "tags": [
      "物理海洋学",
      "物理海洋学导论",
      "第8章｜波浪理论",
      "课堂追问"
    ],
    "options": [],
    "answer": "折射",
    "explanation": "波浪进入浅水区后因水深变化而改变传播方向的现象称为折射。",
    "question": "【第8章｜波浪理论】波浪进入浅水区后因水深变化而改变传播方向的现象称为______。"
  },
  {
    "id": "ocean-intro-core-095",
    "title": "【第8章｜波浪理论】由强天气系统引起的海面显著增水和灾害性波动称为______。",
    "year": 2026,
    "school": "中国海洋大学",
    "score": 5,
    "type": "填空题",
    "category": "第8章｜波浪理论",
    "tags": [
      "物理海洋学",
      "物理海洋学导论",
      "第8章｜波浪理论",
      "课堂追问"
    ],
    "options": [],
    "answer": "风暴潮",
    "explanation": "由强天气系统引起的海面显著增水和灾害性波动称为风暴潮。",
    "question": "【第8章｜波浪理论】由强天气系统引起的海面显著增水和灾害性波动称为______。"
  },
  {
    "id": "ocean-intro-core-096",
    "title": "【第8章｜波浪理论】由海底地震等激发、以长波形式传播的典型灾害性海洋波动是______。",
    "year": 2026,
    "school": "中国海洋大学",
    "score": 5,
    "type": "填空题",
    "category": "第8章｜波浪理论",
    "tags": [
      "物理海洋学",
      "物理海洋学导论",
      "第8章｜波浪理论",
      "课堂追问"
    ],
    "options": [],
    "answer": "海啸",
    "explanation": "由海底地震等激发、以长波形式传播的典型灾害性海洋波动是海啸。",
    "question": "【第8章｜波浪理论】由海底地震等激发、以长波形式传播的典型灾害性海洋波动是______。"
  },
  {
    "id": "ocean-intro-core-097",
    "title": "【第9章｜海洋中的大尺度波动】______，横向速度近零，振幅离边界指数衰减。",
    "year": 2026,
    "school": "中国海洋大学",
    "score": 5,
    "type": "填空题",
    "category": "第9章｜海洋中的大尺度波动",
    "tags": [
      "物理海洋学",
      "物理海洋学导论",
      "第9章｜海洋中的大尺度波动",
      "公式",
      "Kelvin 波核心特征"
    ],
    "options": [],
    "answer": "沿边界传播",
    "explanation": "Kelvin 波核心特征｜沿边界传播，横向速度近零，振幅离边界指数衰减",
    "question": "【第9章｜海洋中的大尺度波动】______，横向速度近零，振幅离边界指数衰减。"
  },
  {
    "id": "ocean-intro-core-098",
    "title": "【第9章｜海洋中的大尺度波动】Rossby 波色散（概念式）可写为：______。",
    "year": 2026,
    "school": "中国海洋大学",
    "score": 5,
    "type": "填空题",
    "category": "第9章｜海洋中的大尺度波动",
    "tags": [
      "物理海洋学",
      "物理海洋学导论",
      "第9章｜海洋中的大尺度波动",
      "公式",
      "Rossby 波色散（概念式）"
    ],
    "options": [],
    "answer": "频率受 β 与波数控制，能量主要承担慢调整",
    "explanation": "Rossby 波色散（概念式）｜频率受 β 与波数控制，能量主要承担慢调整",
    "question": "【第9章｜海洋中的大尺度波动】Rossby 波色散（概念式）可写为：______。"
  },
  {
    "id": "ocean-intro-core-099",
    "title": "【第9章｜海洋中的大尺度波动】______：先用线性波动框架区分不同恢复机制。",
    "year": 2026,
    "school": "中国海洋大学",
    "score": 5,
    "type": "填空题",
    "category": "第9章｜海洋中的大尺度波动",
    "tags": [
      "物理海洋学",
      "物理海洋学导论",
      "第9章｜海洋中的大尺度波动",
      "方法",
      "理论诊断"
    ],
    "options": [],
    "answer": "理论诊断",
    "explanation": "理论诊断：先用线性波动框架区分不同恢复机制。",
    "question": "【第9章｜海洋中的大尺度波动】______：先用线性波动框架区分不同恢复机制。"
  },
  {
    "id": "ocean-intro-core-100",
    "title": "【第9章｜海洋中的大尺度波动】______：边界约束、β 效应和地形梯度分别对应不同波型。",
    "year": 2026,
    "school": "中国海洋大学",
    "score": 5,
    "type": "填空题",
    "category": "第9章｜海洋中的大尺度波动",
    "tags": [
      "物理海洋学",
      "物理海洋学导论",
      "第9章｜海洋中的大尺度波动",
      "方法",
      "物理比较"
    ],
    "options": [],
    "answer": "物理比较",
    "explanation": "物理比较：边界约束、β 效应和地形梯度分别对应不同波型。",
    "question": "【第9章｜海洋中的大尺度波动】______：边界约束、β 效应和地形梯度分别对应不同波型。"
  },
  {
    "id": "ocean-intro-core-101",
    "title": "【第9章｜海洋中的大尺度波动】______体现旋转背景下的惯性重力波特征。",
    "year": 2026,
    "school": "中国海洋大学",
    "score": 5,
    "type": "填空题",
    "category": "第9章｜海洋中的大尺度波动",
    "tags": [
      "物理海洋学",
      "物理海洋学导论",
      "第9章｜海洋中的大尺度波动",
      "现象"
    ],
    "options": [],
    "answer": "庞加莱波",
    "explanation": "庞加莱波体现旋转背景下的惯性重力波特征。",
    "question": "【第9章｜海洋中的大尺度波动】______体现旋转背景下的惯性重力波特征。"
  },
  {
    "id": "ocean-intro-core-102",
    "title": "【第9章｜海洋中的大尺度波动】Kelvin 波承担______。",
    "year": 2026,
    "school": "中国海洋大学",
    "score": 5,
    "type": "填空题",
    "category": "第9章｜海洋中的大尺度波动",
    "tags": [
      "物理海洋学",
      "物理海洋学导论",
      "第9章｜海洋中的大尺度波动",
      "现象"
    ],
    "options": [],
    "answer": "沿岸和赤道快速信息传播",
    "explanation": "Kelvin 波承担沿岸和赤道快速信息传播。",
    "question": "【第9章｜海洋中的大尺度波动】Kelvin 波承担______。"
  },
  {
    "id": "ocean-intro-core-103",
    "title": "【第9章｜海洋中的大尺度波动】兼具旋转约束和重力恢复的大尺度基础波型是______。",
    "year": 2026,
    "school": "中国海洋大学",
    "score": 5,
    "type": "填空题",
    "category": "第9章｜海洋中的大尺度波动",
    "tags": [
      "物理海洋学",
      "物理海洋学导论",
      "第9章｜海洋中的大尺度波动",
      "课堂追问"
    ],
    "options": [],
    "answer": "庞加莱波",
    "explanation": "兼具旋转约束和重力恢复的大尺度基础波型是庞加莱波。",
    "question": "【第9章｜海洋中的大尺度波动】兼具旋转约束和重力恢复的大尺度基础波型是______。"
  },
  {
    "id": "ocean-intro-core-104",
    "title": "【第9章｜海洋中的大尺度波动】沿岸或赤道快速传播、受边界束缚的长波称为______。",
    "year": 2026,
    "school": "中国海洋大学",
    "score": 5,
    "type": "填空题",
    "category": "第9章｜海洋中的大尺度波动",
    "tags": [
      "物理海洋学",
      "物理海洋学导论",
      "第9章｜海洋中的大尺度波动",
      "课堂追问"
    ],
    "options": [],
    "answer": "开尔文 / Kelvin波",
    "explanation": "沿岸或赤道快速传播、受边界束缚的长波称为开尔文 / Kelvin波。",
    "question": "【第9章｜海洋中的大尺度波动】沿岸或赤道快速传播、受边界束缚的长波称为______。"
  },
  {
    "id": "ocean-intro-core-105",
    "title": "【第9章｜海洋中的大尺度波动】以 β 效应为核心恢复机制并承担______。",
    "year": 2026,
    "school": "中国海洋大学",
    "score": 5,
    "type": "填空题",
    "category": "第9章｜海洋中的大尺度波动",
    "tags": [
      "物理海洋学",
      "物理海洋学导论",
      "第9章｜海洋中的大尺度波动",
      "课堂追问"
    ],
    "options": [],
    "answer": "慢调整的波型是罗斯贝 / Rossby波",
    "explanation": "以 β 效应为核心恢复机制并承担慢调整的波型是罗斯贝 / Rossby波。",
    "question": "【第9章｜海洋中的大尺度波动】以 β 效应为核心恢复机制并承担______。"
  },
  {
    "id": "ocean-intro-core-106",
    "title": "【第9章｜海洋中的大尺度波动】______，可形成地形罗斯贝波。",
    "year": 2026,
    "school": "中国海洋大学",
    "score": 5,
    "type": "填空题",
    "category": "第9章｜海洋中的大尺度波动",
    "tags": [
      "物理海洋学",
      "物理海洋学导论",
      "第9章｜海洋中的大尺度波动",
      "课堂追问"
    ],
    "options": [],
    "answer": "若恢复机制来自海底坡度等地形效应",
    "explanation": "若恢复机制来自海底坡度等地形效应，可形成地形罗斯贝波。",
    "question": "【第9章｜海洋中的大尺度波动】______，可形成地形罗斯贝波。"
  },
  {
    "id": "ocean-intro-core-107",
    "title": "【第9章｜海洋中的大尺度波动】Kelvin 波之所以特殊，是______。",
    "year": 2026,
    "school": "中国海洋大学",
    "score": 5,
    "type": "填空题",
    "category": "第9章｜海洋中的大尺度波动",
    "tags": [
      "物理海洋学",
      "物理海洋学导论",
      "第9章｜海洋中的大尺度波动",
      "课堂追问"
    ],
    "options": [],
    "answer": "因为传播受到边界条件强约束",
    "explanation": "Kelvin 波之所以特殊，是因为传播受到边界条件强约束。",
    "question": "【第9章｜海洋中的大尺度波动】Kelvin 波之所以特殊，是______。"
  },
  {
    "id": "ocean-intro-core-108",
    "title": "【第9章｜海洋中的大尺度波动】Rossby 波虽然传播慢，却非常适合承担______。",
    "year": 2026,
    "school": "中国海洋大学",
    "score": 5,
    "type": "填空题",
    "category": "第9章｜海洋中的大尺度波动",
    "tags": [
      "物理海洋学",
      "物理海洋学导论",
      "第9章｜海洋中的大尺度波动",
      "课堂追问"
    ],
    "options": [],
    "answer": "海盆尺度的长期调整",
    "explanation": "Rossby 波虽然传播慢，却非常适合承担海盆尺度的长期调整。",
    "question": "【第9章｜海洋中的大尺度波动】Rossby 波虽然传播慢，却非常适合承担______。"
  },
  {
    "id": "ocean-intro-core-109",
    "title": "【第10章｜海洋内波】稳定度与浮力频率可写为：______。",
    "year": 2026,
    "school": "中国海洋大学",
    "score": 5,
    "type": "填空题",
    "category": "第10章｜海洋内波",
    "tags": [
      "物理海洋学",
      "物理海洋学导论",
      "第10章｜海洋内波",
      "公式",
      "稳定度与浮力频率"
    ],
    "options": [],
    "answer": "N² = -(g/ρ) dρ/dz",
    "explanation": "稳定度与浮力频率｜N² = -(g/ρ) dρ/dz",
    "question": "【第10章｜海洋内波】稳定度与浮力频率可写为：______。"
  },
  {
    "id": "ocean-intro-core-110",
    "title": "【第10章｜海洋内波】内波频散关系表明，ω 与 k、m、N、f 之间存在受______控制的色散关系。",
    "year": 2026,
    "school": "中国海洋大学",
    "score": 5,
    "type": "填空题",
    "category": "第10章｜海洋内波",
    "tags": [
      "物理海洋学",
      "物理海洋学导论",
      "第10章｜海洋内波",
      "公式"
    ],
    "options": [],
    "answer": "层化",
    "explanation": "内波频散关系｜ω 与 k、m、N、f 之间存在层化控制的色散关系",
    "question": "【第10章｜海洋内波】内波频散关系表明，ω 与 k、m、N、f 之间存在受______控制的色散关系。"
  },
  {
    "id": "ocean-intro-core-111",
    "title": "【第10章｜海洋内波】______：先用温盐剖面计算密度和浮力频率。",
    "year": 2026,
    "school": "中国海洋大学",
    "score": 5,
    "type": "填空题",
    "category": "第10章｜海洋内波",
    "tags": [
      "物理海洋学",
      "物理海洋学导论",
      "第10章｜海洋内波",
      "方法",
      "层化诊断"
    ],
    "options": [],
    "answer": "层化诊断",
    "explanation": "层化诊断：先用温盐剖面计算密度和浮力频率。",
    "question": "【第10章｜海洋内波】______：先用温盐剖面计算密度和浮力频率。"
  },
  {
    "id": "ocean-intro-core-112",
    "title": "【第10章｜海洋内波】______：利用本征方程与频散关系判断可传播模态。",
    "year": 2026,
    "school": "中国海洋大学",
    "score": 5,
    "type": "填空题",
    "category": "第10章｜海洋内波",
    "tags": [
      "物理海洋学",
      "物理海洋学导论",
      "第10章｜海洋内波",
      "方法",
      "理论求解"
    ],
    "options": [],
    "answer": "理论求解",
    "explanation": "理论求解：利用本征方程与频散关系判断可传播模态。",
    "question": "【第10章｜海洋内波】______：利用本征方程与频散关系判断可传播模态。"
  },
  {
    "id": "ocean-intro-core-113",
    "title": "【第10章｜海洋内波】死水现象是______。",
    "year": 2026,
    "school": "中国海洋大学",
    "score": 5,
    "type": "填空题",
    "category": "第10章｜海洋内波",
    "tags": [
      "物理海洋学",
      "物理海洋学导论",
      "第10章｜海洋内波",
      "现象"
    ],
    "options": [],
    "answer": "内波最经典的历史案例",
    "explanation": "死水现象是内波最经典的历史案例。",
    "question": "【第10章｜海洋内波】死水现象是______。"
  },
  {
    "id": "ocean-intro-core-114",
    "title": "【第10章｜海洋内波】______共同决定内波生成。",
    "year": 2026,
    "school": "中国海洋大学",
    "score": 5,
    "type": "填空题",
    "category": "第10章｜海洋内波",
    "tags": [
      "物理海洋学",
      "物理海洋学导论",
      "第10章｜海洋内波",
      "现象"
    ],
    "options": [],
    "answer": "稳定层化、能量来源和激发源",
    "explanation": "稳定层化、能量来源和激发源共同决定内波生成。",
    "question": "【第10章｜海洋内波】______共同决定内波生成。"
  },
  {
    "id": "ocean-intro-core-115",
    "title": "【第10章｜海洋内波】内波存在的前提是______。",
    "year": 2026,
    "school": "中国海洋大学",
    "score": 5,
    "type": "填空题",
    "category": "第10章｜海洋内波",
    "tags": [
      "物理海洋学",
      "物理海洋学导论",
      "第10章｜海洋内波",
      "课堂追问"
    ],
    "options": [],
    "answer": "海洋内部具有稳定的层化 / 密度分层",
    "explanation": "内波存在的前提是海洋内部具有稳定的层化 / 密度分层。",
    "question": "【第10章｜海洋内波】内波存在的前提是______。"
  },
  {
    "id": "ocean-intro-core-116",
    "title": "【第10章｜海洋内波】衡量层结强度并限定内波频率范围的重要量是______。",
    "year": 2026,
    "school": "中国海洋大学",
    "score": 5,
    "type": "填空题",
    "category": "第10章｜海洋内波",
    "tags": [
      "物理海洋学",
      "物理海洋学导论",
      "第10章｜海洋内波",
      "课堂追问"
    ],
    "options": [],
    "answer": "浮力频率",
    "explanation": "衡量层结强度并限定内波频率范围的重要量是浮力频率。",
    "question": "【第10章｜海洋内波】衡量层结强度并限定内波频率范围的重要量是______。"
  },
  {
    "id": "ocean-intro-core-117",
    "title": "【第10章｜海洋内波】______使用的是本征模态。",
    "year": 2026,
    "school": "中国海洋大学",
    "score": 5,
    "type": "填空题",
    "category": "第10章｜海洋内波",
    "tags": [
      "物理海洋学",
      "物理海洋学导论",
      "第10章｜海洋内波",
      "课堂追问"
    ],
    "options": [],
    "answer": "把复杂内波场拆分为不同垂向结构时",
    "explanation": "把复杂内波场拆分为不同垂向结构时使用的是本征模态。",
    "question": "【第10章｜海洋内波】______使用的是本征模态。"
  },
  {
    "id": "ocean-intro-core-118",
    "title": "【第10章｜海洋内波】由潮汐流经起伏地形激发的典型内波称为______。",
    "year": 2026,
    "school": "中国海洋大学",
    "score": 5,
    "type": "填空题",
    "category": "第10章｜海洋内波",
    "tags": [
      "物理海洋学",
      "物理海洋学导论",
      "第10章｜海洋内波",
      "课堂追问"
    ],
    "options": [],
    "answer": "内潮",
    "explanation": "由潮汐流经起伏地形激发的典型内波称为内潮。",
    "question": "【第10章｜海洋内波】由潮汐流经起伏地形激发的典型内波称为______。"
  },
  {
    "id": "ocean-intro-core-119",
    "title": "【第10章｜海洋内波】具有强非线性和大振幅特征的典型内波形式是______。",
    "year": 2026,
    "school": "中国海洋大学",
    "score": 5,
    "type": "填空题",
    "category": "第10章｜海洋内波",
    "tags": [
      "物理海洋学",
      "物理海洋学导论",
      "第10章｜海洋内波",
      "课堂追问"
    ],
    "options": [],
    "answer": "内孤立波",
    "explanation": "具有强非线性和大振幅特征的典型内波形式是内孤立波。",
    "question": "【第10章｜海洋内波】具有强非线性和大振幅特征的典型内波形式是______。"
  },
  {
    "id": "ocean-intro-core-120",
    "title": "【第10章｜海洋内波】内波之所以重要，是______。",
    "year": 2026,
    "school": "中国海洋大学",
    "score": 5,
    "type": "填空题",
    "category": "第10章｜海洋内波",
    "tags": [
      "物理海洋学",
      "物理海洋学导论",
      "第10章｜海洋内波",
      "课堂追问"
    ],
    "options": [],
    "answer": "因为它连接大尺度能量输入与小尺度混合增强",
    "explanation": "内波之所以重要，是因为它连接大尺度能量输入与小尺度混合增强。",
    "question": "【第10章｜海洋内波】内波之所以重要，是______。"
  },
  {
    "id": "ocean-intro-core-121",
    "title": "【第11章｜若干前沿专题】ENSO 可用______或南方涛动指数表征。",
    "year": 2026,
    "school": "中国海洋大学",
    "score": 5,
    "type": "填空题",
    "category": "第11章｜若干前沿专题",
    "tags": [
      "物理海洋学",
      "物理海洋学导论",
      "第11章｜若干前沿专题",
      "公式"
    ],
    "options": [],
    "answer": "海表温度距平",
    "explanation": "ENSO 指标表达｜可用海表温度距平或南方涛动指数表征",
    "question": "【第11章｜若干前沿专题】ENSO 可用______或南方涛动指数表征。"
  },
  {
    "id": "ocean-intro-core-122",
    "title": "【第11章｜若干前沿专题】赤道 Kelvin 波和 Rossby 波都属于______。",
    "year": 2026,
    "school": "中国海洋大学",
    "score": 5,
    "type": "填空题",
    "category": "第11章｜若干前沿专题",
    "tags": [
      "物理海洋学",
      "物理海洋学导论",
      "第11章｜若干前沿专题",
      "公式"
    ],
    "options": [],
    "answer": "赤道陷波",
    "explanation": "赤道波导概念｜赤道 Kelvin 波和 Rossby 波为赤道陷波",
    "question": "【第11章｜若干前沿专题】赤道 Kelvin 波和 Rossby 波都属于______。"
  },
  {
    "id": "ocean-intro-core-123",
    "title": "【第11章｜若干前沿专题】______：TOGA 等观测计划建立了海气耦合长期监测框架。",
    "year": 2026,
    "school": "中国海洋大学",
    "score": 5,
    "type": "填空题",
    "category": "第11章｜若干前沿专题",
    "tags": [
      "物理海洋学",
      "物理海洋学导论",
      "第11章｜若干前沿专题",
      "方法",
      "ENSO 观测"
    ],
    "options": [],
    "answer": "ENSO 观测",
    "explanation": "ENSO 观测：TOGA 等观测计划建立了海气耦合长期监测框架。",
    "question": "【第11章｜若干前沿专题】______：TOGA 等观测计划建立了海气耦合长期监测框架。"
  },
  {
    "id": "ocean-intro-core-124",
    "title": "【第11章｜若干前沿专题】______：大气模式、海洋模式和耦合模式共同用于 ENSO 预测。",
    "year": 2026,
    "school": "中国海洋大学",
    "score": 5,
    "type": "填空题",
    "category": "第11章｜若干前沿专题",
    "tags": [
      "物理海洋学",
      "物理海洋学导论",
      "第11章｜若干前沿专题",
      "方法",
      "预报方法"
    ],
    "options": [],
    "answer": "预报方法",
    "explanation": "预报方法：大气模式、海洋模式和耦合模式共同用于 ENSO 预测。",
    "question": "【第11章｜若干前沿专题】______：大气模式、海洋模式和耦合模式共同用于 ENSO 预测。"
  },
  {
    "id": "ocean-intro-core-125",
    "title": "【第11章｜若干前沿专题】______展示了赤道特殊动力环境。",
    "year": 2026,
    "school": "中国海洋大学",
    "score": 5,
    "type": "填空题",
    "category": "第11章｜若干前沿专题",
    "tags": [
      "物理海洋学",
      "物理海洋学导论",
      "第11章｜若干前沿专题",
      "现象"
    ],
    "options": [],
    "answer": "赤道潜流与 ENSO",
    "explanation": "赤道潜流与 ENSO 展示了赤道特殊动力环境。",
    "question": "【第11章｜若干前沿专题】______展示了赤道特殊动力环境。"
  },
  {
    "id": "ocean-intro-core-126",
    "title": "【第11章｜若干前沿专题】把海冰变化、深水形成和气候变化绑定在一起的是______。",
    "year": 2026,
    "school": "中国海洋大学",
    "score": 5,
    "type": "填空题",
    "category": "第11章｜若干前沿专题",
    "tags": [
      "物理海洋学",
      "物理海洋学导论",
      "第11章｜若干前沿专题",
      "现象"
    ],
    "options": [],
    "answer": "极地过程",
    "explanation": "极地过程把海冰变化、深水形成和气候变化绑定在一起。",
    "question": "【第11章｜若干前沿专题】把海冰变化、深水形成和气候变化绑定在一起的是______。"
  },
  {
    "id": "ocean-intro-core-127",
    "title": "【第11章｜若干前沿专题】海气耦合最典型、最著名的赤道年际振荡现象缩写为______。",
    "year": 2026,
    "school": "中国海洋大学",
    "score": 5,
    "type": "填空题",
    "category": "第11章｜若干前沿专题",
    "tags": [
      "物理海洋学",
      "物理海洋学导论",
      "第11章｜若干前沿专题",
      "课堂追问"
    ],
    "options": [],
    "answer": "ENSO",
    "explanation": "海气耦合最典型、最著名的赤道年际振荡现象缩写为ENSO。",
    "question": "【第11章｜若干前沿专题】海气耦合最典型、最著名的赤道年际振荡现象缩写为______。"
  },
  {
    "id": "ocean-intro-core-128",
    "title": "【第11章｜若干前沿专题】教材中用于衡量南方涛动强弱的重要量是______。",
    "year": 2026,
    "school": "中国海洋大学",
    "score": 5,
    "type": "填空题",
    "category": "第11章｜若干前沿专题",
    "tags": [
      "物理海洋学",
      "物理海洋学导论",
      "第11章｜若干前沿专题",
      "课堂追问"
    ],
    "options": [],
    "answer": "南方涛动指数",
    "explanation": "教材中用于衡量南方涛动强弱的重要量是南方涛动指数。",
    "question": "【第11章｜若干前沿专题】教材中用于衡量南方涛动强弱的重要量是______。"
  },
  {
    "id": "ocean-intro-core-129",
    "title": "【第11章｜若干前沿专题】与海冰变化、深水形成以及全球气候变化密切相关的是______。",
    "year": 2026,
    "school": "中国海洋大学",
    "score": 5,
    "type": "填空题",
    "category": "第11章｜若干前沿专题",
    "tags": [
      "物理海洋学",
      "物理海洋学导论",
      "第11章｜若干前沿专题",
      "课堂追问"
    ],
    "options": [],
    "answer": "极地过程",
    "explanation": "极地过程与海冰变化、深水形成以及全球气候变化密切相关。",
    "question": "【第11章｜若干前沿专题】与海冰变化、深水形成以及全球气候变化密切相关的是______。"
  },
  {
    "id": "ocean-intro-core-130",
    "title": "【第11章｜若干前沿专题】______，教材特别强调了自动探测的重要性。",
    "year": 2026,
    "school": "中国海洋大学",
    "score": 5,
    "type": "填空题",
    "category": "第11章｜若干前沿专题",
    "tags": [
      "物理海洋学",
      "物理海洋学导论",
      "第11章｜若干前沿专题",
      "课堂追问"
    ],
    "options": [],
    "answer": "海洋中尺度涡旋研究中",
    "explanation": "海洋中尺度涡旋研究中，教材特别强调了自动探测的重要性。",
    "question": "【第11章｜若干前沿专题】______，教材特别强调了自动探测的重要性。"
  },
  {
    "id": "ocean-intro-core-131",
    "title": "【第11章｜若干前沿专题】______，次中尺度过程通常具有更强的垂向交换。",
    "year": 2026,
    "school": "中国海洋大学",
    "score": 5,
    "type": "填空题",
    "category": "第11章｜若干前沿专题",
    "tags": [
      "物理海洋学",
      "物理海洋学导论",
      "第11章｜若干前沿专题",
      "课堂追问"
    ],
    "options": [],
    "answer": "相较中尺度",
    "explanation": "相较中尺度，次中尺度过程通常具有更强的垂向交换。",
    "question": "【第11章｜若干前沿专题】______，次中尺度过程通常具有更强的垂向交换。"
  },
  {
    "id": "ocean-intro-core-132",
    "title": "【第11章｜若干前沿专题】前沿专题章节的根本作用，是______。",
    "year": 2026,
    "school": "中国海洋大学",
    "score": 5,
    "type": "填空题",
    "category": "第11章｜若干前沿专题",
    "tags": [
      "物理海洋学",
      "物理海洋学导论",
      "第11章｜若干前沿专题",
      "课堂追问"
    ],
    "options": [],
    "answer": "把基础理论推进到现代科研 / 前沿问题",
    "explanation": "前沿专题章节的根本作用，是把基础理论推进到现代科研 / 前沿问题。",
    "question": "【第11章｜若干前沿专题】前沿专题章节的根本作用，是______。"
  }
]