{
  "ok": true,
  "version": "round536-181103-proof-depth-upgrade-20260624",
  "generatedAt": "2026-06-24T13:43:28.140Z",
  "upgradedRows": 30,
  "upgradedIds": [
    "181103-material-extracted-0118",
    "181103-material-extracted-0049",
    "181103-material-extracted-0134",
    "181103-material-extracted-0013",
    "181103-material-extracted-0035",
    "181103-material-extracted-0046",
    "181103-material-extracted-0099",
    "181103-material-extracted-0132",
    "181103-material-extracted-0151",
    "181103-material-extracted-0153",
    "181103-material-extracted-0306",
    "181103-material-extracted-0317",
    "181103-material-extracted-0318",
    "181103-material-extracted-0324",
    "181103-material-extracted-0325",
    "181103-material-extracted-0326",
    "181103-material-extracted-0344",
    "181103-material-extracted-0349",
    "181103-material-extracted-0350",
    "181103-material-extracted-0351",
    "181103-material-extracted-0378",
    "181103-material-extracted-0386",
    "181103-material-extracted-0396",
    "181103-material-extracted-0399",
    "181103-material-extracted-0403",
    "181103-material-extracted-0408",
    "181103-material-extracted-0499",
    "181103-material-extracted-0500",
    "181103-material-extracted-0501",
    "181103-material-extracted-0521"
  ],
  "minChars": 471,
  "minSentenceCount": 7,
  "minFormulaCount": 30,
  "minProofSignalCount": 5,
  "failedIds": [],
  "records": [
    {
      "id": "181103-material-extracted-0118",
      "sourceHtmlUrl": "/resources/fluid-181103-html/materials/01-fluid-181103-01-material/index.html#page-148",
      "sourceMaterialTitle": "流体力学习题解 余志豪",
      "sourcePage": 148,
      "type": "名词解释",
      "question": "3.10 若螺旋桨推进力 \\(F\\) 与直径 \\(d\\)、推进速度 \\(V\\)、每秒转数 \\(n\\)、流体密度 \\(ρ\\) 和粘性系数 \\(μ\\) 有关，试用 \\(Π\\) 定理证明推力表示式，并分别以两组基本量求解。",
      "diagnosis": "原答案只列两个最终相似式，没有展示量纲矩阵、重复变量选择和无量纲数组构造，学生看不出 Π 定理怎么用。",
      "before": "用 \\(\\rho,V,d\\) 作基本量，可得 \\(F/(\\rho V^2d^2)\\)、\\(nd/V\\)、\\(\\rho Vd/\\mu\\) 三个无量纲数组，因此 \\[F=\\rho V^2d^2\\,\\Phi\\!\\left({nd\\over V},{\\rho Vd\\over\\mu}\\right).\\] 若改用 \\(\\rho,n,d\\) 作基本量，则等价写成 \\[F=\\rho n^2d^4\\,\\Psi\\!\\left({V\\over nd},{\\rho nd^2\\over\\mu}\\right).\\]",
      "boundaryNote": "按题面变量作 Buckingham Π 定理补全；量纲分析只能确定无量纲结构，不能给出经验函数。",
      "afterScore": {
        "chars": 760,
        "sentenceCount": 9,
        "formulaCount": 54,
        "proofSignalCount": 13
      },
      "htmlRel": "resources/fluid-181103-html/materials/01-fluid-181103-01-material/index.html",
      "htmlUpdated": true,
      "htmlUpdateReason": "",
      "proofDepthPass": true
    },
    {
      "id": "181103-material-extracted-0049",
      "sourceHtmlUrl": "/resources/fluid-181103-html/materials/01-fluid-181103-01-material/index.html#page-060",
      "sourceMaterialTitle": "流体力学习题解 余志豪",
      "sourcePage": 60,
      "type": "名词解释",
      "question": "2.2 试用欧拉观点导出柱坐标和球坐标中的连续方程。",
      "diagnosis": "原答案只给柱坐标结论，球坐标用“相应式”带过，缺少固定微元质量守恒推导。",
      "before": "柱坐标：\\(\\partial_t\\rho+\\frac1r\\partial_r(r\\rho v_r)+\\frac1r\\partial_\\theta(\\rho v_\\theta)+\\partial_z(\\rho v_z)=0\\)。球坐标按球对称/轴对称情形可化为解答给出的相应式，通式体现质量通量散度为零。",
      "boundaryNote": "球坐标中 (\theta,phi) 的命名随教材可互换，但尺度因子与散度结构不能省略。",
      "afterScore": {
        "chars": 922,
        "sentenceCount": 7,
        "formulaCount": 64,
        "proofSignalCount": 5
      },
      "htmlRel": "resources/fluid-181103-html/materials/01-fluid-181103-01-material/index.html",
      "htmlUpdated": true,
      "htmlUpdateReason": "",
      "proofDepthPass": true
    },
    {
      "id": "181103-material-extracted-0134",
      "sourceHtmlUrl": "/resources/fluid-181103-html/materials/01-fluid-181103-01-material/index.html#page-162",
      "sourceMaterialTitle": "流体力学习题解 余志豪",
      "sourcePage": 162,
      "type": "名词解释",
      "question": "3.22 水库与涡轮机之间有一涌浪槽（如图 3.3 所示）。若涡轮机的阀门突然关紧，试证明 \\(dy=-(aV/A)dt\\) 以及 \\(y-cV^2=(l/g)(dV/dt)\\)；并进一步证明模型与原型之间的相似关系。若模型与原型中各变量的数据如表所示，试求模型槽直径。",
      "diagnosis": "原答案把涌浪槽连续方程、非定常动量方程和模型相似条件压缩成几句，缺少逐步证明。",
      "before": "把涌浪槽水面升降 \\(y\\) 与管道流速 \\(V\\) 联立。连续性给槽内水量变化 \\(A\\,dy=-aV\\,dt\\)，即 \\(dy=-(aV/A)dt\\)。沿水库-涡轮机水道列非定常 Bernoulli 或动量平衡，可得 \\(y-cV^2=(l/g)dV/dt\\)。相似部分按源页表格关系整理为 \\(R_m=R(c/c_m)^2(l_m/l)(V/V_m)^2\\)。代入表中数据得 \\(A_m/a_m=6.67=d_m^2/0.05^2\\)，所以模型槽直径 \\(d_m\\approx0.129\\,\\mathrm m\\)。",
      "boundaryNote": "数值结论依赖源页表格；若缺表格，只能证明两个方程和相似无量纲组。",
      "afterScore": {
        "chars": 621,
        "sentenceCount": 15,
        "formulaCount": 39,
        "proofSignalCount": 11
      },
      "htmlRel": "resources/fluid-181103-html/materials/01-fluid-181103-01-material/index.html",
      "htmlUpdated": true,
      "htmlUpdateReason": "",
      "proofDepthPass": true
    },
    {
      "id": "181103-material-extracted-0013",
      "sourceHtmlUrl": "/resources/fluid-181103-html/materials/01-fluid-181103-01-material/index.html#page-014",
      "sourceMaterialTitle": "流体力学习题解 余志豪",
      "sourcePage": 14,
      "type": "名词解释",
      "question": "1.10 推导二维流动 \\(u=u_0,\\ v=v_0\\cos(kx-\\alpha t)\\) 的流线方程，并求 \\(t=0\\) 的流线和迹线方程。当 \\(k,\\alpha\\to0\\) 时，比较流线和迹线曲线。",
      "diagnosis": "原答案直接给流线和迹线公式，没有说明固定时刻积分、质点积分以及 (ku_0=alpha) 的特殊极限。",
      "before": "流线可写为 \\(y=(v_0/u_0k)\\sin(kx-\\alpha t)+c\\)；\\(t=0\\) 过原点为 \\(y=(v_0/u_0k)\\sin kx\\)。迹线过原点满足 \\(x=u_0t\\)，\\(y=\\frac{v_0}{ku_0-\\alpha}\\sin[(ku_0-\\alpha)t]\\)。当 \\(k,\\alpha\\to0\\) 时二者趋于直线 \\(y=(v_0/u_0)x\\)。",
      "boundaryNote": "迹线结论默认质点从原点出发；若初始点不同，只需加入积分常数。",
      "afterScore": {
        "chars": 663,
        "sentenceCount": 11,
        "formulaCount": 50,
        "proofSignalCount": 16
      },
      "htmlRel": "resources/fluid-181103-html/materials/01-fluid-181103-01-material/index.html",
      "htmlUpdated": true,
      "htmlUpdateReason": "",
      "proofDepthPass": true
    },
    {
      "id": "181103-material-extracted-0035",
      "sourceHtmlUrl": "/resources/fluid-181103-html/materials/01-fluid-181103-01-material/index.html#page-041",
      "sourceMaterialTitle": "流体力学习题解 余志豪",
      "sourcePage": 41,
      "type": "名词解释",
      "question": "1.36 对平面点涡速度场，证明速度势 \\(\\varphi=-\\Gamma\\theta/(2\\pi)\\)，并说明 \\(\\Gamma\\) 的意义。",
      "diagnosis": "原答案未说明极坐标积分、多值速度势和环量符号约定，只给出结论。",
      "before": "点涡速度为 \\(u=-\\frac{\\Gamma}{2\\pi}\\frac{y}{x^2+y^2}\\)、\\(v=\\frac{\\Gamma}{2\\pi}\\frac{x}{x^2+y^2}\\)，积分得 \\(\\varphi=-\\Gamma\\theta/(2\\pi)\\)。\\(\\Gamma\\) 为绕包含原点闭曲线的环量，即点涡强度。",
      "boundaryNote": "若教材把正点涡速度写为 (+Gamma/(2pi r))，速度势与环量符号需同步反向。",
      "afterScore": {
        "chars": 703,
        "sentenceCount": 10,
        "formulaCount": 45,
        "proofSignalCount": 13
      },
      "htmlRel": "resources/fluid-181103-html/materials/01-fluid-181103-01-material/index.html",
      "htmlUpdated": true,
      "htmlUpdateReason": "",
      "proofDepthPass": true
    },
    {
      "id": "181103-material-extracted-0046",
      "sourceHtmlUrl": "/resources/fluid-181103-html/materials/01-fluid-181103-01-material/index.html#page-052",
      "sourceMaterialTitle": "流体力学习题解 余志豪",
      "sourcePage": 52,
      "type": "名词解释",
      "question": "1.47 讨论由速度势 \\(\\varphi=-\\frac{a}{3}x(x^2-3y^2)\\) 所确定的运动，并求每秒通过 \\((0,0)\\) 与 \\((1,1)\\) 两点间直线段的流体体积，其中 \\(a>0\\)。",
      "diagnosis": "原答案只给流函数和流量，没有检查速度场、调和性、流量方向和正负号边界。",
      "before": "该势函数为调和函数，流动为二维不可压无旋流。流函数为 \\(\\psi=-\\frac{a}{3}y(3x^2-y^2)\\)，通过两点间任意曲线的流量为 \\(Q=\\psi(1,1)-\\psi(0,0)=-2a/3\\)（符号依所取法向）。",
      "boundaryNote": "保留有向流量和流量大小两种口径，避免把符号约定误当成计算错误。",
      "afterScore": {
        "chars": 700,
        "sentenceCount": 10,
        "formulaCount": 62,
        "proofSignalCount": 15
      },
      "htmlRel": "resources/fluid-181103-html/materials/01-fluid-181103-01-material/index.html",
      "htmlUpdated": true,
      "htmlUpdateReason": "",
      "proofDepthPass": true
    },
    {
      "id": "181103-material-extracted-0099",
      "sourceHtmlUrl": "/resources/fluid-181103-html/materials/01-fluid-181103-01-material/index.html#page-117",
      "sourceMaterialTitle": "流体力学习题解 余志豪",
      "sourcePage": 117,
      "type": "名词解释",
      "question": "2.51 已知半径为 \\(R\\) 的管道速度分布为 \\(u=u_0(1-y/R)^{1/m}\\)，其中 \\(y\\) 为距管壁距离、\\(u_0\\) 为轴线速度。证明皮托管放在距管壁 \\(0.25R\\) 处时，\\(m=4∼10\\) 时所测平均速度相对误差在约 \\(±5%\\) 内。",
      "diagnosis": "原答案没有统一 (y) 的定义，也没有写出截面平均速度和皮托读数误差公式。",
      "before": "速度分布为 \\(u=u_0(y/R)^{1/m}\\)（\\(y\\) 为距管壁距离）。距壁 \\(0.25R\\) 处的皮托管读数为 \\(u_p=u_0(1/4)^{1/m}\\)。对整个截面积积分可得平均速度 \\(\\bar V=u_0\\frac{2m^2}{(m+1)(2m+1)}\\)。比较 \\(u_p\\) 与 \\(\\bar V\\)，当 \\(m=4\\sim10\\) 时相对误差在约 \\(\\pm5\\%\\) 内；例如页图计算给出代表情形误差约 \\(-0.43\\%\\)。",
      "boundaryNote": "若源页原式写作 (u_0(1-y/R)^{1/m})，则 (y) 应改解为距轴距离；本答案显式按题面“距管壁”修正。",
      "afterScore": {
        "chars": 688,
        "sentenceCount": 15,
        "formulaCount": 51,
        "proofSignalCount": 5
      },
      "htmlRel": "resources/fluid-181103-html/materials/01-fluid-181103-01-material/index.html",
      "htmlUpdated": true,
      "htmlUpdateReason": "",
      "proofDepthPass": true
    },
    {
      "id": "181103-material-extracted-0132",
      "sourceHtmlUrl": "/resources/fluid-181103-html/materials/01-fluid-181103-01-material/index.html#page-160",
      "sourceMaterialTitle": "流体力学习题解 余志豪",
      "sourcePage": 160,
      "type": "名词解释",
      "question": "3.20 已知通过 V 型槽流量通式含水头 \\(H\\)、运动粘性系数 \\(\\nu\\) 和槽夹角 \\(\\theta\\)。90° 型槽水流量实用公式为 \\(Q=1.37H^{2.47}\\)。证明用该水流公式测量运动粘性系数为水 12 倍的另一流体流量时，相对误差约为 6%。",
      "diagnosis": "原答案只写“约 6%”，没有把经验指数 2.47 与黏性相似项联系起来。",
      "before": "V 型槽流量可写成 \\(Q=H^{5/2}\\Phi(\\nu/(H^{3/2}\\sqrt g),\\theta)\\)。对同一 \\(90^\\circ\\) 槽，若直接把水的经验式 \\(Q=1.37H^{2.47}\\) 用于运动粘性系数为水 12 倍的流体，会因粘性相似项改变而产生误差；按题中指数比较，估算流量约为真实流量的 \\(95\\%\\)，相对误差约 \\(5\\%\\) 到 \\(6\\%\\)。",
      "boundaryNote": "这是按经验指数反推黏性修正的近似证明，不是由理论唯一确定系数。",
      "afterScore": {
        "chars": 670,
        "sentenceCount": 18,
        "formulaCount": 32,
        "proofSignalCount": 8
      },
      "htmlRel": "resources/fluid-181103-html/materials/01-fluid-181103-01-material/index.html",
      "htmlUpdated": true,
      "htmlUpdateReason": "",
      "proofDepthPass": true
    },
    {
      "id": "181103-material-extracted-0151",
      "sourceHtmlUrl": "/resources/fluid-181103-html/materials/01-fluid-181103-01-material/index.html#page-181",
      "sourceMaterialTitle": "流体力学习题解 余志豪",
      "sourcePage": 181,
      "type": "名词解释",
      "question": "4.16（1）（2）同 0150：求球形滴内流线方程并比较固体小球与流体滴粘性阻力。",
      "diagnosis": "原答案写“同 0150”式描述，单独打开题卡时缺少流线形式、阻力公式和固体小球极限比较。",
      "before": "球形流体滴内部存在闭合循环流线，流线方程由内部流函数 \\(\\psi_i=C\\) 给出，典型形状与 \\(r^2(a^2-r^2)\\sin^2\\theta\\) 成正比。与同半径固体小球相比，流体滴表面允许切向速度连续并发生内部循环，界面切变较小，所以在同一外部速度下粘性阻力小于固体小球的 \\(6\\pi\\mu_eaU\\)。",
      "boundaryNote": "本条是重复题卡的独立可读答案，避免学生从单题入口看到“同 0150”后无从作答。",
      "afterScore": {
        "chars": 535,
        "sentenceCount": 9,
        "formulaCount": 30,
        "proofSignalCount": 12
      },
      "htmlRel": "resources/fluid-181103-html/materials/01-fluid-181103-01-material/index.html",
      "htmlUpdated": true,
      "htmlUpdateReason": "",
      "proofDepthPass": true
    },
    {
      "id": "181103-material-extracted-0153",
      "sourceHtmlUrl": "/resources/fluid-181103-html/materials/01-fluid-181103-01-material/index.html#page-182",
      "sourceMaterialTitle": "流体力学习题解 余志豪",
      "sourcePage": 182,
      "type": "名词解释",
      "question": "4.17 一小球在无界粘性不可压流体中以匀角速度 \\(\\omega\\) 绕某轴线缓慢转动，求小球所受阻力的合力矩。",
      "diagnosis": "原答案只给最终力矩，没有切向速度解、边界条件、剪应力和球面积分。",
      "before": "小球缓慢转动时只有绕轴的切向速度分量。解球坐标 Stokes 方程并用边界条件 \\(v_\\varphi(a)=\\omega a\\sin\\theta\\)、\\(v_\\varphi(\\infty)=0\\)，可得粘性切应力对球面积分后的阻力合力矩 \\[M=8\\pi\\mu a^3\\omega.\\]",
      "boundaryNote": "答案给出力矩大小和方向；符号若按外力矩维持转动则与阻力矩相反。",
      "afterScore": {
        "chars": 672,
        "sentenceCount": 9,
        "formulaCount": 37,
        "proofSignalCount": 8
      },
      "htmlRel": "resources/fluid-181103-html/materials/01-fluid-181103-01-material/index.html",
      "htmlUpdated": true,
      "htmlUpdateReason": "",
      "proofDepthPass": true
    },
    {
      "id": "181103-material-extracted-0306",
      "sourceHtmlUrl": "/resources/fluid-181103-html/materials/09-fluid-181103-09-2010/index.html#page-003",
      "sourceMaterialTitle": "流体力学习题册答案2010修改版",
      "sourcePage": 3,
      "type": "名词解释",
      "question": "习题一第5题参考答案：证明满足 a·(P·a)=0 的张量 P 为反对称张量。",
      "diagnosis": "当前为 source-clue 定位卡，题面要求证明反对称张量，缺少必要性和充分性。",
      "before": "资料定位：习题一第5题参考答案：证明满足 a·(P·a)=0 的张量 P 为反对称张量。该卡用于定位 第 3 页 的讲义正文、续页、章节标题或上下文证据，帮助学生在站内直接阅读 181103 HTML。来源边界：本条不进入默认刷题池，只有已确认题干和答案的独立条目才会进入题库刷题。",
      "boundaryNote": "证明要求“任意向量”成立；若只对某一个向量成立，不能推出 (P) 反对称。",
      "afterScore": {
        "chars": 727,
        "sentenceCount": 13,
        "formulaCount": 47,
        "proofSignalCount": 17
      },
      "htmlRel": "resources/fluid-181103-html/materials/09-fluid-181103-09-2010/index.html",
      "htmlUpdated": true,
      "htmlUpdateReason": "",
      "proofDepthPass": true
    },
    {
      "id": "181103-material-extracted-0317",
      "sourceHtmlUrl": "/resources/fluid-181103-html/materials/09-fluid-181103-09-2010/index.html#page-014",
      "sourceMaterialTitle": "流体力学习题册答案2010修改版",
      "sourcePage": 14,
      "type": "名词解释",
      "question": "习题五第1题参考答案：用量纲分析求管流流量与压差、黏度、长度和管径之间的关系。",
      "diagnosis": "当前为 source-clue 定位卡，题面要求量纲分析关系，但没有无量纲组和比例结论。",
      "before": "资料定位：习题五第1题参考答案：用量纲分析求管流流量与压差、黏度、长度和管径之间的关系。该卡用于定位 第 14 页 的讲义正文、续页、章节标题或上下文证据，帮助学生在站内直接阅读 181103 HTML。来源边界：本条不进入默认刷题池，只有已确认题干和答案的独立条目才会进入题库刷题。",
      "boundaryNote": "保持量纲分析与精确管流解的边界；常数不能靠 Π 定理单独推出。",
      "afterScore": {
        "chars": 621,
        "sentenceCount": 11,
        "formulaCount": 45,
        "proofSignalCount": 12
      },
      "htmlRel": "resources/fluid-181103-html/materials/09-fluid-181103-09-2010/index.html",
      "htmlUpdated": true,
      "htmlUpdateReason": "",
      "proofDepthPass": true
    },
    {
      "id": "181103-material-extracted-0318",
      "sourceHtmlUrl": "/resources/fluid-181103-html/materials/09-fluid-181103-09-2010/index.html#page-015",
      "sourceMaterialTitle": "流体力学习题册答案2010修改版",
      "sourcePage": 15,
      "type": "名词解释",
      "question": "习题五第2题参考答案：用量纲分析确定水跃高度比 H/h 与雷诺数、弗劳德数等无量纲数的关系。",
      "diagnosis": "当前为 source-clue 定位卡，题面要求水跃高度比的无量纲关系，答案只提示页码。",
      "before": "资料定位：习题五第2题参考答案：用量纲分析确定水跃高度比 \\(H/h\\) 与雷诺数、弗劳德数等无量纲数的关系。该卡用于定位 第 15 页 的讲义正文、续页、章节标题或上下文证据，帮助学生在站内直接阅读 181103 HTML。来源边界：本条不进入默认刷题池，只有已确认题干和答案的独立条目才会进入题库刷题。",
      "boundaryNote": "答案区分量纲关系和动量方程精确共轭水深公式，避免过claim。",
      "afterScore": {
        "chars": 471,
        "sentenceCount": 9,
        "formulaCount": 38,
        "proofSignalCount": 12
      },
      "htmlRel": "resources/fluid-181103-html/materials/09-fluid-181103-09-2010/index.html",
      "htmlUpdated": true,
      "htmlUpdateReason": "",
      "proofDepthPass": true
    },
    {
      "id": "181103-material-extracted-0324",
      "sourceHtmlUrl": "/resources/fluid-181103-html/materials/09-fluid-181103-09-2010/index.html#page-023",
      "sourceMaterialTitle": "流体力学习题册答案2010修改版",
      "sourcePage": 23,
      "type": "名词解释",
      "question": "习题六第15题参考答案：取柱形微元体作为欧拉控制体，推导平面辐射流动柱坐标动量方程的 R 方向形式。",
      "diagnosis": "当前为 source-clue 定位卡，题面要求柱坐标径向动量方程推导，没有给方程。",
      "before": "资料定位：习题六第15题参考答案：取柱形微元体作为欧拉控制体，推导平面辐射流动柱坐标动量方程的 R 方向形式。该卡用于定位 第 23 页 的讲义正文、续页、章节标题或上下文证据，帮助学生在站内直接阅读 181103 HTML。来源边界：本条不进入默认刷题池，只有已确认题干和答案的独立条目才会进入题库刷题。",
      "boundaryNote": "按“平面辐射流动”取 (v_\theta=0)；有周向速度时需另加向心项。",
      "afterScore": {
        "chars": 682,
        "sentenceCount": 9,
        "formulaCount": 50,
        "proofSignalCount": 8
      },
      "htmlRel": "resources/fluid-181103-html/materials/09-fluid-181103-09-2010/index.html",
      "htmlUpdated": true,
      "htmlUpdateReason": "",
      "proofDepthPass": true
    },
    {
      "id": "181103-material-extracted-0325",
      "sourceHtmlUrl": "/resources/fluid-181103-html/materials/09-fluid-181103-09-2010/index.html#page-024",
      "sourceMaterialTitle": "流体力学习题册答案2010修改版",
      "sourcePage": 24,
      "type": "名词解释",
      "question": "习题六第16题参考答案：取固定平行六面体微元控制体，推导能量守恒方程并得到最简形式。",
      "diagnosis": "当前为 source-clue 定位卡，题面要求推导能量守恒最简形式，缺少总能、动能和内能方程相减。",
      "before": "资料定位：习题六第16题参考答案：取固定平行六面体微元控制体，推导能量守恒方程并得到最简形式。该卡用于定位 第 24 页 的讲义正文、续页、章节标题或上下文证据，帮助学生在站内直接阅读 181103 HTML。来源边界：本条不进入默认刷题池，只有已确认题干和答案的独立条目才会进入题库刷题。",
      "boundaryNote": "该式为理想流体、绝热且无黏性耗散形式；若源题包含热量或黏性项，应补入相应项。",
      "afterScore": {
        "chars": 713,
        "sentenceCount": 7,
        "formulaCount": 47,
        "proofSignalCount": 7
      },
      "htmlRel": "resources/fluid-181103-html/materials/09-fluid-181103-09-2010/index.html",
      "htmlUpdated": true,
      "htmlUpdateReason": "",
      "proofDepthPass": true
    },
    {
      "id": "181103-material-extracted-0326",
      "sourceHtmlUrl": "/resources/fluid-181103-html/materials/09-fluid-181103-09-2010/index.html#page-026",
      "sourceMaterialTitle": "流体力学习题册答案2010修改版",
      "sourcePage": 26,
      "type": "名词解释",
      "question": "习题六第17题参考答案：以平板滑动方向建立坐标系，推导不定常平板流动的应力张量、动量方程和边界条件。",
      "diagnosis": "当前为 source-clue 定位卡，题面要求不定常平板流动的应力、方程和边界条件，答案只有定位。",
      "before": "资料定位：习题六第17题参考答案：以平板滑动方向建立坐标系，推导不定常平板流动的应力张量、动量方程和边界条件。该卡用于定位 第 26 页 的讲义正文、续页、章节标题或上下文证据，帮助学生在站内直接阅读 181103 HTML。来源边界：本条不进入默认刷题池，只有已确认题干和答案的独立条目才会进入题库刷题。",
      "boundaryNote": "按 Stokes 第一问题补全；题面未给 (U(t)) 时不强行固定瞬时启动解。",
      "afterScore": {
        "chars": 644,
        "sentenceCount": 9,
        "formulaCount": 52,
        "proofSignalCount": 15
      },
      "htmlRel": "resources/fluid-181103-html/materials/09-fluid-181103-09-2010/index.html",
      "htmlUpdated": true,
      "htmlUpdateReason": "",
      "proofDepthPass": true
    },
    {
      "id": "181103-material-extracted-0344",
      "sourceHtmlUrl": "/resources/fluid-181103-html/materials/09-fluid-181103-09-2010/index.html#page-044",
      "sourceMaterialTitle": "流体力学习题册答案2010修改版",
      "sourcePage": 44,
      "type": "名词解释",
      "question": "习题九第5题参考答案：如图建立坐标系，求自由面无切应力边界条件下的竖向黏性流动速度和流量。",
      "diagnosis": "当前为 source-clue 定位卡，题面给自由面无切应力条件但没有速度分布和流量公式。",
      "before": "资料定位：习题九第5题参考答案：如图建立坐标系，求自由面无切应力边界条件下的竖向黏性流动速度和流量。该卡用于定位 第 44 页 的讲义正文、续页、章节标题或上下文证据，帮助学生在站内直接阅读 181103 HTML。来源边界：本条不进入默认刷题池，只有已确认题干和答案的独立条目才会进入题库刷题。",
      "boundaryNote": "符号取决于 (z) 轴正向和压强梯度定义；答案显式用 (G) 收纳驱动力。",
      "afterScore": {
        "chars": 535,
        "sentenceCount": 10,
        "formulaCount": 51,
        "proofSignalCount": 16
      },
      "htmlRel": "resources/fluid-181103-html/materials/09-fluid-181103-09-2010/index.html",
      "htmlUpdated": true,
      "htmlUpdateReason": "",
      "proofDepthPass": true
    },
    {
      "id": "181103-material-extracted-0349",
      "sourceHtmlUrl": "/resources/fluid-181103-html/materials/09-fluid-181103-09-2010/index.html#page-049",
      "sourceMaterialTitle": "流体力学习题册答案2010修改版",
      "sourcePage": 49,
      "type": "名词解释",
      "question": "习题九第11题参考答案：由第7题运动方程求旋转圆柱外无限域流动的速度、应力和维持运动所需力矩。",
      "diagnosis": "当前为 source-clue 定位卡，题面要求旋转圆柱外速度、应力和力矩，缺少完整推导。",
      "before": "资料定位：习题九第11题参考答案：由第7题运动方程求旋转圆柱外无限域流动的速度、应力和维持运动所需力矩。该卡用于定位 第 49 页 的讲义正文、续页、章节标题或上下文证据，帮助学生在站内直接阅读 181103 HTML。来源边界：本条不进入默认刷题池，只有已确认题干和答案的独立条目才会进入题库刷题。",
      "boundaryNote": "按无限长圆柱单位长度给出；有限长度需另乘长度并考虑端部效应。",
      "afterScore": {
        "chars": 659,
        "sentenceCount": 11,
        "formulaCount": 44,
        "proofSignalCount": 7
      },
      "htmlRel": "resources/fluid-181103-html/materials/09-fluid-181103-09-2010/index.html",
      "htmlUpdated": true,
      "htmlUpdateReason": "",
      "proofDepthPass": true
    },
    {
      "id": "181103-material-extracted-0350",
      "sourceHtmlUrl": "/resources/fluid-181103-html/materials/09-fluid-181103-09-2010/index.html#page-050",
      "sourceMaterialTitle": "流体力学习题册答案2010修改版",
      "sourcePage": 50,
      "type": "名词解释",
      "question": "习题九第12题参考答案：证明零压梯度平板定常层流边界层动量积分，并求边界层厚度和位移厚度关系。",
      "diagnosis": "当前为 source-clue 定位卡，题面要求证明动量积分并讨论厚度关系，答案仅定位页码。",
      "before": "资料定位：习题九第12题参考答案：证明零压梯度平板定常层流边界层动量积分，并求边界层厚度和位移厚度关系。该卡用于定位 第 50 页 的讲义正文、续页、章节标题或上下文证据，帮助学生在站内直接阅读 181103 HTML。来源边界：本条不进入默认刷题池，只有已确认题干和答案的独立条目才会进入题库刷题。",
      "boundaryNote": "未给具体速度剖面时只给通用积分关系，不伪造唯一厚度比例。",
      "afterScore": {
        "chars": 836,
        "sentenceCount": 8,
        "formulaCount": 72,
        "proofSignalCount": 19
      },
      "htmlRel": "resources/fluid-181103-html/materials/09-fluid-181103-09-2010/index.html",
      "htmlUpdated": true,
      "htmlUpdateReason": "",
      "proofDepthPass": true
    },
    {
      "id": "181103-material-extracted-0351",
      "sourceHtmlUrl": "/resources/fluid-181103-html/materials/09-fluid-181103-09-2010/index.html#page-050",
      "sourceMaterialTitle": "流体力学习题册答案2010修改版",
      "sourcePage": 50,
      "type": "名词解释",
      "question": "习题九第13题参考答案：用相似变量和流函数推导边界层方程及其边界条件。",
      "diagnosis": "当前为 source-clue 定位卡，题面要求相似变量、流函数、方程和边界条件，缺少可学习推导。",
      "before": "资料定位：习题九第13题参考答案：用相似变量和流函数推导边界层方程及其边界条件。该卡用于定位 第 50 页 的讲义正文、续页、章节标题或上下文证据，帮助学生在站内直接阅读 181103 HTML。来源边界：本条不进入默认刷题池，只有已确认题干和答案的独立条目才会进入题库刷题。",
      "boundaryNote": "相似变量系数依教材定义可差常数；方程结构和边界条件应保持一致。",
      "afterScore": {
        "chars": 664,
        "sentenceCount": 8,
        "formulaCount": 65,
        "proofSignalCount": 17
      },
      "htmlRel": "resources/fluid-181103-html/materials/09-fluid-181103-09-2010/index.html",
      "htmlUpdated": true,
      "htmlUpdateReason": "",
      "proofDepthPass": true
    },
    {
      "id": "181103-material-extracted-0378",
      "sourceHtmlUrl": "/resources/fluid-181103-html/materials/38-fluid-181103-38-3-3/index.html#page-007",
      "sourceMaterialTitle": "未命名 3",
      "sourcePage": 7,
      "type": "填空题",
      "question": "习题三第1题参考答案：由不可压与定常条件证明速度沿等密度面方向，并说明反向命题。",
      "diagnosis": "当前为 source-clue 定位卡，题面要求由定常不可压证明速度沿等密度面，并说明反向命题。",
      "before": "资料定位：习题三第1题参考答案：由不可压与定常条件证明速度沿等密度面方向，并说明反向命题。该卡用于定位 第 7 页 的讲义正文、续页、章节标题或上下文证据，帮助学生在站内直接阅读 181103 HTML。来源边界：本条不进入默认刷题池，只有已确认题干和答案的独立条目才会进入题库刷题。",
      "boundaryNote": "反向命题依赖定常和非零密度；不定常密度场中速度沿等密度面不足以推出不可压。",
      "afterScore": {
        "chars": 640,
        "sentenceCount": 10,
        "formulaCount": 53,
        "proofSignalCount": 16
      },
      "htmlRel": "resources/fluid-181103-html/materials/38-fluid-181103-38-3-3/index.html",
      "htmlUpdated": true,
      "htmlUpdateReason": "",
      "proofDepthPass": true
    },
    {
      "id": "181103-material-extracted-0386",
      "sourceHtmlUrl": "/resources/fluid-181103-html/materials/38-fluid-181103-38-3-3/index.html#page-016",
      "sourceMaterialTitle": "未命名 3",
      "sourcePage": 16,
      "type": "填空题",
      "question": "习题六第1题参考答案：由给定运动边界面方程和物质面条件，求边界面上任一点的法向速度。",
      "diagnosis": "当前为 source-clue 定位卡，题面要求运动边界面法向速度，但答案没有物质面条件。",
      "before": "资料定位：习题六第1题参考答案：由给定运动边界面方程和物质面条件，求边界面上任一点的法向速度。该卡用于定位 第 16 页 的讲义正文、续页、章节标题或上下文证据，帮助学生在站内直接阅读 181103 HTML。来源边界：本条不进入默认刷题池，只有已确认题干和答案的独立条目才会进入题库刷题。",
      "boundaryNote": "按物质面运动学边界条件补全；若题面给特殊面方程，直接代入 (F) 即可。",
      "afterScore": {
        "chars": 700,
        "sentenceCount": 9,
        "formulaCount": 63,
        "proofSignalCount": 24
      },
      "htmlRel": "resources/fluid-181103-html/materials/38-fluid-181103-38-3-3/index.html",
      "htmlUpdated": true,
      "htmlUpdateReason": "",
      "proofDepthPass": true
    },
    {
      "id": "181103-material-extracted-0396",
      "sourceHtmlUrl": "/resources/fluid-181103-html/materials/38-fluid-181103-38-3-3/index.html#page-031",
      "sourceMaterialTitle": "未命名 3",
      "sourcePage": 31,
      "type": "填空题",
      "question": "习题八第6题参考答案：求偶相对于半径为 a 的圆的像，证明像偶强度与原偶强度之比，并求圆柱外的偶作用在圆柱上的力。",
      "diagnosis": "当前为 source-clue 定位卡，题面要求圆外偶极像、强度比和圆柱受力，答案没有复势框架。",
      "before": "资料定位：习题八第6题参考答案：求偶相对于半径为 a 的圆的像，证明像偶强度与原偶强度之比，并求圆柱外的偶作用在圆柱上的力。该卡用于定位 第 31 页 的讲义正文、续页、章节标题或上下文证据，帮助学生在站内直接阅读 181103 HTML。来源边界：本条不进入默认刷题池，只有已确认题干和答案的独立条目才会进入题库刷题。",
      "boundaryNote": "当前 JSON 题面缺偶极位置/方向；本答案给出可计算框架并明确不能凭空给唯一数值。",
      "afterScore": {
        "chars": 589,
        "sentenceCount": 9,
        "formulaCount": 37,
        "proofSignalCount": 13
      },
      "htmlRel": "resources/fluid-181103-html/materials/38-fluid-181103-38-3-3/index.html",
      "htmlUpdated": true,
      "htmlUpdateReason": "",
      "proofDepthPass": true
    },
    {
      "id": "181103-material-extracted-0399",
      "sourceHtmlUrl": "/resources/fluid-181103-html/materials/38-fluid-181103-38-3-3/index.html#page-036",
      "sourceMaterialTitle": "未命名 3",
      "sourcePage": 36,
      "type": "填空题",
      "question": "习题八第18题参考答案：建立静止坐标系下运动圆柱的势流问题，求速度势/速度场、流体动能及圆柱惯性阻力。",
      "diagnosis": "当前为 source-clue 定位卡，题面要求运动圆柱势函数、速度、动能和惯性阻力。",
      "before": "资料定位：习题八第18题参考答案：建立静止坐标系下运动圆柱的势流问题，求速度势/速度场、流体动能及圆柱惯性阻力。该卡用于定位 第 36 页 的讲义正文、续页、章节标题或上下文证据，帮助学生在站内直接阅读 181103 HTML。来源边界：本条不进入默认刷题池，只有已确认题干和答案的独立条目才会进入题库刷题。",
      "boundaryNote": "按无限域、单位长度圆柱给出；有限边界或不同运动方向需重写边界条件。",
      "afterScore": {
        "chars": 741,
        "sentenceCount": 9,
        "formulaCount": 48,
        "proofSignalCount": 10
      },
      "htmlRel": "resources/fluid-181103-html/materials/38-fluid-181103-38-3-3/index.html",
      "htmlUpdated": true,
      "htmlUpdateReason": "",
      "proofDepthPass": true
    },
    {
      "id": "181103-material-extracted-0403",
      "sourceHtmlUrl": "/resources/fluid-181103-html/materials/38-fluid-181103-38-3-3/index.html#page-043",
      "sourceMaterialTitle": "未命名 3",
      "sourcePage": 43,
      "type": "填空题",
      "question": "习题九第7题参考答案：求同轴圆筒间旋转粘性流在内管固定/外管固定情形下的速度分布、压强分布、应力和管壁摩擦力矩。",
      "diagnosis": "当前为 source-clue 定位卡，题面要求同轴圆筒旋转流速度、压强、应力和力矩，缺少完整公式。",
      "before": "资料定位：习题九第7题参考答案：求同轴圆筒间旋转粘性流在内管固定/外管固定情形下的速度分布、压强分布、应力和管壁摩擦力矩。该卡用于定位 第 43 页 的讲义正文、续页、章节标题或上下文证据，帮助学生在站内直接阅读 181103 HTML。来源边界：本条不进入默认刷题池，只有已确认题干和答案的独立条目才会进入题库刷题。",
      "boundaryNote": "用通式覆盖内管固定/外管固定；若源页采用相反角速度符号，(B) 与力矩方向同步变号。",
      "afterScore": {
        "chars": 749,
        "sentenceCount": 9,
        "formulaCount": 51,
        "proofSignalCount": 9
      },
      "htmlRel": "resources/fluid-181103-html/materials/38-fluid-181103-38-3-3/index.html",
      "htmlUpdated": true,
      "htmlUpdateReason": "",
      "proofDepthPass": true
    },
    {
      "id": "181103-material-extracted-0408",
      "sourceHtmlUrl": "/resources/fluid-181103-html/materials/38-fluid-181103-38-3-3/index.html#page-048",
      "sourceMaterialTitle": "未命名 3",
      "sourcePage": 48,
      "type": "证明推导题",
      "question": "习题九第13题参考答案：引入相似变量和流函数，将边界层方程化为相似常微分方程，并给出边界条件。",
      "diagnosis": "当前为 source-clue 定位卡，题面要求边界层相似方程，答案没有速度表达、ODE 和边界条件。",
      "before": "资料定位：习题九第13题参考答案：引入相似变量和流函数，将边界层方程化为相似常微分方程，并给出边界条件。该卡用于定位 第 48 页 的讲义正文、续页、章节标题或上下文证据，帮助学生在站内直接阅读 181103 HTML。来源边界：本条不进入默认刷题池，只有已确认题干和答案的独立条目才会进入题库刷题。",
      "boundaryNote": "若源题写成无 (+m) 项的方程，应核对其压力梯度项或归一化定义；本答案按标准 Falkner-Skan 推导。",
      "afterScore": {
        "chars": 608,
        "sentenceCount": 9,
        "formulaCount": 48,
        "proofSignalCount": 20
      },
      "htmlRel": "resources/fluid-181103-html/materials/38-fluid-181103-38-3-3/index.html",
      "htmlUpdated": true,
      "htmlUpdateReason": "",
      "proofDepthPass": true
    },
    {
      "id": "181103-material-extracted-0499",
      "sourceHtmlUrl": "/resources/fluid-181103-html/materials/03-fluid-181103-03-material/index.html#page-010",
      "sourceMaterialTitle": "练习册",
      "sourcePage": 10,
      "type": "计算与分析题",
      "question": "10. 求圆柱外之源作用在圆柱上的力，取圆柱高为一个单位。",
      "diagnosis": "可见答案只有“用像法/积分”的方法句，缺少像系、速度、压强积分和单位高度受力表达。",
      "before": "圆柱外源用 Milne-Thomson 圆定理或反演像法处理，在圆内配置像源/像汇以使圆周为流线。由圆柱表面速度求压强，再沿圆周积分压强的水平与竖直分量，得到圆柱外源对单位高度圆柱的作用力。",
      "boundaryNote": "按外源在实轴 (b>a) 和常见二维源强约定给出；不同源强规范只改变系数。",
      "afterScore": {
        "chars": 604,
        "sentenceCount": 9,
        "formulaCount": 34,
        "proofSignalCount": 12
      },
      "htmlRel": "resources/fluid-181103-html/materials/03-fluid-181103-03-material/index.html",
      "htmlUpdated": true,
      "htmlUpdateReason": "",
      "proofDepthPass": true
    },
    {
      "id": "181103-material-extracted-0500",
      "sourceHtmlUrl": "/resources/fluid-181103-html/materials/03-fluid-181103-03-material/index.html#page-010",
      "sourceMaterialTitle": "练习册",
      "sourcePage": 10,
      "type": "计算与分析题",
      "question": "11. 求圆柱外之偶作用在圆柱上的力，取圆柱高为一个单位。",
      "diagnosis": "可见答案只说用圆定理，缺少像偶强度、边界验证、受力积分以及参数不足边界。",
      "before": "圆柱外偶极同样用圆定理构造圆内像偶极与必要的补偿项，使 \\(|z|=a\\) 为流线。求得复势后由 \\(dW/dz\\) 得表面速度，代入 Bernoulli 压强并沿圆周积分，即得单位高度圆柱所受力。",
      "boundaryNote": "不伪造缺失参数下的唯一力；给出可代入的完整复势和受力公式。",
      "afterScore": {
        "chars": 567,
        "sentenceCount": 8,
        "formulaCount": 37,
        "proofSignalCount": 7
      },
      "htmlRel": "resources/fluid-181103-html/materials/03-fluid-181103-03-material/index.html",
      "htmlUpdated": true,
      "htmlUpdateReason": "",
      "proofDepthPass": true
    },
    {
      "id": "181103-material-extracted-0501",
      "sourceHtmlUrl": "/resources/fluid-181103-html/materials/03-fluid-181103-03-material/index.html#page-010",
      "sourceMaterialTitle": "练习册",
      "sourcePage": 10,
      "type": "计算与分析题",
      "question": "12. 设半径为 \\(a\\) 的圆外有一源 \\(m\\) 和汇 \\((-m)\\)，在极坐标系下，它们分别位于 \\((r_1,0)\\) 和 \\((r_2,\\alpha)\\) 处，求流场的复势，并研究 \\(\\alpha=\\pi\\) 且 \\(r_1=r_2\\) 的情况。",
      "diagnosis": "可见答案只有方法轮廓，缺少源汇复势、像点和特殊情形化简。",
      "before": "分别对圆外的源 \\(m\\) 和汇 \\((-m)\\) 使用圆定理，在反演点布置相应像点以满足圆边界不可穿透条件，复势为各源、汇及像点对数势的叠加。当 \\(\\alpha=\\pi\\) 且 \\(r_1=r_2\\) 时，源汇关于圆心成对称布置，复势和流线相应化简为轴对称形式。",
      "boundaryNote": "假设源汇均在圆外且采用常见二维源强 (m/(2pi)log) 规范。",
      "afterScore": {
        "chars": 571,
        "sentenceCount": 9,
        "formulaCount": 36,
        "proofSignalCount": 11
      },
      "htmlRel": "resources/fluid-181103-html/materials/03-fluid-181103-03-material/index.html",
      "htmlUpdated": true,
      "htmlUpdateReason": "",
      "proofDepthPass": true
    },
    {
      "id": "181103-material-extracted-0521",
      "sourceHtmlUrl": "/resources/fluid-181103-html/materials/03-fluid-181103-03-material/index.html#page-012",
      "sourceMaterialTitle": "练习册",
      "sourcePage": 12,
      "type": "证明题",
      "question": "13. 如果平板附近稳定状态边界层外的外部流动为 \\(U=cx^m\\)，式中 \\(c>0\\) 与 \\(m\\) 为常数，引入变换：\\(\\psi=\\sqrt{\\gamma Ux}\\,f(\\eta)\\)，\\(\\eta=\\sqrt{\\frac{U}{\\gamma x}}\\,y\\)。证明边界层方程可以化为：\\(m(f')^2-\\frac12(m+1)ff''=f'''\\)。其中 \\(f(0)=f'(0)=0\\)，\\(f''(\\delta)=0\\)；\\(f'(\\eta)\\to1\\)，\\(\\eta\\to\\infty\\)。",
      "diagnosis": "原答案虽较长，但对外压梯度项与题设 ODE 的差异提示不够清晰，学生容易把缺项方程当作已证明。",
      "before": "由 \\(\\psi=\\sqrt{\\gamma Ux}\\,f(\\eta)\\)、\\(\\eta=y\\sqrt{U/(\\gamma x)}\\)、\\(U=cx^m\\) 得 \\(u=\\partial\\psi/\\partial y=Uf\\prime\\)，且由连续性给出 \\(v=-\\partial\\psi/\\partial x=-\\sqrt{\\gamma U/x}\\,[\\tfrac12(m+1)f+\\tfrac12(m-1)\\eta f\\prime]\\)。代入边界层方程 \\(u u_x+v u_y=U dU/dx+\\gamma u_",
      "boundaryNote": "把题设方程疑点直接写入答案，防止学生背下缺外压梯度项的错误证明。",
      "afterScore": {
        "chars": 676,
        "sentenceCount": 8,
        "formulaCount": 47,
        "proofSignalCount": 16
      },
      "htmlRel": "resources/fluid-181103-html/materials/03-fluid-181103-03-material/index.html",
      "htmlUpdated": true,
      "htmlUpdateReason": "",
      "proofDepthPass": true
    }
  ],
  "studentAnswerBoundary": "Round536 stores student-facing proof/process answers in the bank and keeps diagnosis/boundary notes in the QA ledger; these notes are not strict original-answer PDF proof.",
  "remainingBoundary": "Round536 sixth batch upgrades 30 proof/process/source-clue rows after Round531-Round535; remaining suspicious proof rows stay in the next-round queue and must not be claimed complete.",
  "qualityBoundary": "Round536 treats source-clue cards, conclusion-only proof answers, method-only answer blocks, and same-as-above references as insufficient whenever a student-facing answer block is visible.",
  "correctnessBoundary": "Round536 records sign conventions, missing source parameters, source-equation discrepancies, and dimensional-boundary notes instead of forcing false certainty.",
  "strictAnswerPdfProofBoundary": "strictAnswerPdfProof remains separate; Round536 does not claim original-answer-PDF span/bbox/hash proof."
}
