{
  "ok": true,
  "version": "round333-real-exam-source-cardinality-20260615",
  "generatedAt": "2026-06-15T03:55:00+08:00",
  "sourceFiles": {
    "round307": "data/fluid-round307-real-exam-source-row-year-count-lock.json",
    "round324": "data/fluid-round324-real-exam-expanded-count-guard.json",
    "round325": "data/fluid-round325-real-exam-answer-no-merge.json",
    "round324Checker": "tools/check-round324-real-exam-expanded-count-guard.mjs",
    "yearPacks": "question-banks/real-exam-years/*.json"
  },
  "expected": {
    "sourceAtomicQuestionCount": 325,
    "webAtomicQuestionCount": 325,
    "groupedSectionCount": 68,
    "groupedWebQuestionIdCount": 217,
    "fourFiveQuestionLockCount": 18,
    "fourFiveQuestionAtomicCount": 77,
    "fiveItemShortAnswerLockCount": 5,
    "fiveItemShortAnswerAtomicCount": 25,
    "criticalYearCount": 9,
    "criticalGroupedSectionCount": 27,
    "failedCriticalStructureCount": 0,
    "failedCheckCount": 0
  },
  "policy": {
    "rule": "Some years have original short-answer/concept sections with exactly five independent source questions. Those sections must remain five web question IDs and cannot be merged into one parent prompt.",
    "releaseBlocking": [
      "source/web atomic questions must stay 325/325",
      "grouped source sections must stay 68 and grouped web subquestions must stay 217",
      "all 18 four/five source rows must stay locked",
      "the five-item short-answer keys 2010-02, 2015-01, 2018-01, 2019-01, 2020-01 must each expose item numbers 1-5",
      "critical year structures for 2000, 2001, 2004, 2008, 2010, 2015, 2018, 2020, and 2023 must be materialized in this ledger"
    ]
  },
  "summary": {
    "sourceAtomicQuestionCount": 325,
    "webAtomicQuestionCount": 325,
    "groupedSectionCount": 68,
    "groupedWebQuestionIdCount": 217,
    "fourFiveQuestionLockCount": 18,
    "fourFiveQuestionAtomicCount": 77,
    "fiveItemShortAnswerLockCount": 5,
    "fiveItemShortAnswerAtomicCount": 25,
    "criticalYearCount": 9,
    "criticalGroupedSectionCount": 27,
    "failedCriticalStructureCount": 0,
    "passCount": 7,
    "failCount": 0
  },
  "round325Authority": {
    "version": "round325-real-exam-answer-no-merge-20260615",
    "ok": true,
    "summary": {
      "sourceAtomicQuestionCount": 325,
      "webAtomicQuestionCount": 325,
      "groupedSectionCount": 68,
      "groupedWebQuestionIdCount": 217,
      "fiveItemShortAnswerLockedCount": 5,
      "strictAnswerEvidenceOnAligned": 0
    }
  },
  "groupLedger": {
    "id": "all-grouped-source-sections",
    "label": "全部 grouped / multi-part source rows",
    "expected": {
      "sourceSectionCount": 68,
      "atomicQuestionCount": 217
    },
    "actual": {
      "sourceSectionCount": 68,
      "atomicQuestionCount": 217,
      "lockedSourceSectionCount": 68
    },
    "anchor": {
      "keys": [
        "2000-02",
        "2000-03",
        "2000-06",
        "2000-07",
        "2000-08",
        "2001-06",
        "2002-08",
        "2003-07",
        "2004-01",
        "2004-02",
        "2005-01",
        "2005-02",
        "2005-03",
        "2005-06",
        "2005-07",
        "2005-08",
        "2006-01",
        "2006-02",
        "2006-06",
        "2007-01",
        "2007-02",
        "2007-03",
        "2007-04",
        "2007-07",
        "2007-08",
        "2008-01",
        "2008-03",
        "2010-01",
        "2010-02",
        "2010-05",
        "2011-01",
        "2011-02",
        "2012-01",
        "2012-02",
        "2012-05",
        "2012-06",
        "2012-07",
        "2013-02",
        "2013-03",
        "2014-01",
        "2014-02",
        "2014-03",
        "2015-01",
        "2015-02",
        "2015-04",
        "2015-05",
        "2018-01",
        "2018-04",
        "2018-05",
        "2018-06",
        "2019-01",
        "2019-02",
        "2019-03",
        "2019-04",
        "2019-05",
        "2020-01",
        "2020-02",
        "2020-04",
        "2020-05",
        "2020-06",
        "2021-06",
        "2021-09",
        "2023-09",
        "2024-06",
        "2024-07",
        "2024-08",
        "2024-09",
        "2024-10"
      ],
      "sampleAnchors": [
        {
          "key": "2000-02",
          "questionIdSpan": "ocean-2000-02-01 -> ocean-2000-02-02",
          "sourceTitle": "2(10 分)"
        },
        {
          "key": "2000-03",
          "questionIdSpan": "ocean-2000-03-01 -> ocean-2000-03-02",
          "sourceTitle": "3(10 分)"
        },
        {
          "key": "2000-06",
          "questionIdSpan": "ocean-2000-06-01 -> ocean-2000-06-03",
          "sourceTitle": "6(10 分)"
        },
        {
          "key": "2000-07",
          "questionIdSpan": "ocean-2000-07-01 -> ocean-2000-07-04",
          "sourceTitle": "7(20 分)"
        },
        {
          "key": "2000-08",
          "questionIdSpan": "ocean-2000-08-01 -> ocean-2000-08-02",
          "sourceTitle": "8(10 分)"
        },
        {
          "key": "2001-06",
          "questionIdSpan": "ocean-2001-06-01 -> ocean-2001-06-04",
          "sourceTitle": "6(15 分)"
        },
        {
          "key": "2002-08",
          "questionIdSpan": "ocean-2002-08-01 -> ocean-2002-08-02",
          "sourceTitle": "8(18 分)"
        },
        {
          "key": "2003-07",
          "questionIdSpan": "ocean-2003-07-01 -> ocean-2003-07-03",
          "sourceTitle": "7(30 分)"
        }
      ]
    },
    "status": "locked",
    "failedKeys": []
  },
  "fourFiveRows": [
    {
      "key": "2000-07",
      "year": 2000,
      "label": "2000 连续小问×4",
      "family": "continuous-calculation",
      "expected": {
        "atomicQuestionCount": 4,
        "itemNumbers": [
          1,
          2,
          3,
          4
        ]
      },
      "actual": {
        "sourceActualAtomicCount": 4,
        "questionIdCount": 4,
        "yearPackQuestionCount": 4,
        "itemNumbers": [
          1,
          2,
          3,
          4
        ]
      },
      "questionIdSpan": "ocean-2000-07-01 -> ocean-2000-07-04",
      "sourceTitle": "7(20 分)",
      "sourceExcerpt": "- (A)简要说明边界层的概念与边界层理论; - (B)写出定常情况下不可压缩流体沿平板流动的边界层微分方程式与边界条件; - (C)导出 von Kármán 动量积分方程: (∂)/(∂ x)(U²θ) + U(∂ U)/(∂ x)δ₁ = ν((∂ u)/(∂ y))_{y=0} 其中 δ₁ 与 θ 分别为排移厚度与动量厚度; - (D)令 η = y/δ, U = const 并取速度分布为 (u)/(U) = Aη - Bη² - Cη³, η ≤ 1 (u)/(U) = 1, η > 1 先确定常数 A",
      "status": "locked",
      "reasons": []
    },
    {
      "key": "2001-06",
      "year": 2001,
      "label": "2001 连续小问×4",
      "family": "objective-or-other",
      "expected": {
        "atomicQuestionCount": 4,
        "itemNumbers": [
          1,
          2,
          3,
          4
        ]
      },
      "actual": {
        "sourceActualAtomicCount": 4,
        "questionIdCount": 4,
        "yearPackQuestionCount": 4,
        "itemNumbers": [
          1,
          2,
          3,
          4
        ]
      },
      "questionIdSpan": "ocean-2001-06-01 -> ocean-2001-06-04",
      "sourceTitle": "6(15 分)",
      "sourceExcerpt": "(1) 边界层概念的基本内容是什么? (2) 写出边界层理论基本方程。 (3) 写出边界层理论中位移厚度和动量损失厚度表达式。 (4) 为什么理想流体势流理论能成功处理绕流问题?",
      "status": "locked",
      "reasons": []
    },
    {
      "key": "2004-02",
      "year": 2004,
      "label": "2004 名词解释题×4",
      "family": "short-name-concept",
      "expected": {
        "atomicQuestionCount": 4,
        "itemNumbers": [
          1,
          2,
          3,
          4
        ]
      },
      "actual": {
        "sourceActualAtomicCount": 4,
        "questionIdCount": 4,
        "yearPackQuestionCount": 4,
        "itemNumbers": [
          1,
          2,
          3,
          4
        ]
      },
      "questionIdSpan": "ocean-2004-02-01 -> ocean-2004-02-04",
      "sourceTitle": "二、名词解释（20 分，每小题 5 分）",
      "sourceExcerpt": "1. 流线。 2. 不可压缩流体。 3. 流体正压。 4. 边界层厚度。",
      "status": "locked",
      "reasons": []
    },
    {
      "key": "2006-01",
      "year": 2006,
      "label": "2006 选择题×4",
      "family": "objective-or-other",
      "expected": {
        "atomicQuestionCount": 4,
        "itemNumbers": [
          1,
          2,
          3,
          4
        ]
      },
      "actual": {
        "sourceActualAtomicCount": 4,
        "questionIdCount": 4,
        "yearPackQuestionCount": 4,
        "itemNumbers": [
          1,
          2,
          3,
          4
        ]
      },
      "questionIdSpan": "ocean-2006-01-01 -> ocean-2006-01-04",
      "sourceTitle": "一、选择题(每小题 5 分,共 20 分)",
      "sourceExcerpt": "1. 用欧拉变数描述不可压缩流体的数学表达式是() - A. dρ/dt = 0 - B. ρ = 常数 - C. (∂ρ)/(∂t) = 0 - D. Δρ = 0 2. rot v 大小的物理意义是() - A. 流体的旋转角速度 - B. 流体微团的平均角速度 - C. 流体微团的自旋角速度的两倍 - D. 流体微团自旋角速度的一半 3. 流体易流动性的含义是() - A. 流体不能承受切向应力 - B. 流体静止时只有法向应力,没有切向应力 - C. 流体可以发生任意大的变形 - D. 流体静止时不能承受任",
      "status": "locked",
      "reasons": []
    },
    {
      "key": "2006-02",
      "year": 2006,
      "label": "2006 连续小问×4",
      "family": "continuous-calculation",
      "expected": {
        "atomicQuestionCount": 4,
        "itemNumbers": [
          1,
          2,
          3,
          4
        ]
      },
      "actual": {
        "sourceActualAtomicCount": 4,
        "questionIdCount": 4,
        "yearPackQuestionCount": 4,
        "itemNumbers": [
          1,
          2,
          3,
          4
        ]
      },
      "questionIdSpan": "ocean-2006-02-01 -> ocean-2006-02-04",
      "sourceTitle": "二、(20 分)",
      "sourceExcerpt": "对于点源诱导的二维中心对称辐射性流动,已知点源强度为 m: 1. 试以欧拉变量写出流体运动的速度场; 2. 试以拉格朗日变量写出流体质点的运动方程; 3. 求流线和轨迹方程; 4. 求流体质点的加速度。",
      "status": "locked",
      "reasons": []
    },
    {
      "key": "2007-01",
      "year": 2007,
      "label": "2007 名词解释题×4",
      "family": "short-name-concept",
      "expected": {
        "atomicQuestionCount": 4,
        "itemNumbers": [
          1,
          2,
          3,
          4
        ]
      },
      "actual": {
        "sourceActualAtomicCount": 4,
        "questionIdCount": 4,
        "yearPackQuestionCount": 4,
        "itemNumbers": [
          1,
          2,
          3,
          4
        ]
      },
      "questionIdSpan": "ocean-2007-01-01 -> ocean-2007-01-04",
      "sourceTitle": "一、名词解释（20 分，各 5 分）",
      "sourceExcerpt": "1. 连续介质假设。 2. 正压流体。 3. 流动动力学相似条件。 4. 普朗特边界层假设。",
      "status": "locked",
      "reasons": []
    },
    {
      "key": "2007-02",
      "year": 2007,
      "label": "2007 选择题×4",
      "family": "objective-or-other",
      "expected": {
        "atomicQuestionCount": 4,
        "itemNumbers": [
          1,
          2,
          3,
          4
        ]
      },
      "actual": {
        "sourceActualAtomicCount": 4,
        "questionIdCount": 4,
        "yearPackQuestionCount": 4,
        "itemNumbers": [
          1,
          2,
          3,
          4
        ]
      },
      "questionIdSpan": "ocean-2007-02-01 -> ocean-2007-02-04",
      "sourceTitle": "二、选择正确答案（20 分，各 5 分，请在答案纸上写正确答案）",
      "sourceExcerpt": "1. 理想流体在 $y - z$ 平面做无旋运动，速度势 $\\phi = (y^{2} + z^{2})t$（$t$ 代表时间）。则同一时刻在两条流线之间的不同截面上， - A. 体积流量和质量流量都守恒； - B. 体积流量和质量流量都不守恒； - C. 只有体积流量守恒； - D. 只有质量流量守恒。 2. 已知地中海含盐分比黑海大，那么在连通二海的海峡中 - A. 会引起海面附近的海水由地中海流向黑海； - B. 会引起海面附近的海水由黑海流向地中海； - C. 不会引起两海间的海水相对流动； - D. 引起",
      "status": "locked",
      "reasons": []
    },
    {
      "key": "2007-07",
      "year": 2007,
      "label": "2007 连续小问×4",
      "family": "continuous-calculation",
      "expected": {
        "atomicQuestionCount": 4,
        "itemNumbers": [
          1,
          2,
          3,
          4
        ]
      },
      "actual": {
        "sourceActualAtomicCount": 4,
        "questionIdCount": 4,
        "yearPackQuestionCount": 4,
        "itemNumbers": [
          1,
          2,
          3,
          4
        ]
      },
      "questionIdSpan": "ocean-2007-07-01 -> ocean-2007-07-04",
      "sourceTitle": "七、（25 分）",
      "sourceExcerpt": "两个无限大的平行平板间充满着不可压缩的粘性流体。已知粘性系数和密度分别为 $\\mu$ 和 $\\rho$。设下板静止，上板以速度 $u_{0}$ 沿水平方向匀速移动。当流动达到定常状态后，求： 1）速度场； 2）流场中每单位体积内能增加率； 3）流体作用在上平板上的切应力； 4）拖动单位面积上平板外力做功功率和单位面积平板间流体柱内的总机械能耗散率。 设水平方向压强梯度为零。",
      "status": "locked",
      "reasons": []
    },
    {
      "key": "2008-01",
      "year": 2008,
      "label": "2008 简述题×4",
      "family": "short-name-concept",
      "expected": {
        "atomicQuestionCount": 4,
        "itemNumbers": [
          1,
          2,
          3,
          4
        ]
      },
      "actual": {
        "sourceActualAtomicCount": 4,
        "questionIdCount": 4,
        "yearPackQuestionCount": 4,
        "itemNumbers": [
          1,
          2,
          3,
          4
        ]
      },
      "questionIdSpan": "ocean-2008-01-01 -> ocean-2008-01-04",
      "sourceTitle": "一、简述题",
      "sourceExcerpt": "1. Bernoulli 方程与 Lagrange 积分的适用条件及物理意义。 2. 连续方程的物理意义和适用口径。 3. 边界层理论的基本思想。 4. 流动相似条件以及 Reynolds、Strouhal、Euler、Froude 等无量纲数的作用。",
      "status": "locked",
      "reasons": []
    },
    {
      "key": "2010-02",
      "year": 2010,
      "label": "2010 简答题×5",
      "family": "short-name-concept",
      "expected": {
        "atomicQuestionCount": 5,
        "itemNumbers": [
          1,
          2,
          3,
          4,
          5
        ]
      },
      "actual": {
        "sourceActualAtomicCount": 5,
        "questionIdCount": 5,
        "yearPackQuestionCount": 5,
        "itemNumbers": [
          1,
          2,
          3,
          4,
          5
        ]
      },
      "questionIdSpan": "ocean-2010-02-01 -> ocean-2010-02-05",
      "sourceTitle": "二、简答题(每题 8 分,共 40 分)",
      "sourceExcerpt": "1. 气体和液体的动力粘性系数随温度如何变化,为什么? 2. 均匀来流绕流半无限长平板,平板上方层流边界层的厚度由哪些因素决定?会发生边界层分离吗? 3. 什么是雷诺应力?雷诺应力与粘性应力产生机制有什么不同? 4. 为确定深水航行的潜艇所受的阻力,设计模型实验时要满足的相似性条件有哪些?实验结果应当如何定量表达? 5. 流体微团的基本运动形式有哪些,粘性应力与其中的哪种运动形式有关?",
      "status": "locked",
      "reasons": []
    },
    {
      "key": "2011-02",
      "year": 2011,
      "label": "2011 简答题×4",
      "family": "short-name-concept",
      "expected": {
        "atomicQuestionCount": 4,
        "itemNumbers": [
          1,
          2,
          3,
          4
        ]
      },
      "actual": {
        "sourceActualAtomicCount": 4,
        "questionIdCount": 4,
        "yearPackQuestionCount": 4,
        "itemNumbers": [
          1,
          2,
          3,
          4
        ]
      },
      "questionIdSpan": "ocean-2011-02-01 -> ocean-2011-02-04",
      "sourceTitle": "二、简答题（每题 10 分，40 分）",
      "sourceExcerpt": "1. 简述连续介质假设的内容，并回答对于气体绕流固体的流动而言，什么情况下连续介质假设不实用。 2. 涡管强度在什么条件下守恒，涡管强度守恒时，涡管内的涡度是否一定保持不变。 3. 层流向湍流转换的条件是什么？层流和湍流中动量输运的机制分别是什么？ 4. 简述理想流体假设的适用条件。计算在水中运动的物体所受阻力时，该假设是否适用，为什么？",
      "status": "locked",
      "reasons": []
    },
    {
      "key": "2012-06",
      "year": 2012,
      "label": "2012 连续小问×4",
      "family": "continuous-calculation",
      "expected": {
        "atomicQuestionCount": 4,
        "itemNumbers": [
          1,
          2,
          3,
          4
        ]
      },
      "actual": {
        "sourceActualAtomicCount": 4,
        "questionIdCount": 4,
        "yearPackQuestionCount": 4,
        "itemNumbers": [
          1,
          2,
          3,
          4
        ]
      },
      "questionIdSpan": "ocean-2012-06-01 -> ocean-2012-06-04",
      "sourceTitle": "六、(30 分)",
      "sourceExcerpt": "如图 2 所示,一点源在两半无限长平板围成的直角区域内诱导的流动,该流动可看成理想不可压缩流体平面无旋流动,点源距两平板垂直距离均为 a,强度为 9m。求: 1. 流动的复势; 2. 平板边界上的速度分布及速度最大值点的位置; 3. 平板边界上的压强分布及压强最小值点的位置; 4. 求点源对平板边界的作用力(注:写出积分表达式即可)。",
      "status": "locked",
      "reasons": []
    },
    {
      "key": "2014-03",
      "year": 2014,
      "label": "2014 连续小问×4",
      "family": "continuous-calculation",
      "expected": {
        "atomicQuestionCount": 4,
        "itemNumbers": [
          1,
          2,
          3,
          4
        ]
      },
      "actual": {
        "sourceActualAtomicCount": 4,
        "questionIdCount": 4,
        "yearPackQuestionCount": 4,
        "itemNumbers": [
          1,
          2,
          3,
          4
        ]
      },
      "questionIdSpan": "ocean-2014-03-01 -> ocean-2014-03-04",
      "sourceTitle": "三、(20 分)",
      "sourceExcerpt": "已知流体运动的速度大小和流线方程分别为 V = sqrt(x² + y²), x² - y² = C 其中 C 为任意常数。求: 1. 速度场两速度分量; 2. 初始位于原点的流体质点轨迹; 3. 该流动是否有旋;若无旋,求速度势; 4. 该流动是否可压缩;若不可压缩,求流函数。",
      "status": "locked",
      "reasons": []
    },
    {
      "key": "2015-01",
      "year": 2015,
      "label": "2015 简答题×5",
      "family": "short-name-concept",
      "expected": {
        "atomicQuestionCount": 5,
        "itemNumbers": [
          1,
          2,
          3,
          4,
          5
        ]
      },
      "actual": {
        "sourceActualAtomicCount": 5,
        "questionIdCount": 5,
        "yearPackQuestionCount": 5,
        "itemNumbers": [
          1,
          2,
          3,
          4,
          5
        ]
      },
      "questionIdSpan": "ocean-2015-01-01 -> ocean-2015-01-05",
      "sourceTitle": "一、简答题(1-5)",
      "sourceExcerpt": "1(10 分) - 流速的散度和旋度的物理意义分别是什么? 2(10 分) - 当满足什么条件时,流体自静止开始的流动始终是无旋流动?薄平板在原本静止的流体中平移,流场在哪些区域有旋,哪些区域无旋? 3(10 分) - 图 1 中三条曲线都表示圆柱表面压强系数的分布,请问哪条是理想流体理论解,哪条是观测结果?试说明导致三条曲线差异的原因。 4(10 分) - 平板边界层内流动可以是层流,也可以是湍流,影响边界层内流态的因素有哪些?哪种流态下平板上的粘性应力较大? 5(10 分) - 什么是正压流体?大气层空气密度随",
      "status": "locked",
      "reasons": []
    },
    {
      "key": "2018-01",
      "year": 2018,
      "label": "2018 简答题×5",
      "family": "short-name-concept",
      "expected": {
        "atomicQuestionCount": 5,
        "itemNumbers": [
          1,
          2,
          3,
          4,
          5
        ]
      },
      "actual": {
        "sourceActualAtomicCount": 5,
        "questionIdCount": 5,
        "yearPackQuestionCount": 5,
        "itemNumbers": [
          1,
          2,
          3,
          4,
          5
        ]
      },
      "questionIdSpan": "ocean-2018-01-01 -> ocean-2018-01-05",
      "sourceTitle": "一、简答题(每题 10 分,共 50 分)",
      "sourceExcerpt": "1. 写出 Reynolds 数的表达式,说明其物理含义,并简要描述 Reynolds 实验的结论。 2. 稳定转动的圆形转盘内水面如何分布?试用流体力学原理分析其原因。 3. 波浪引起的水质点如何运动?为何近岸传播的波浪都是向岸的? 4. 粗糙管道阻力与哪些物理量有关?试说明 Nikuradse 曲线绘制的是哪些物理量之间的关系曲线,以及关系如何。 5. 请说明 Prandtl 边界层假设内容、边界层内流动的特点以及边界层理论的适用条件。",
      "status": "locked",
      "reasons": []
    },
    {
      "key": "2019-01",
      "year": 2019,
      "label": "2019 名词解释题×5",
      "family": "short-name-concept",
      "expected": {
        "atomicQuestionCount": 5,
        "itemNumbers": [
          1,
          2,
          3,
          4,
          5
        ]
      },
      "actual": {
        "sourceActualAtomicCount": 5,
        "questionIdCount": 5,
        "yearPackQuestionCount": 5,
        "itemNumbers": [
          1,
          2,
          3,
          4,
          5
        ]
      },
      "questionIdSpan": "ocean-2019-01-01 -> ocean-2019-01-05",
      "sourceTitle": "一、名词解释(每个名词 10 分,共 50 分)",
      "sourceExcerpt": "要求写出定义的数学表达式和物理意义。 1. 应变率张量; 2. 边界层厚度; 3. 本构方程; 4. Reynolds 数; 5. Reynolds 应力。",
      "status": "locked",
      "reasons": []
    },
    {
      "key": "2020-01",
      "year": 2020,
      "label": "2020 简答题×5",
      "family": "short-name-concept",
      "expected": {
        "atomicQuestionCount": 5,
        "itemNumbers": [
          1,
          2,
          3,
          4,
          5
        ]
      },
      "actual": {
        "sourceActualAtomicCount": 5,
        "questionIdCount": 5,
        "yearPackQuestionCount": 5,
        "itemNumbers": [
          1,
          2,
          3,
          4,
          5
        ]
      },
      "questionIdSpan": "ocean-2020-01-01 -> ocean-2020-01-05",
      "sourceTitle": "一、概念与简答题(每题 10 分,共 50 分)",
      "sourceExcerpt": "1. 皮托管测速的原理。 2. 湍流的基本特征。 3. 牛顿流体。 4. 描述流体流动的两种方法,每种方法各举 1 个海洋观测的例子。 5. Rossby 数表征惯性力与地转科氏力之比,写出 Rossby 数的表达式。",
      "status": "locked",
      "reasons": []
    },
    {
      "key": "2020-04",
      "year": 2020,
      "label": "2020 连续小问×4",
      "family": "continuous-calculation",
      "expected": {
        "atomicQuestionCount": 4,
        "itemNumbers": [
          1,
          2,
          3,
          4
        ]
      },
      "actual": {
        "sourceActualAtomicCount": 4,
        "questionIdCount": 4,
        "yearPackQuestionCount": 4,
        "itemNumbers": [
          1,
          2,
          3,
          4
        ]
      },
      "questionIdSpan": "ocean-2020-04-01 -> ocean-2020-04-04",
      "sourceTitle": "四、(20 分)",
      "sourceExcerpt": "在 xy 坐标系中分别位于 (-a,0)、(a,0)(a>0)两点,强度分别为 Q 和 -Q(Q>0)的点源和点汇,与沿 x 方向速度为 U 的均匀流叠加成一平面流场。求: 1. 流函数与速度势函数; 2. 速度分布式; 3. 流线方程; 4. 画出零流线及部分流线图。",
      "status": "locked",
      "reasons": []
    }
  ],
  "fiveItemShortAnswerRows": [
    {
      "key": "2010-02",
      "year": 2010,
      "label": "2010 二、简答题×5",
      "expected": {
        "atomicQuestionCount": 5,
        "itemNumbers": [
          1,
          2,
          3,
          4,
          5
        ]
      },
      "actual": {
        "sourceActualAtomicCount": 5,
        "questionIdCount": 5,
        "yearPackQuestionCount": 5,
        "itemNumbers": [
          1,
          2,
          3,
          4,
          5
        ]
      },
      "anchor": {
        "sourceFile": "data/fluid-round307-real-exam-source-row-year-count-lock.json",
        "sourceTitle": "二、简答题(每题 8 分,共 40 分)",
        "questionIdSpan": "ocean-2010-02-01 -> ocean-2010-02-05",
        "firstQuestionId": "ocean-2010-02-01",
        "lastQuestionId": "ocean-2010-02-05",
        "evidenceStyles": [
          "score-ratio",
          "source-numbered-items"
        ],
        "sourceExcerpt": "1. 气体和液体的动力粘性系数随温度如何变化,为什么? 2. 均匀来流绕流半无限长平板,平板上方层流边界层的厚度由哪些因素决定?会发生边界层分离吗? 3. 什么是雷诺应力?雷诺应力与粘性应力产生机制有什么不同? 4. 为确定深水航行的潜艇所受的阻力,设计模型实验时要满足的相似性条件有哪些?实验结果应当如何定量表达? 5. 流体微团的基本运动形式有哪些,粘性应",
        "round290Status": "locked",
        "round307Status": "locked",
        "round323Status": "locked",
        "yearPack": "question-banks/real-exam-years/2010.json"
      },
      "status": "locked",
      "reasons": []
    },
    {
      "key": "2015-01",
      "year": 2015,
      "label": "2015 一、简答题×5",
      "expected": {
        "atomicQuestionCount": 5,
        "itemNumbers": [
          1,
          2,
          3,
          4,
          5
        ]
      },
      "actual": {
        "sourceActualAtomicCount": 5,
        "questionIdCount": 5,
        "yearPackQuestionCount": 5,
        "itemNumbers": [
          1,
          2,
          3,
          4,
          5
        ]
      },
      "anchor": {
        "sourceFile": "data/fluid-round307-real-exam-source-row-year-count-lock.json",
        "sourceTitle": "一、简答题(1-5)",
        "questionIdSpan": "ocean-2015-01-01 -> ocean-2015-01-05",
        "firstQuestionId": "ocean-2015-01-01",
        "lastQuestionId": "ocean-2015-01-05",
        "evidenceStyles": [
          "title-range",
          "source-numbered-items"
        ],
        "sourceExcerpt": "1(10 分) - 流速的散度和旋度的物理意义分别是什么? 2(10 分) - 当满足什么条件时,流体自静止开始的流动始终是无旋流动?薄平板在原本静止的流体中平移,流场在哪些区域有旋,哪些区域无旋? 3(10 分) - 图 1 中三条曲线都表示圆柱表面压强系数的分布,请问哪条是理想流体理论解,哪条是观测结果?试说明导致三条曲线差异的原因。 4(10 分) -",
        "round290Status": "locked",
        "round307Status": "locked",
        "round323Status": "locked",
        "yearPack": "question-banks/real-exam-years/2015.json"
      },
      "status": "locked",
      "reasons": []
    },
    {
      "key": "2018-01",
      "year": 2018,
      "label": "2018 一、简答题×5",
      "expected": {
        "atomicQuestionCount": 5,
        "itemNumbers": [
          1,
          2,
          3,
          4,
          5
        ]
      },
      "actual": {
        "sourceActualAtomicCount": 5,
        "questionIdCount": 5,
        "yearPackQuestionCount": 5,
        "itemNumbers": [
          1,
          2,
          3,
          4,
          5
        ]
      },
      "anchor": {
        "sourceFile": "data/fluid-round307-real-exam-source-row-year-count-lock.json",
        "sourceTitle": "一、简答题(每题 10 分,共 50 分)",
        "questionIdSpan": "ocean-2018-01-01 -> ocean-2018-01-05",
        "firstQuestionId": "ocean-2018-01-01",
        "lastQuestionId": "ocean-2018-01-05",
        "evidenceStyles": [
          "score-ratio",
          "source-numbered-items"
        ],
        "sourceExcerpt": "1. 写出 Reynolds 数的表达式,说明其物理含义,并简要描述 Reynolds 实验的结论。 2. 稳定转动的圆形转盘内水面如何分布?试用流体力学原理分析其原因。 3. 波浪引起的水质点如何运动?为何近岸传播的波浪都是向岸的? 4. 粗糙管道阻力与哪些物理量有关?试说明 Nikuradse 曲线绘制的是哪些物理量之间的关系曲线,以及关系如何。 5.",
        "round290Status": "locked",
        "round307Status": "locked",
        "round323Status": "locked",
        "yearPack": "question-banks/real-exam-years/2018.json"
      },
      "status": "locked",
      "reasons": []
    },
    {
      "key": "2019-01",
      "year": 2019,
      "label": "2019 一、名词解释×5",
      "expected": {
        "atomicQuestionCount": 5,
        "itemNumbers": [
          1,
          2,
          3,
          4,
          5
        ]
      },
      "actual": {
        "sourceActualAtomicCount": 5,
        "questionIdCount": 5,
        "yearPackQuestionCount": 5,
        "itemNumbers": [
          1,
          2,
          3,
          4,
          5
        ]
      },
      "anchor": {
        "sourceFile": "data/fluid-round307-real-exam-source-row-year-count-lock.json",
        "sourceTitle": "一、名词解释(每个名词 10 分,共 50 分)",
        "questionIdSpan": "ocean-2019-01-01 -> ocean-2019-01-05",
        "firstQuestionId": "ocean-2019-01-01",
        "lastQuestionId": "ocean-2019-01-05",
        "evidenceStyles": [
          "source-numbered-items"
        ],
        "sourceExcerpt": "要求写出定义的数学表达式和物理意义。 1. 应变率张量; 2. 边界层厚度; 3. 本构方程; 4. Reynolds 数; 5. Reynolds 应力。",
        "round290Status": "locked",
        "round307Status": "locked",
        "round323Status": "locked",
        "yearPack": "question-banks/real-exam-years/2019.json"
      },
      "status": "locked",
      "reasons": []
    },
    {
      "key": "2020-01",
      "year": 2020,
      "label": "2020 一、概念与简答题×5",
      "expected": {
        "atomicQuestionCount": 5,
        "itemNumbers": [
          1,
          2,
          3,
          4,
          5
        ]
      },
      "actual": {
        "sourceActualAtomicCount": 5,
        "questionIdCount": 5,
        "yearPackQuestionCount": 5,
        "itemNumbers": [
          1,
          2,
          3,
          4,
          5
        ]
      },
      "anchor": {
        "sourceFile": "data/fluid-round307-real-exam-source-row-year-count-lock.json",
        "sourceTitle": "一、概念与简答题(每题 10 分,共 50 分)",
        "questionIdSpan": "ocean-2020-01-01 -> ocean-2020-01-05",
        "firstQuestionId": "ocean-2020-01-01",
        "lastQuestionId": "ocean-2020-01-05",
        "evidenceStyles": [
          "score-ratio",
          "source-numbered-items"
        ],
        "sourceExcerpt": "1. 皮托管测速的原理。 2. 湍流的基本特征。 3. 牛顿流体。 4. 描述流体流动的两种方法,每种方法各举 1 个海洋观测的例子。 5. Rossby 数表征惯性力与地转科氏力之比,写出 Rossby 数的表达式。",
        "round290Status": "locked",
        "round307Status": "locked",
        "round323Status": "locked",
        "yearPack": "question-banks/real-exam-years/2020.json"
      },
      "status": "locked",
      "reasons": []
    }
  ],
  "criticalYearStructures": [
    {
      "year": 2000,
      "reason": "2000 includes multiple A/B/C/D source sections; 2000-07 must remain four separate cards.",
      "expected": {
        "yearQuestionCount": 16,
        "groupedSectionCount": 5,
        "sectionKeys": [
          "2000-02",
          "2000-03",
          "2000-06",
          "2000-07",
          "2000-08"
        ]
      },
      "actual": {
        "yearQuestionCount": 16,
        "groupedSectionCount": 5,
        "groupedWebQuestionIdCount": 13
      },
      "sections": [
        {
          "key": "2000-02",
          "role": "calculation-ab",
          "expectedAtomicCount": 2,
          "actualAtomicCount": 2,
          "questionIdCount": 2,
          "itemNumbers": [
            1,
            2
          ],
          "questionIdSpan": "ocean-2000-02-01 -> ocean-2000-02-02",
          "sourceTitle": "2(10 分)",
          "sourceExcerpt": "椭球 (x²)/(a²) + (y²)/(b²) + (z²)/(c²) = 1 以 V₀ = U₀ i 等速运动,试给出理想流体绕流。并写出椭球的运动学边界条件: - (A)固定于椭球上的坐标系中的相对运动; - (B)绝对坐标系中的绝对运动。",
          "status": "locked",
          "reasons": []
        },
        {
          "key": "2000-03",
          "role": "calculation-ab",
          "expectedAtomicCount": 2,
          "actualAtomicCount": 2,
          "questionIdCount": 2,
          "itemNumbers": [
            1,
            2
          ],
          "questionIdSpan": "ocean-2000-03-01 -> ocean-2000-03-02",
          "sourceTitle": "3(10 分)",
          "sourceExcerpt": "已知不可压缩平面无旋流动的流函数为 ψ = x² + xy - y² 求: - (A)流动的速度势以及流动的复势; - (B)流动的流线方程。",
          "status": "locked",
          "reasons": []
        },
        {
          "key": "2000-06",
          "role": "calculation-abc",
          "expectedAtomicCount": 3,
          "actualAtomicCount": 3,
          "questionIdCount": 3,
          "itemNumbers": [
            1,
            2,
            3
          ],
          "questionIdSpan": "ocean-2000-06-01 -> ocean-2000-06-03",
          "sourceTitle": "6(10 分)",
          "sourceExcerpt": "水平放置的两固定平行平板之间存在定常不可压缩层流流动,两平板间距为 h,沿流动方向长度 L 上的压强降为 Δ p = const 求: - (A)流体中的速度分布; - (B)流体层之间的剪切应力以及作用在单位质量流体上的摩擦力; - (C)单位体积流体内的能量耗散。",
          "status": "locked",
          "reasons": []
        },
        {
          "key": "2000-07",
          "role": "boundary-layer-abcd-four-lock",
          "expectedAtomicCount": 4,
          "actualAtomicCount": 4,
          "questionIdCount": 4,
          "itemNumbers": [
            1,
            2,
            3,
            4
          ],
          "questionIdSpan": "ocean-2000-07-01 -> ocean-2000-07-04",
          "sourceTitle": "7(20 分)",
          "sourceExcerpt": "- (A)简要说明边界层的概念与边界层理论; - (B)写出定常情况下不可压缩流体沿平板流动的边界层微分方程式与边界条件; - (C)导出 von Kármán 动量积分方程: (∂)/(∂ x)(U²θ) + U(∂ U)/(∂ x)δ₁ = ν((∂ u)/(∂ y))_{y=0} 其中 δ₁ 与 θ 分别为排移厚度与动量厚度; - (D)令 η = y",
          "status": "locked",
          "reasons": []
        },
        {
          "key": "2000-08",
          "role": "discussion-ab",
          "expectedAtomicCount": 2,
          "actualAtomicCount": 2,
          "questionIdCount": 2,
          "itemNumbers": [
            1,
            2
          ],
          "questionIdSpan": "ocean-2000-08-01 -> ocean-2000-08-02",
          "sourceTitle": "8(10 分)",
          "sourceExcerpt": "- (A)简要说明层流与湍流两种流动现象; - (B)就你所知,简要说出有关湍流的研究成果与理论。",
          "status": "locked",
          "reasons": []
        }
      ],
      "status": "locked",
      "reasons": []
    },
    {
      "year": 2001,
      "reason": "2001 section 6 is four original concept subquestions, not one merged prompt.",
      "expected": {
        "yearQuestionCount": 11,
        "groupedSectionCount": 1,
        "sectionKeys": [
          "2001-06"
        ]
      },
      "actual": {
        "yearQuestionCount": 11,
        "groupedSectionCount": 1,
        "groupedWebQuestionIdCount": 4
      },
      "sections": [
        {
          "key": "2001-06",
          "role": "concept-numbered-four-lock",
          "expectedAtomicCount": 4,
          "actualAtomicCount": 4,
          "questionIdCount": 4,
          "itemNumbers": [
            1,
            2,
            3,
            4
          ],
          "questionIdSpan": "ocean-2001-06-01 -> ocean-2001-06-04",
          "sourceTitle": "6(15 分)",
          "sourceExcerpt": "(1) 边界层概念的基本内容是什么? (2) 写出边界层理论基本方程。 (3) 写出边界层理论中位移厚度和动量损失厚度表达式。 (4) 为什么理想流体势流理论能成功处理绕流问题?",
          "status": "locked",
          "reasons": []
        }
      ],
      "status": "locked",
      "reasons": []
    },
    {
      "year": 2004,
      "reason": "2004 has a ten-item fill-in source section and a four-item definition section.",
      "expected": {
        "yearQuestionCount": 18,
        "groupedSectionCount": 2,
        "sectionKeys": [
          "2004-01",
          "2004-02"
        ]
      },
      "actual": {
        "yearQuestionCount": 18,
        "groupedSectionCount": 2,
        "groupedWebQuestionIdCount": 14
      },
      "sections": [
        {
          "key": "2004-01",
          "role": "fill-in-ten-lock",
          "expectedAtomicCount": 10,
          "actualAtomicCount": 10,
          "questionIdCount": 10,
          "itemNumbers": [
            1,
            2,
            3,
            4,
            5,
            6,
            7,
            8,
            9,
            10
          ],
          "questionIdSpan": "ocean-2004-01-01 -> ocean-2004-01-10",
          "sourceTitle": "一、填空题（50 分，共 10 小题，每小题 5 分）",
          "sourceExcerpt": "1. 已知平面流动速度场 u=x²-y²,\\ v=-2xy，则通过 x=1,\\ y=1 的一条流线为__________。 2. 已知速度场分布为 u=yzt,\\ v=zxt,\\ w=0，则当 t=10 时，质点在 (2,5,3) 处的加速度是__________。 3. __________和__________之间的关系满足广义牛顿公式的流体称为牛顿流体",
          "status": "locked",
          "reasons": []
        },
        {
          "key": "2004-02",
          "role": "definition-four-lock",
          "expectedAtomicCount": 4,
          "actualAtomicCount": 4,
          "questionIdCount": 4,
          "itemNumbers": [
            1,
            2,
            3,
            4
          ],
          "questionIdSpan": "ocean-2004-02-01 -> ocean-2004-02-04",
          "sourceTitle": "二、名词解释（20 分，每小题 5 分）",
          "sourceExcerpt": "1. 流线。 2. 不可压缩流体。 3. 流体正压。 4. 边界层厚度。",
          "status": "locked",
          "reasons": []
        }
      ],
      "status": "locked",
      "reasons": []
    },
    {
      "year": 2008,
      "reason": "2008 short-description section has four original items and must not collapse.",
      "expected": {
        "yearQuestionCount": 9,
        "groupedSectionCount": 2,
        "sectionKeys": [
          "2008-01",
          "2008-03"
        ]
      },
      "actual": {
        "yearQuestionCount": 9,
        "groupedSectionCount": 2,
        "groupedWebQuestionIdCount": 7
      },
      "sections": [
        {
          "key": "2008-01",
          "role": "short-description-four-lock",
          "expectedAtomicCount": 4,
          "actualAtomicCount": 4,
          "questionIdCount": 4,
          "itemNumbers": [
            1,
            2,
            3,
            4
          ],
          "questionIdSpan": "ocean-2008-01-01 -> ocean-2008-01-04",
          "sourceTitle": "一、简述题",
          "sourceExcerpt": "1. Bernoulli 方程与 Lagrange 积分的适用条件及物理意义。 2. 连续方程的物理意义和适用口径。 3. 边界层理论的基本思想。 4. 流动相似条件以及 Reynolds、Strouhal、Euler、Froude 等无量纲数的作用。",
          "status": "locked",
          "reasons": []
        },
        {
          "key": "2008-03",
          "role": "calculation-three-lock",
          "expectedAtomicCount": 3,
          "actualAtomicCount": 3,
          "questionIdCount": 3,
          "itemNumbers": [
            1,
            2,
            3
          ],
          "questionIdSpan": "ocean-2008-03-01 -> ocean-2008-03-03",
          "sourceTitle": "三、(20 分)",
          "sourceExcerpt": "已知流场 u=x²y²-x, v=-xy+y, w=0 求: 1. 该流动是否不可压缩; 2. 该流动是否位势; 3. 若条件满足,求速度势函数与流函数。",
          "status": "locked",
          "reasons": []
        }
      ],
      "status": "locked",
      "reasons": []
    },
    {
      "year": 2010,
      "reason": "2010 short-answer section is originally five questions; the five cards are not mergeable.",
      "expected": {
        "yearQuestionCount": 21,
        "groupedSectionCount": 3,
        "sectionKeys": [
          "2010-01",
          "2010-02",
          "2010-05"
        ]
      },
      "actual": {
        "yearQuestionCount": 21,
        "groupedSectionCount": 3,
        "groupedWebQuestionIdCount": 18
      },
      "sections": [
        {
          "key": "2010-01",
          "role": "choice-ten-lock",
          "expectedAtomicCount": 10,
          "actualAtomicCount": 10,
          "questionIdCount": 10,
          "itemNumbers": [
            1,
            2,
            3,
            4,
            5,
            6,
            7,
            8,
            9,
            10
          ],
          "questionIdSpan": "ocean-2010-01-01 -> ocean-2010-01-10",
          "sourceTitle": "一、选择题(每小题 4 分,共 40 分)",
          "sourceExcerpt": "1. 以欧拉变数描述的不可压缩流动的密度场 ρ 必满足() - A. dρ/dt = 0 - B. ρ = 常数 - C. (∂ρ)/(∂t) = 0 - D. Δρ = 0 2. 偶极子由一对无限靠近(距离 l 趋近于零)的等强度的点源(强度为 m)和点汇构成。一个偶极子位于无限大平板边界上方 b 处,如图所示,图中箭头代表偶极子;箭头指向点源,箭头与 x",
          "status": "locked",
          "reasons": []
        },
        {
          "key": "2010-02",
          "role": "short-answer-five-lock",
          "expectedAtomicCount": 5,
          "actualAtomicCount": 5,
          "questionIdCount": 5,
          "itemNumbers": [
            1,
            2,
            3,
            4,
            5
          ],
          "questionIdSpan": "ocean-2010-02-01 -> ocean-2010-02-05",
          "sourceTitle": "二、简答题(每题 8 分,共 40 分)",
          "sourceExcerpt": "1. 气体和液体的动力粘性系数随温度如何变化,为什么? 2. 均匀来流绕流半无限长平板,平板上方层流边界层的厚度由哪些因素决定?会发生边界层分离吗? 3. 什么是雷诺应力?雷诺应力与粘性应力产生机制有什么不同? 4. 为确定深水航行的潜艇所受的阻力,设计模型实验时要满足的相似性条件有哪些?实验结果应当如何定量表达? 5. 流体微团的基本运动形式有哪些,粘性应",
          "status": "locked",
          "reasons": []
        },
        {
          "key": "2010-05",
          "role": "calculation-three-lock",
          "expectedAtomicCount": 3,
          "actualAtomicCount": 3,
          "questionIdCount": 3,
          "itemNumbers": [
            1,
            2,
            3
          ],
          "questionIdSpan": "ocean-2010-05-01 -> ocean-2010-05-03",
          "sourceTitle": "五、(20 分)",
          "sourceExcerpt": "已知某流动速度场 u = y + 2z, v = z + 2x, w = x + 2y 1. 求涡量及涡线; 2. 求在 x+y+z=1 平面上面积为 δS 的面元上的涡通量; 3. 求 z=0 平面上以原点为心、半径为 r 的圆周上的速度环量。",
          "status": "locked",
          "reasons": []
        }
      ],
      "status": "locked",
      "reasons": []
    },
    {
      "year": 2015,
      "reason": "2015 begins with five standalone short-answer questions before later calculation groups.",
      "expected": {
        "yearQuestionCount": 14,
        "groupedSectionCount": 4,
        "sectionKeys": [
          "2015-01",
          "2015-02",
          "2015-04",
          "2015-05"
        ]
      },
      "actual": {
        "yearQuestionCount": 14,
        "groupedSectionCount": 4,
        "groupedWebQuestionIdCount": 13
      },
      "sections": [
        {
          "key": "2015-01",
          "role": "short-answer-five-lock",
          "expectedAtomicCount": 5,
          "actualAtomicCount": 5,
          "questionIdCount": 5,
          "itemNumbers": [
            1,
            2,
            3,
            4,
            5
          ],
          "questionIdSpan": "ocean-2015-01-01 -> ocean-2015-01-05",
          "sourceTitle": "一、简答题(1-5)",
          "sourceExcerpt": "1(10 分) - 流速的散度和旋度的物理意义分别是什么? 2(10 分) - 当满足什么条件时,流体自静止开始的流动始终是无旋流动?薄平板在原本静止的流体中平移,流场在哪些区域有旋,哪些区域无旋? 3(10 分) - 图 1 中三条曲线都表示圆柱表面压强系数的分布,请问哪条是理想流体理论解,哪条是观测结果?试说明导致三条曲线差异的原因。 4(10 分) -",
          "status": "locked",
          "reasons": []
        },
        {
          "key": "2015-02",
          "role": "calculation-three-lock",
          "expectedAtomicCount": 3,
          "actualAtomicCount": 3,
          "questionIdCount": 3,
          "itemNumbers": [
            1,
            2,
            3
          ],
          "questionIdSpan": "ocean-2015-02-01 -> ocean-2015-02-03",
          "sourceTitle": "二、(30 分)",
          "sourceExcerpt": "某二维流动速度场 u = xt, v = -yt 试求: 1. 流线方程和欧拉表述的加速度; 2. 流体质点的轨迹方程和拉格朗日表述的加速度; 3. 该流动是否满足速度势和(或)流函数存在的条件?若满足,则求速度势和(或)流函数。",
          "status": "locked",
          "reasons": []
        },
        {
          "key": "2015-04",
          "role": "calculation-three-lock",
          "expectedAtomicCount": 3,
          "actualAtomicCount": 3,
          "questionIdCount": 3,
          "itemNumbers": [
            1,
            2,
            3
          ],
          "questionIdSpan": "ocean-2015-04-01 -> ocean-2015-04-03",
          "sourceTitle": "四、(20 分)",
          "sourceExcerpt": "某理想不可压缩流体平面流动在极坐标系下的速度势为 φ = m \\ln r,其中 m 为实的常量,设流体密度为 ρ,无穷远压强为 P∞。 1. 求此流动之复势; 2. 求速度和压强分布; 3. 求通过点 A(1,-1) 和 B(1,1) 连线的流体体积通量。",
          "status": "locked",
          "reasons": []
        },
        {
          "key": "2015-05",
          "role": "calculation-two-lock",
          "expectedAtomicCount": 2,
          "actualAtomicCount": 2,
          "questionIdCount": 2,
          "itemNumbers": [
            1,
            2
          ],
          "questionIdSpan": "ocean-2015-05-01 -> ocean-2015-05-02",
          "sourceTitle": "五、(20 分)",
          "sourceExcerpt": "一无限大平板浸没在无界的静止流体中,流体不可压缩、运动学粘性系数为 ν。突然启动平板,使其沿自身所在平面以速度 U 匀速直线运动,以 u 代表经过时间 t 距离平板 y 处的流速。 1. 写出求解该流动速度分布的微分方程和定解条件; 2. 试利用量纲分析方法给出无因次速度 u/U 与 t、y 和 ν 的可能函数关系。",
          "status": "locked",
          "reasons": []
        }
      ],
      "status": "locked",
      "reasons": []
    },
    {
      "year": 2018,
      "reason": "2018 first section is five short-answer questions; later grouped calculations remain separate too.",
      "expected": {
        "yearQuestionCount": 14,
        "groupedSectionCount": 4,
        "sectionKeys": [
          "2018-01",
          "2018-04",
          "2018-05",
          "2018-06"
        ]
      },
      "actual": {
        "yearQuestionCount": 14,
        "groupedSectionCount": 4,
        "groupedWebQuestionIdCount": 12
      },
      "sections": [
        {
          "key": "2018-01",
          "role": "short-answer-five-lock",
          "expectedAtomicCount": 5,
          "actualAtomicCount": 5,
          "questionIdCount": 5,
          "itemNumbers": [
            1,
            2,
            3,
            4,
            5
          ],
          "questionIdSpan": "ocean-2018-01-01 -> ocean-2018-01-05",
          "sourceTitle": "一、简答题(每题 10 分,共 50 分)",
          "sourceExcerpt": "1. 写出 Reynolds 数的表达式,说明其物理含义,并简要描述 Reynolds 实验的结论。 2. 稳定转动的圆形转盘内水面如何分布?试用流体力学原理分析其原因。 3. 波浪引起的水质点如何运动?为何近岸传播的波浪都是向岸的? 4. 粗糙管道阻力与哪些物理量有关?试说明 Nikuradse 曲线绘制的是哪些物理量之间的关系曲线,以及关系如何。 5.",
          "status": "locked",
          "reasons": []
        },
        {
          "key": "2018-04",
          "role": "calculation-two-lock",
          "expectedAtomicCount": 2,
          "actualAtomicCount": 2,
          "questionIdCount": 2,
          "itemNumbers": [
            1,
            2
          ],
          "questionIdSpan": "ocean-2018-04-01 -> ocean-2018-04-02",
          "sourceTitle": "四、(20 分)",
          "sourceExcerpt": "三角堰是一种简单又实用的水力测量计。设三角堰孔口角为 2θ,定常流动时上游水面距角尖的水深保持为 h。 1. 试用量纲分析法分析三角堰流量表达式。 2. 利用解析方法计算流量。",
          "status": "locked",
          "reasons": []
        },
        {
          "key": "2018-05",
          "role": "calculation-three-lock",
          "expectedAtomicCount": 3,
          "actualAtomicCount": 3,
          "questionIdCount": 3,
          "itemNumbers": [
            1,
            2,
            3
          ],
          "questionIdSpan": "ocean-2018-05-01 -> ocean-2018-05-03",
          "sourceTitle": "五、(20 分)",
          "sourceExcerpt": "已知理想不可压缩流体二维平面流动的速度势为 φ=(m)/(2π)\\ln r 其中 m 为实常量,设流体密度为 ρ,无穷远处压力为 P∞。求: 1. 此流动的复势; 2. 速度和压力分布; 3. 通过点 A(1,-1) 和点 B(1,1) 连线的流体体积通量。",
          "status": "locked",
          "reasons": []
        },
        {
          "key": "2018-06",
          "role": "calculation-two-lock",
          "expectedAtomicCount": 2,
          "actualAtomicCount": 2,
          "questionIdCount": 2,
          "itemNumbers": [
            1,
            2
          ],
          "questionIdSpan": "ocean-2018-06-01 -> ocean-2018-06-02",
          "sourceTitle": "六、(20 分)",
          "sourceExcerpt": "两无限大平行平板间有两层不同密度、不同粘性的流体。已知下层流体厚度、密度和粘性系数分别为 h₁,ρ₁,μ₁,上层流体厚度、密度和粘性系数分别为 h₂,ρ₂,μ₂。设水平方向无压力差,上平板以速度 V₀ 匀速运动。 1. 写出平板上和两介质界面处的边界条件; 2. 求两板间定常层流流动的速度分布。",
          "status": "locked",
          "reasons": []
        }
      ],
      "status": "locked",
      "reasons": []
    },
    {
      "year": 2020,
      "reason": "2020 has both a five-item concept/short-answer section and a four-item calculation section.",
      "expected": {
        "yearQuestionCount": 17,
        "groupedSectionCount": 5,
        "sectionKeys": [
          "2020-01",
          "2020-02",
          "2020-04",
          "2020-05",
          "2020-06"
        ]
      },
      "actual": {
        "yearQuestionCount": 17,
        "groupedSectionCount": 5,
        "groupedWebQuestionIdCount": 16
      },
      "sections": [
        {
          "key": "2020-01",
          "role": "concept-short-answer-five-lock",
          "expectedAtomicCount": 5,
          "actualAtomicCount": 5,
          "questionIdCount": 5,
          "itemNumbers": [
            1,
            2,
            3,
            4,
            5
          ],
          "questionIdSpan": "ocean-2020-01-01 -> ocean-2020-01-05",
          "sourceTitle": "一、概念与简答题(每题 10 分,共 50 分)",
          "sourceExcerpt": "1. 皮托管测速的原理。 2. 湍流的基本特征。 3. 牛顿流体。 4. 描述流体流动的两种方法,每种方法各举 1 个海洋观测的例子。 5. Rossby 数表征惯性力与地转科氏力之比,写出 Rossby 数的表达式。",
          "status": "locked",
          "reasons": []
        },
        {
          "key": "2020-02",
          "role": "calculation-three-lock",
          "expectedAtomicCount": 3,
          "actualAtomicCount": 3,
          "questionIdCount": 3,
          "itemNumbers": [
            1,
            2,
            3
          ],
          "questionIdSpan": "ocean-2020-02-01 -> ocean-2020-02-03",
          "sourceTitle": "二、(20 分)",
          "sourceExcerpt": "设速度场为 u=t+1、v=1,t=0 时刻流体质点 A 位于原点。求: 1. 质点 A 的迹线方程; 2. t=0 时刻过原点的流线方程; 3. t=1 时刻质点 A 的运动方向。",
          "status": "locked",
          "reasons": []
        },
        {
          "key": "2020-04",
          "role": "calculation-four-lock",
          "expectedAtomicCount": 4,
          "actualAtomicCount": 4,
          "questionIdCount": 4,
          "itemNumbers": [
            1,
            2,
            3,
            4
          ],
          "questionIdSpan": "ocean-2020-04-01 -> ocean-2020-04-04",
          "sourceTitle": "四、(20 分)",
          "sourceExcerpt": "在 xy 坐标系中分别位于 (-a,0)、(a,0)(a>0)两点,强度分别为 Q 和 -Q(Q>0)的点源和点汇,与沿 x 方向速度为 U 的均匀流叠加成一平面流场。求: 1. 流函数与速度势函数; 2. 速度分布式; 3. 流线方程; 4. 画出零流线及部分流线图。",
          "status": "locked",
          "reasons": []
        },
        {
          "key": "2020-05",
          "role": "calculation-two-lock",
          "expectedAtomicCount": 2,
          "actualAtomicCount": 2,
          "questionIdCount": 2,
          "itemNumbers": [
            1,
            2
          ],
          "questionIdSpan": "ocean-2020-05-01 -> ocean-2020-05-02",
          "sourceTitle": "五、(20 分)",
          "sourceExcerpt": "在一定范围内圆柱绕流的后部会发生 Kármán 涡街现象,从圆柱上下交替释放的涡旋频率为 f。若两个流场中采用相同流体,两个圆柱的直径比 d₁/d₂=3,求: 1. 流动与哪些物理量相关?为保证动力相似,速度比 V₁/V₂ 为多少? 2. 释放涡旋的频率比 f₁/f₂ 为多少?",
          "status": "locked",
          "reasons": []
        },
        {
          "key": "2020-06",
          "role": "calculation-two-lock",
          "expectedAtomicCount": 2,
          "actualAtomicCount": 2,
          "questionIdCount": 2,
          "itemNumbers": [
            1,
            2
          ],
          "questionIdSpan": "ocean-2020-06-01 -> ocean-2020-06-02",
          "sourceTitle": "六、(20 分)",
          "sourceExcerpt": "半径分别为 a 和 b(a<b)的两共轴圆管之间充以粘性流体。分别讨论: 1. 内管固定,外管以角速度 ω 绕其轴匀速转动; 2. 内管以角速度 ω₀ 绕其轴匀速转动,外管固定。 分别求流体中速度的分布和作用在管壁上的摩擦力矩。仅考虑流动为定常层流情形。",
          "status": "locked",
          "reasons": []
        }
      ],
      "status": "locked",
      "reasons": []
    },
    {
      "year": 2023,
      "reason": "2023 has one grouped viscous-flow source section and should stay visible in the later-year ledger.",
      "expected": {
        "yearQuestionCount": 11,
        "groupedSectionCount": 1,
        "sectionKeys": [
          "2023-09"
        ]
      },
      "actual": {
        "yearQuestionCount": 11,
        "groupedSectionCount": 1,
        "groupedWebQuestionIdCount": 2
      },
      "sections": [
        {
          "key": "2023-09",
          "role": "viscous-flow-two-lock",
          "expectedAtomicCount": 2,
          "actualAtomicCount": 2,
          "questionIdCount": 2,
          "itemNumbers": [
            1,
            2
          ],
          "questionIdSpan": "ocean-2023-09-01 -> ocean-2023-09-02",
          "sourceTitle": "9. 求解粘性流体沿倾斜平板下泻的流动:",
          "sourceExcerpt": "9. 求解粘性流体沿倾斜平板下泻的流动: - (1)流动速度分布; - (2)上板速度多大时,下板的摩擦应力为 0。",
          "status": "locked",
          "reasons": []
        }
      ],
      "status": "locked",
      "reasons": []
    }
  ],
  "boundary": {
    "localSourceDataOnly": true,
    "pageEdited": false,
    "productionClaim": false,
    "releaseGateClaim": false,
    "answerTextEdited": false,
    "privateVideoClaim": false,
    "allowedWrites": [
      "data/fluid-round333-real-exam-source-cardinality.json",
      "data/fluid-round333-real-exam-source-cardinality.json.gz",
      "docs/round333/real-exam-source-cardinality.md"
    ]
  },
  "checks": [
    {
      "id": "round325-authority-baseline-still-325-325-68-217",
      "pass": true,
      "evidence": {
        "sourceAtomicQuestionCount": 325,
        "webAtomicQuestionCount": 325,
        "groupedSectionCount": 68,
        "groupedWebQuestionIdCount": 217,
        "fourFiveQuestionLockCount": 18,
        "fourFiveQuestionLockedCount": 18,
        "fiveItemShortAnswerLockCount": 5,
        "fiveItemShortAnswerLockedCount": 5,
        "sourceNoMergeFailCount": 0,
        "alignedQuestionCount": 325,
        "round314AlignedQuestionCount": 325,
        "evidenceMatrixAlignedQuestionCount": 325,
        "originalQuestionPdfProvableCount": 325,
        "answerPdfProvableCount": 0,
        "strictAnswerEvidenceOnAligned": 0,
        "evidenceMatrixStrictAnswerEvidenceOnAligned": 0,
        "derivedOrUnprovenAnswerCount": 325,
        "pendingReviewReferenceAnswerCount": 325,
        "improperOriginalAnswerClaimCount": 0,
        "strictOriginalAnswerPdfProofRows": 0,
        "visibleAnswerBoundarySampleRows": 80,
        "derivedOrUnprovenVisibleSampleRows": 80,
        "visibleAnswerBoundarySampleAllDerivedOrUnproven": true,
        "collapseLossIfMerged": 149,
        "passCount": 9,
        "failCount": 0
      }
    },
    {
      "id": "rebuilt-round324-expanded-count-guard-still-passes",
      "pass": true,
      "evidence": {
        "sourceAtomicQuestionCount": 325,
        "webAtomicQuestionCount": 325,
        "groupedSectionCount": 68,
        "groupedWebQuestionIdCount": 217,
        "fourFiveQuestionLockCount": 18,
        "fourFiveQuestionAtomicCount": 77,
        "fiveItemShortAnswerLockCount": 5,
        "fiveItemShortAnswerAtomicCount": 25,
        "criticalYearCount": 9,
        "criticalGroupedSectionCount": 27,
        "failedCriticalStructureCount": 0,
        "passCount": 7,
        "failCount": 0
      }
    },
    {
      "id": "all-68-grouped-sections-remain-217-web-subquestions",
      "pass": true,
      "evidence": {
        "id": "all-grouped-source-sections",
        "label": "全部 grouped / multi-part source rows",
        "expected": {
          "sourceSectionCount": 68,
          "atomicQuestionCount": 217
        },
        "actual": {
          "sourceSectionCount": 68,
          "atomicQuestionCount": 217,
          "lockedSourceSectionCount": 68
        },
        "anchor": {
          "keys": [
            "2000-02",
            "2000-03",
            "2000-06",
            "2000-07",
            "2000-08",
            "2001-06",
            "2002-08",
            "2003-07",
            "2004-01",
            "2004-02",
            "2005-01",
            "2005-02",
            "2005-03",
            "2005-06",
            "2005-07",
            "2005-08",
            "2006-01",
            "2006-02",
            "2006-06",
            "2007-01",
            "2007-02",
            "2007-03",
            "2007-04",
            "2007-07",
            "2007-08",
            "2008-01",
            "2008-03",
            "2010-01",
            "2010-02",
            "2010-05",
            "2011-01",
            "2011-02",
            "2012-01",
            "2012-02",
            "2012-05",
            "2012-06",
            "2012-07",
            "2013-02",
            "2013-03",
            "2014-01",
            "2014-02",
            "2014-03",
            "2015-01",
            "2015-02",
            "2015-04",
            "2015-05",
            "2018-01",
            "2018-04",
            "2018-05",
            "2018-06",
            "2019-01",
            "2019-02",
            "2019-03",
            "2019-04",
            "2019-05",
            "2020-01",
            "2020-02",
            "2020-04",
            "2020-05",
            "2020-06",
            "2021-06",
            "2021-09",
            "2023-09",
            "2024-06",
            "2024-07",
            "2024-08",
            "2024-09",
            "2024-10"
          ],
          "sampleAnchors": [
            {
              "key": "2000-02",
              "questionIdSpan": "ocean-2000-02-01 -> ocean-2000-02-02",
              "sourceTitle": "2(10 分)"
            },
            {
              "key": "2000-03",
              "questionIdSpan": "ocean-2000-03-01 -> ocean-2000-03-02",
              "sourceTitle": "3(10 分)"
            },
            {
              "key": "2000-06",
              "questionIdSpan": "ocean-2000-06-01 -> ocean-2000-06-03",
              "sourceTitle": "6(10 分)"
            },
            {
              "key": "2000-07",
              "questionIdSpan": "ocean-2000-07-01 -> ocean-2000-07-04",
              "sourceTitle": "7(20 分)"
            },
            {
              "key": "2000-08",
              "questionIdSpan": "ocean-2000-08-01 -> ocean-2000-08-02",
              "sourceTitle": "8(10 分)"
            },
            {
              "key": "2001-06",
              "questionIdSpan": "ocean-2001-06-01 -> ocean-2001-06-04",
              "sourceTitle": "6(15 分)"
            },
            {
              "key": "2002-08",
              "questionIdSpan": "ocean-2002-08-01 -> ocean-2002-08-02",
              "sourceTitle": "8(18 分)"
            },
            {
              "key": "2003-07",
              "questionIdSpan": "ocean-2003-07-01 -> ocean-2003-07-03",
              "sourceTitle": "7(30 分)"
            }
          ]
        },
        "status": "locked",
        "failedKeys": []
      }
    },
    {
      "id": "four-five-source-rows-remain-18-locks",
      "pass": true,
      "evidence": {
        "rows": 18,
        "atoms": 77,
        "failedKeys": []
      }
    },
    {
      "id": "five-item-short-answer-keys-are-exact-and-unmerged",
      "pass": true,
      "evidence": {
        "expectedKeys": [
          "2010-02",
          "2015-01",
          "2018-01",
          "2019-01",
          "2020-01"
        ],
        "actualKeys": [
          "2010-02",
          "2015-01",
          "2018-01",
          "2019-01",
          "2020-01"
        ],
        "rows": 5,
        "atoms": 25
      }
    },
    {
      "id": "critical-year-structures-listed-and-locked",
      "pass": true,
      "evidence": [
        {
          "year": 2000,
          "status": "locked",
          "expected": {
            "yearQuestionCount": 16,
            "groupedSectionCount": 5,
            "sectionKeys": [
              "2000-02",
              "2000-03",
              "2000-06",
              "2000-07",
              "2000-08"
            ]
          },
          "actual": {
            "yearQuestionCount": 16,
            "groupedSectionCount": 5,
            "groupedWebQuestionIdCount": 13
          },
          "failedSections": []
        },
        {
          "year": 2001,
          "status": "locked",
          "expected": {
            "yearQuestionCount": 11,
            "groupedSectionCount": 1,
            "sectionKeys": [
              "2001-06"
            ]
          },
          "actual": {
            "yearQuestionCount": 11,
            "groupedSectionCount": 1,
            "groupedWebQuestionIdCount": 4
          },
          "failedSections": []
        },
        {
          "year": 2004,
          "status": "locked",
          "expected": {
            "yearQuestionCount": 18,
            "groupedSectionCount": 2,
            "sectionKeys": [
              "2004-01",
              "2004-02"
            ]
          },
          "actual": {
            "yearQuestionCount": 18,
            "groupedSectionCount": 2,
            "groupedWebQuestionIdCount": 14
          },
          "failedSections": []
        },
        {
          "year": 2008,
          "status": "locked",
          "expected": {
            "yearQuestionCount": 9,
            "groupedSectionCount": 2,
            "sectionKeys": [
              "2008-01",
              "2008-03"
            ]
          },
          "actual": {
            "yearQuestionCount": 9,
            "groupedSectionCount": 2,
            "groupedWebQuestionIdCount": 7
          },
          "failedSections": []
        },
        {
          "year": 2010,
          "status": "locked",
          "expected": {
            "yearQuestionCount": 21,
            "groupedSectionCount": 3,
            "sectionKeys": [
              "2010-01",
              "2010-02",
              "2010-05"
            ]
          },
          "actual": {
            "yearQuestionCount": 21,
            "groupedSectionCount": 3,
            "groupedWebQuestionIdCount": 18
          },
          "failedSections": []
        },
        {
          "year": 2015,
          "status": "locked",
          "expected": {
            "yearQuestionCount": 14,
            "groupedSectionCount": 4,
            "sectionKeys": [
              "2015-01",
              "2015-02",
              "2015-04",
              "2015-05"
            ]
          },
          "actual": {
            "yearQuestionCount": 14,
            "groupedSectionCount": 4,
            "groupedWebQuestionIdCount": 13
          },
          "failedSections": []
        },
        {
          "year": 2018,
          "status": "locked",
          "expected": {
            "yearQuestionCount": 14,
            "groupedSectionCount": 4,
            "sectionKeys": [
              "2018-01",
              "2018-04",
              "2018-05",
              "2018-06"
            ]
          },
          "actual": {
            "yearQuestionCount": 14,
            "groupedSectionCount": 4,
            "groupedWebQuestionIdCount": 12
          },
          "failedSections": []
        },
        {
          "year": 2020,
          "status": "locked",
          "expected": {
            "yearQuestionCount": 17,
            "groupedSectionCount": 5,
            "sectionKeys": [
              "2020-01",
              "2020-02",
              "2020-04",
              "2020-05",
              "2020-06"
            ]
          },
          "actual": {
            "yearQuestionCount": 17,
            "groupedSectionCount": 5,
            "groupedWebQuestionIdCount": 16
          },
          "failedSections": []
        },
        {
          "year": 2023,
          "status": "locked",
          "expected": {
            "yearQuestionCount": 11,
            "groupedSectionCount": 1,
            "sectionKeys": [
              "2023-09"
            ]
          },
          "actual": {
            "yearQuestionCount": 11,
            "groupedSectionCount": 1,
            "groupedWebQuestionIdCount": 2
          },
          "failedSections": []
        }
      ]
    },
    {
      "id": "round333-scope-is-local-data-doc-only",
      "pass": true,
      "evidence": {
        "localSourceDataOnly": true,
        "pageEdited": false,
        "productionClaim": false,
        "releaseGateClaim": false,
        "answerTextEdited": false,
        "privateVideoClaim": false,
        "allowedWrites": [
          "data/fluid-round333-real-exam-source-cardinality.json",
          "data/fluid-round333-real-exam-source-cardinality.json.gz",
          "docs/round333/real-exam-source-cardinality.md"
        ]
      }
    }
  ],
  "failures": [],
  "sourceSignature": {
    "inputsSha256": "3fbae018845621c1275200379d99fe3c4742e41b477fbfe5468e3a23650adb9f"
  }
}
